{"default":{"lang":"en","nita150":{"1":"","2":"","3":"","4":"","5":"","6":"","7":"","8":"","9":"","10":"","11":"","12":"","13":"","14":"","15":"","16":"","17":"","18":"","19":"","20":"","21":"","22":"","23":"","24":"","25":"","26":"","27":"","28":"","29":"","30":"","31":"","32":"","33":"","34":"","35":"","36":"","37":"","38":"","39":"","40":"","41":"","42":"","43":"","44":"","45":"","46":"","47":"","48":"","49":"","50":"","51":"","52":"","53":"","54":"","55":"","56":"","57":"","58":"","59":"","60":"","61":"","62":"","63":"","64":"","65":"","66":"","67":"","68":"","69":"","70":"","71":"","72":"","73":"","74":"","75":"","76":"","77":"","78":"","79":"","80":"","81":"","82":"","83":"","84":"","85":"","86":"","87":"","88":"","89":"","90":"","91":"","92":"","93":"","94":"","95":"","96":""},"nita200":{"1":"","2":"","3":"","4":"","5":"","6":"","7":"","8":"","9":"","10":"","11":"","12":"","13":"","14":"","15":"","16":"","17":"","18":"","19":"","20":"","21":"","22":"","23":"","24":"","25":"","26":"","27":"","28":"","29":"","30":"","31":"","32":"","33":"","34":"","35":"","36":"","37":"","38":"","39":"","40":"","41":"","42":"","43":"","44":"","45":"","46":"","47":"","48":"","49":"","50":"","51":"","52":"","53":"","54":"","55":"","56":"","57":"","58":"","59":"","60":"","61":"","62":"","63":"","64":"","65":"","66":"","67":"","68":"","69":"","70":"","71":"","72":"","73":"","74":"","75":"","76":"","77":"","78":"","79":"","80":"","81":"","82":"","83":"","84":"","85":"","86":"","87":"","88":"","89":"","90":"","91":"","92":"","93":"","94":"","95":"","96":""},"ta150":{"1":"","2":"","3":"","4":"","5":"","6":"","7":"","8":"","9":"","10":"","11":"","12":"","13":"","14":"","15":"","16":"","17":"","18":"","19":"","20":"","21":"","22":"","23":"","24":"","25":"","26":"","27":"","28":"","29":"","30":"","31":"","32":"","33":"","34":"","35":"","36":"","37":"","38":"","39":"","40":"","41":"","42":"","43":"","44":"","45":"","46":"","47":"","48":"","49":"","50":"","51":"","52":"","53":"","54":"","55":"","56":"","57":"","58":"","59":"","60":"","61":"","62":"","63":"","64":"","65":"","66":"","67":"","68":"","69":"","70":"","71":"","72":"","73":"","74":"","75":"","76":"","77":"","78":"","79":"","80":"","81":"","82":"","83":"","84":"","85":"","86":"","87":"","88":"","89":"","90":"","91":"","92":"","93":"","94":"","95":"","96":""},"ta200":{"1":"","2":"","3":"","4":"","5":"","6":"","7":"","8":"","9":"","10":"","11":"","12":"","13":"","14":"","15":"","16":"","17":"","18":"","19":"","20":"","21":"","22":"","23":"","24":"","25":"","26":"","27":"","28":"","29":"","30":"","31":"","32":"","33":"","34":"","35":"","36":"","37":"","38":"","39":"","40":"","41":"","42":"","43":"","44":"","45":"","46":"","47":"","48":"","49":"","50":"","51":"","52":"","53":"","54":"","55":"","56":"","57":"","58":"","59":"","60":"","61":"","62":"","63":"","64":"","65":"","66":"","67":"","68":"","69":"","70":"","71":"","72":"","73":"","74":"","75":"","76":"","77":"","78":"","79":"","80":"","81":"","82":"","83":"","84":"","85":"","86":"","87":"","88":"","89":"","90":"","91":"","92":"","93":"","94":"","95":"","96":""}},"tracks":{"ja":["マリオカートスタジアム","ウォーターパーク","スイーツキャニオン","ドッスンいせき","マリオサーキット","キノピオハーバー","ねじれマンション","ヘイホーこうざん","サンシャインくうこう","ドルフィンみさき","エレクトロドリーム","ワリオスノーマウンテン","スカイガーデン","ホネホネさばく","クッパキャッスル","レインボーロード","Wii モーモーカントリー","GBA マリオサーキット","DS プクプクビーチ","N64 キノピオハイウェイ","GC カラカラさばく","SFC ドーナツへいや3","N64 ピーチサーキット","3DS DKジャングル","DS ワリオスタジアム","GC シャーベットランド","3DS ミュージックパーク","N64 ヨッシーバレー","DS チクタクロック","3DS パックンスライダー","Wii グラグラかざん","N64 レインボーロード","GC ヨッシーサーキット","エキサイトバイク","ドラゴンロード","ミュートシティ","Wii ワリオこうざん","SFC レインボーロード","ツルツルツイスター","ハイラルサーキット","GC ベビィパーク","GBA チーズランド","ネイチャーロード","どうぶつの森","3DS ネオクッパシティ","GBA リボンロード","リンリンメトロ","ビッグブルー","Tour パリプロムナード","3DS キノピオサーキット","N64 チョコマウンテン","Wii ココナッツモール","Tour トーキョースクランブル","DS キノコリッジウェイ","GBA スカイガーデン","ニンニンドージョー","Tour ニューヨークドリーム","SFC マリオサーキット 3","N64 カラカラさばく","DS ワルイージピンボール","Tour シドニーサンシャイン","GBA スノーランド","Wii キノコキャニオン","アイスビルディング","Tour ロンドンアベニュー","GBA テレサレイク","3DS ロックロックマウンテン","Wii メイプルツリーハウス","Tour ベルリンシュトラーセ","DS ピーチガーデン","メリーメリーマウンテン","3DS レインボーロード","Tour アムステルダムブルーム","GBA リバーサイドパーク","Wii DKスノーボードクロス","ヨッシーアイランド","Tour バンコクラッシュ","DS マリオサーキット","GC ワルイージスタジアム","Tour シンガポールスプラッシュ","Tour アテネポリス","GC デイジークルーザー","Wii ムーンリッジ&ハイウェイ","シャボンロード","Tour ロサンゼルスコースト","GBA サンセットこうや","Wii ノコノコみさき","Tour バンクーバーバレー","Tour ローマアバンティ","GC DKマウンテン","Wii デイジーサーキット","パックンしんでん","Tour マドリードグランデ","3DS ロゼッタプラネット","SFC クッパじょう 3","Wii レインボーロード"],"en":["Mario Kart Stadium","Water Park","Sweet Sweet Canyon","Thwomp Ruins","Mario Circuit","Toad Harbor","Twisted Mansion","Shy Guy Falls","Sunshine Airport","Dolphin Shoals","Electrodrome","Mount Wario","Cloudtop Cruise","Bone-Dry Dunes","Bowser's Castle","Rainbow Road","Wii Moo Moo Meadows","GBA Mario Circuit","DS Cheep Cheep Beach","N64 Toad's Turnpike","GC Dry Dry Desert","SFC Donut Plains 3","N64 Royal Raceway","3DS DK Jungle","DS Wario Stadium","GC Sherbet Land","3DS Music Park","N64 Yoshi Valley","DS Tick-Tock Clock","3DS Pilanha Plant Slide","Wii Grumble Volcano","N64 Rainbow Road","GC Yoshi Circuit","Excitebike Arena","Dragon Driftway","Mute City","Wii Wario's Gold Mine","SFC Rainbow Road","Ice Ice Outpost","Hyrule Circuit","GC Baby Park","GBA Cheese Land","Wild Woods","Animal Crossing","3DS Neo Bowser City","GBA Ribbon Road","Super Bell Subway","Big Blue","Tour Paris Promenade","3DS Toad Circuit","N64 Choco Mountain","Wii Coconut Mall","Tour Tokyo Blur","DS Shroom Ridge","GBA Sky Garden","Ninja Hideaway","Tour New York Minute","SFC Mario Circuit 3","N64 Kalimali Desert","DS Waluigi Pinball","Tour Sydney Sprint","GBA Snow Land","Wii Mushroom Gorge","Sky-high Sundae","Tour London Loop","GBA Boo Lake","3DS Rock Rock Mountain","Wii Maple Treeway","Tour Berlin Byways","DS Peach Gardens","Merry Mountain","3DS Rainbow Road","Tour Amsterdam Drift","GBA Riverside Park","Wii DK Summit","Yoshi's Island","Tour Bangkok Rush","Ds Mario Circuit","GC Waluigi Stadium","Tour Singapore Speedway","Tour Athens Dash","GC Daisy Cruiser","Wii Moonview Highway","Squeaky Clean Sprint","Tour Los Angeles Laps","GBA Sunset Wilds","Wii Koopa Cape","Tour Vancouver Velocity","Tour Rome Avanti","GC DK Mountain","Wii Daisy Circuit","Tour Pilanha Plant Cove","Tour Madrid Drive","3DS Rosalina's Ice World","SFC Bowser Castle 3","Wii Rainbow Road"],"raw":{"1":"","2":"","3":"","4":"","5":"","6":"","7":"","8":"","9":"","10":"","11":"","12":"","13":"","14":"","15":"","16":"","17":"","18":"","19":"","20":"","21":"","22":"","23":"","24":"","25":"","26":"","27":"","28":"","29":"","30":"","31":"","32":"","33":"","34":"","35":"","36":"","37":"","38":"","39":"","40":"","41":"","42":"","43":"","44":"","45":"","46":"","47":"","48":"","49":"","50":"","51":"","52":"","53":"","54":"","55":"","56":"","57":"","58":"","59":"","60":"","61":"","62":"","63":"","64":"","65":"","66":"","67":"","68":"","69":"","70":"","71":"","72":"","73":"","74":"","75":"","76":"","77":"","78":"","79":"","80":"","81":"","82":"","83":"","84":"","85":"","86":"","87":"","88":"","89":"","90":"","91":"","92":"","93":"","94":"","95":"","96":""}},"messages":{"en":{"notregistered":"You haven't registered this track's time yet.","illegalformat":"Invalid time format.","tracknotexists":"Track doesn't exist.","sameasbest":"Time is the same as the best time.","fasterthanwr":"Your time is faster than current WR. \nPlease submit your WR on https://mkwrs.com/mk8dx/ Current WR: ","difference":"Difference","yourtime":"Your time","slowerthanbest":"Your time is slower than your best time. Your best: "},"ja":{"notregistered":"このトラックでのタイムが未申請です。","illegalformat":"タイムのフォーマットが無効です。","tracknotexists":"トラックが存在しません。","sameasbest":"ベストタイムと同じです。","fasterthanwr":"あなたのタイムは現在のWRより速いです。\nhttps://mkwrs.com/mk8dx/ であなたのタイムを申請してください。 WR: ","difference":"差","yourtime":"あなたのタイム","slowerthanbest":"あなたのタイムはあなたのベストタイムより遅いです。ベスト: "}},"wr":{"nita150":{"1":[99332,"かたゆ","https://www.google.com/url?q=https://youtu.be/uTPigvK0RBU?si%3D1VrBQ76dL4VPjO6l&sa=D&source=editors&ust=1740622331081079&usg=AOvVaw1B_fvAV_ONpY4vdbj1SgPo"],"2":[101575,"Army","https://www.google.com/url?q=https://youtu.be/ekGa6RD0N2c?si%3DLBjihd5-stidW8iW&sa=D&source=editors&ust=1740622331081382&usg=AOvVaw3SMJHi6UpdY5hLRS3XwWv1"],"3":[113640,"ちくちくぴろんぴろん","https://www.google.com/url?q=https://www.youtube.com/watch?v%3Dkum3XyMnRqE&sa=D&source=editors&ust=1740622331081794&usg=AOvVaw14G0ume1Cy1P0e8SKTyADf"],"4":[113139,"2ucker","https://www.google.com/url?q=https://youtu.be/ti_S4T6oeTg?si%3DxAMBnYzdeE3kvUZN&sa=D&source=editors&ust=1740622331082063&usg=AOvVaw0It2ePdEe4oKs0sjfnKNAb"],"5":[107911,"Panda","https://www.google.com/url?q=https://youtu.be/GtzbC25DPKg?si%3DAFxXQ0NsX6MFkc-p&sa=D&source=editors&ust=1740622331104826&usg=AOvVaw07tkrmzcR52yGvIgS36QfL"],"6":[124610,"chigerungo","https://www.google.com/url?q=https://youtu.be/Z5QIjnNkWMU&sa=D&source=editors&ust=1740622331105208&usg=AOvVaw0HeMQ1WdhM8pxjrN-0Wqkm"],"7":[118973,"1000be","https://www.google.com/url?q=https://youtu.be/AG5jb0HoNmk?si%3D1VvLBc132YKwWMAm&sa=D&source=editors&ust=1740622331105621&usg=AOvVaw3RL1jK5dAOXqDCRiacSJav"],"8":[117956,"Isaac","https://www.google.com/url?q=https://www.youtube.com/watch?v%3DbYNQNHqjs_c&sa=D&source=editors&ust=1740622331105757&usg=AOvVaw2VxF8g4kag7gimSC4Lu-H_"],"9":[120357,"らくbot","https://www.google.com/url?q=https://youtu.be/wqJecs3OU6M?feature%3Dshared&sa=D&source=editors&ust=1740622331133448&usg=AOvVaw1cPD2ei5BxnQIb7WurH51b"],"10":[116975,"piyopotechi","https://www.google.com/url?q=https://youtu.be/3D4awky_PKk&sa=D&source=editors&ust=1740622331133789&usg=AOvVaw2rVC6pbUPxj4yRvCsG7DXp"],"11":[120429,"らくbot","https://www.google.com/url?q=https://youtu.be/umy1WwRb28g?feature%3Dshared&sa=D&source=editors&ust=1740622331134097&usg=AOvVaw1Txqk_AHbHHA-1EF0uFD_d"],"12":[103373,"ちくちくぴろんぴろん","https://www.google.com/url?q=https://www.youtube.com/watch?v%3D0XYb1wXPGr4&sa=D&source=editors&ust=1740622331134540&usg=AOvVaw3_b8BNiCXzHphGGMI7yOzo"],"13":[121968,"にら","https://www.google.com/url?q=https://youtu.be/UbOk9prR4kE&sa=D&source=editors&ust=1740622331157724&usg=AOvVaw14ujQ4nW7VCepW08YWCF8w"],"14":[111413,"ぷらぷら","https://www.google.com/url?q=https://youtu.be/431YVpaHOao?si%3D12yb2Wl6KVmcTRuj&sa=D&source=editors&ust=1740622331158049&usg=AOvVaw0yHfbSIpptqqCViJNinY28"],"15":[122451,"methanol","https://www.google.com/url?q=https://youtu.be/Zm34Y3sdPWs&sa=D&source=editors&ust=1740622331158641&usg=AOvVaw1BIfgUkU6BtU9oaNqaqEgU"],"16":[121524,"¥146","https://www.google.com/url?q=https://youtu.be/Equf18lDPRo?si%3Dsw16ohf4I69i8m5N&sa=D&source=editors&ust=1740622331158786&usg=AOvVaw02VazUMWdUigCC07X-5UhD"],"17":[86780,"Panda","https://www.google.com/url?q=https://youtu.be/g7bVEkfHZmc?si%3D9IvV5iN6AntQwKZH&sa=D&source=editors&ust=1740622331182494&usg=AOvVaw3fBrf2bsmR-_kmC8VACwA1"],"18":[87146,"Panda","https://www.google.com/url?q=https://www.youtube.com/watch?v%3DBzB5PrrhhTE&sa=D&source=editors&ust=1740622331182835&usg=AOvVaw3ytcjkTF-7l_R3wBSt4IWh"],"19":[109335,"nire","https://www.google.com/url?q=https://youtu.be/JitQKJc2giU?si%3DYqp0Ug2niGQ7Tgoe&sa=D&source=editors&ust=1740622331183128&usg=AOvVaw2h_5Bsr9lLRxGgwlHCjQPq"],"20":[107671,"ain","https://www.google.com/url?q=https://youtu.be/86O09cE4-ls?si%3DbhtSN2hzquaeKrnX&sa=D&source=editors&ust=1740622331183426&usg=AOvVaw07lYfJKZ57FTDPLBWdEKD_"],"21":[120486,"Panda","https://www.google.com/url?q=https://www.youtube.com/watch?v%3Dzel3p5VK1jA&sa=D&source=editors&ust=1740622331205805&usg=AOvVaw13lIn-jWJu83JeUAogum0B"],"22":[77180,"Pii","https://www.google.com/url?q=https://www.youtube.com/watch?v%3Dncj3YGdrD_Y&sa=D&source=editors&ust=1740622331206186&usg=AOvVaw0_HgBYuBm-cZwyYjULymyZ"],"23":[118752,"らくbot","https://www.google.com/url?q=https://youtu.be/eb-yJ5vDZf8?feature%3Dshared&sa=D&source=editors&ust=1740622331206515&usg=AOvVaw1oh8fNfBsooYKiTH0ABDGa"],"24":[123342,"Alberto","https://www.google.com/url?q=https://www.youtube.com/watch?v%3DzpyzZRW6oTk&sa=D&source=editors&ust=1740622331206831&usg=AOvVaw3mxM07rR0bwknT22uqclZD"],"25":[112687,"aybzq","https://www.google.com/url?q=https://youtu.be/2sxgKS8D5qQ?si%3D94gQJQF6_bje3mcx&sa=D&source=editors&ust=1740622331232032&usg=AOvVaw2zYteLZVgROBbYGfSM1v6E"],"26":[109804,"Mana","https://www.google.com/url?q=https://youtu.be/PueVnqjqSVs?si%3DpbA6BCL59Awpayyw&sa=D&source=editors&ust=1740622331232434&usg=AOvVaw0Y-Y2Vpjd37xYtPjPogX_-"],"27":[112021,"ちくちくぴろんぴろん","https://www.google.com/url?q=https://x.com/chikupilon_mk/status/1864282328950005973&sa=D&source=editors&ust=1740622331232848&usg=AOvVaw0TlD5KGVSigx9n6cop0zmL"],"28":[122579,"Panda","https://www.google.com/url?q=https://youtu.be/rk4_FAUauEc?si%3Dw4U3bYednyINLu3s&sa=D&source=editors&ust=1740622331233047&usg=AOvVaw1keXqkmOr7WcbriO0s8JrG"],"29":[103377,"すとーぶ","https://www.google.com/url?q=https://www.youtube.com/watch?v%3D4_R8Wymo_sU&sa=D&source=editors&ust=1740622331259419&usg=AOvVaw1R-9vBKiXRTEwVuvVWThCy"],"30":[123211,"Fuga","https://www.google.com/url?q=https://youtu.be/BSoCORqLH1s?si%3DBQCmOowf70Sd8S8s&sa=D&source=editors&ust=1740622331259644&usg=AOvVaw32OGHmNzu_F2DAd_wlGmCF"],"31":[114936,"quartz","https://www.google.com/url?q=https://youtu.be/MnhtY7vyZvw?si%3DtqaOEq6dvHfWot6e&sa=D&source=editors&ust=1740622331259961&usg=AOvVaw0C7e80QkxK7WdKmFdi_vzn"],"32":[80975,"ぼあさん","https://www.google.com/url?q=https://youtu.be/MSYxRa7ThWY?si%3DQV-2oTdIyC1zy-Lr&sa=D&source=editors&ust=1740622331260236&usg=AOvVaw3w-Dvx9WBkqyeRKBkvVPa6"],"33":[105992,"calna","https://www.google.com/url?q=https://youtu.be/DUV4PQ55gPc?si%3D_wzroJqVuMNLkb74&sa=D&source=editors&ust=1740622331280738&usg=AOvVaw260aRNyrG42a1ZRDo6MQru"],"34":[102747,"Yoshiyoshi","https://www.google.com/url?q=https://youtu.be/rOPobkqoFag?si%3D-7-y9SkkFXGZvHnF&sa=D&source=editors&ust=1740622331280903&usg=AOvVaw0P2klhzB_VsMjSEh8ZniMi"],"35":[104976,"Mana","https://www.google.com/url?q=https://youtu.be/683C5dJT0kk?si%3DUxL6XcyL_VjfghGF&sa=D&source=editors&ust=1740622331281304&usg=AOvVaw2H9_Nq2tZ4wOVGPZy7DWZl"],"36":[115892,"ふじほたる","https://www.google.com/url?q=https://youtu.be/vQLKOFuChxI&sa=D&source=editors&ust=1740622331281587&usg=AOvVaw3XEMrTIF_z7jeSpAOecwrf"],"37":[123551,"Panda","https://www.google.com/url?q=https://www.youtube.com/watch?v%3DKQtMUnHG9jg&sa=D&source=editors&ust=1740622331306678&usg=AOvVaw2bKEerkr5B01-7pBOVokCH"],"38":[88456,"Jotrix","https://www.google.com/url?q=https://youtu.be/eYRy1iKpxSg&sa=D&source=editors&ust=1740622331306981&usg=AOvVaw10oroiOvCWWHWIffGcWfmr"],"39":[107409,"とれいん。","https://www.google.com/url?q=https://www.youtube.com/watch?v%3DKIOwI-HfrXE&sa=D&source=editors&ust=1740622331307352&usg=AOvVaw0UnwC5nA8qrMtFfXuHBKvF"],"40":[110981,"究極攻略ch","https://www.google.com/url?q=https://www.youtube.com/watch?v%3DDLpuUC_fEQ8&sa=D&source=editors&ust=1740622331307496&usg=AOvVaw2gcoxa0wMewS9fkoJwjFQj"],"41":[64257,"なきりおと","https://www.google.com/url?q=https://youtu.be/0hGaJeMKSQY?si%3D6snGYKPyGZbbIeuK&sa=D&source=editors&ust=1740622331332936&usg=AOvVaw2py7aB0YQHZKNyLKldTGTW"],"42":[108094,"Panda","https://www.google.com/url?q=https://www.youtube.com/watch?v%3DI4w6Z5CmsO8&sa=D&source=editors&ust=1740622331333401&usg=AOvVaw0WdyzfTno_9bW-1qam_egd"],"43":[107675,"ちくちくぴろんぴろん","https://www.google.com/url?q=https://m.youtube.com/watch?v%3Dd3iZOK31GUc&sa=D&source=editors&ust=1740622331334076&usg=AOvVaw2KOEkBkEZ0swLFfbZHbAEJ"],"44":[100935,"ziline","https://www.google.com/url?q=https://youtu.be/iDtpYRvgnCo?si%3D5_iQhWQB35H_FoKX&sa=D&source=editors&ust=1740622331334478&usg=AOvVaw3EP_iHptJXc2NI6DB6J-W6"],"45":[106187,"Panda","https://www.google.com/url?q=https://www.youtube.com/watch?v%3DJ2JJ2p6qjy8&sa=D&source=editors&ust=1740622331362173&usg=AOvVaw2BM_GqRaPIS3XGs6lxIsuZ"],"46":[110701,"¥146","https://www.google.com/url?q=https://youtu.be/J029EQKelFU?si%3Dcleo5lmtfYWU_bEP&sa=D&source=editors&ust=1740622331362476&usg=AOvVaw0gWq5TRE_I421jCFFqWUAQ"],"47":[104196,"sugar","https://www.google.com/url?q=https://youtu.be/aPxNG5eH0HU&sa=D&source=editors&ust=1740622331362908&usg=AOvVaw3BocOLQWLotSjzNWAklNvj"],"48":[86263,"shi","https://www.google.com/url?q=https://twitter.com/shihomk8dx/status/1825813114899804300?t%3D5dUm1EPLs7-YBMUMqAUNTQ%26s%3D19&sa=D&source=editors&ust=1740622331363036&usg=AOvVaw1smNMlM0faFEHTJIPwJW_8"],"49":[111756,"ぐち","https://www.google.com/url?q=https://www.youtube.com/watch?v%3DKWsuSpC-VMA&sa=D&source=editors&ust=1740622331386355&usg=AOvVaw0Bc4aWK4O6Be-pxNygalcU"],"50":[84337,"ぼあさん","https://www.google.com/url?q=https://vt.tiktok.com/ZSNTHB93V/&sa=D&source=editors&ust=1740622331386621&usg=AOvVaw2azEMCQWi7Fwt7W9xaDYss"],"51":[113834,"ラス","https://www.google.com/url?q=https://youtu.be/_WdGba1EAJ0?si%3DUBpHd6SKPzE5BWg4&sa=D&source=editors&ust=1740622331386910&usg=AOvVaw2xQPYDS6bvMH78zstZoHm1"],"52":[103756,"ichigo","https://www.google.com/url?q=https://youtu.be/IeCCtzLnukk?si%3D0RaJ0WveAMA09TLl&sa=D&source=editors&ust=1740622331387146&usg=AOvVaw0hQ9rOs361aVkvvgSGaiJj"],"53":[87486,"ぼあさん","https://www.google.com/url?q=https://youtu.be/M4eGjW_cUnk?si%3DMeNu13ezwwQ7AZ1l&sa=D&source=editors&ust=1740622331409006&usg=AOvVaw0SKLmDUuhkpQr5QffVe3GT"],"54":[107922,"ましゅ","https://www.google.com/url?q=https://youtu.be/4stwmH-wxpg?si%3DJiDhbLcePw182-1Z&sa=D&source=editors&ust=1740622331409386&usg=AOvVaw3Gml5g1_Mtlr4kn5qkNFVG"],"55":[89996,"Wish","https://www.google.com/url?q=https://youtu.be/pd17P_HObfo?feature%3Dshared&sa=D&source=editors&ust=1740622331409727&usg=AOvVaw2CTW2k9e2TMbqWZ-DQD1fu"],"56":[113949,"なきりおと","https://www.google.com/url?q=https://youtu.be/2rAdExPtt1w?si%3DdLU0EoDjoNU2Z2Z4&sa=D&source=editors&ust=1740622331410015&usg=AOvVaw3h4EnLmN6RoTXghlXMUlce"],"57":[84597,"Panda","https://www.google.com/url?q=https://youtu.be/S2h54_Sl9jM?si%3DM5kheBh-1jpRdaTr&sa=D&source=editors&ust=1740622331436370&usg=AOvVaw3bV8cxUcJinm5IUWYwrz0S"],"58":[95794,"ラス","https://www.google.com/url?q=https://youtu.be/TWnbD54vew8?si%3Der35cWckglMzMKM2&sa=D&source=editors&ust=1740622331436800&usg=AOvVaw0f9pfNNgXFkPyppCuE1ly4"],"59":[93381,"まめ","https://www.google.com/url?q=https://youtu.be/AhXqDJZ0IWg?si%3DicTtDLkGFKEXOaZl&sa=D&source=editors&ust=1740622331437396&usg=AOvVaw3Ven5yT9uZCr7YFsfHiiwX"],"60":[140341,"らくbot","https://www.google.com/url?q=https://youtu.be/r6y1qY0Z-F0?feature%3Dshared&sa=D&source=editors&ust=1740622331437597&usg=AOvVaw25WT6qqj9RmM-afXsJwZ_o"],"61":[122827,"Panda","https://www.google.com/url?q=https://youtu.be/pSkfnteexcs?si%3DUKygTIw3FkMaw4jt&sa=D&source=editors&ust=1740622331461313&usg=AOvVaw3VRl-zzSzL4FyHvO_AMHgm"],"62":[96247,"Panda","https://www.google.com/url?q=https://youtu.be/WJAnQ1WUZBI?si%3D5kipTEfeonUY4bFk&sa=D&source=editors&ust=1740622331461713&usg=AOvVaw2XDGq2Cwb2xvHmchuh6zgm"],"63":[95837,"fairy","https://www.google.com/url?q=https://www.youtube.com/watch?v%3DOnyzC_FlWAA&sa=D&source=editors&ust=1740622331462095&usg=AOvVaw26hFvlhmUkFmHUeppn2OFv"],"64":[115908,"ゆうき","https://www.google.com/url?q=https://youtu.be/dUxlc2LZ0x0?si%3D4d5dQnDeltu9oFbn&sa=D&source=editors&ust=1740622331462703&usg=AOvVaw1z_uway2iIDMnQT9XzZIpw"],"65":[131538,"Gra","https://www.google.com/url?q=https://youtu.be/hV7ZbXwOfCE?si%3D1dAA7KzN6mhQLspL&sa=D&source=editors&ust=1740622331484398&usg=AOvVaw2F6Wx44iFOwwi5ayzbrKJ6"],"66":[83170,"すらりん","https://www.google.com/url?q=https://youtu.be/LRBOa36WH5o&sa=D&source=editors&ust=1740622331484667&usg=AOvVaw0Nh5GfyMt_czbRfO92Weiq"],"67":[135863,"らくbot","https://www.google.com/url?q=https://youtu.be/ISeXZIc4vpk?feature%3Dshared&sa=D&source=editors&ust=1740622331484819&usg=AOvVaw04E3Yc-wxzq2pJ2fUvN42e"],"68":[145512,"aybzq","https://www.google.com/url?q=https://youtu.be/hssGI2m_AOc?si%3DYUsuY1iQ_kGj89ff&sa=D&source=editors&ust=1740622331485122&usg=AOvVaw0ziaXlfNOw5QqhAYYaDakq"],"69":[119394,"らくbot","https://www.google.com/url?q=https://youtu.be/4EqrJRRWkTQ?feature%3Dshared&sa=D&source=editors&ust=1740622331509832&usg=AOvVaw2gRScHgSVbSlFbONoro7z6"],"70":[127733,"ラス","https://www.google.com/url?q=https://youtu.be/SaLiBuQ41os?si%3DJDZYiBkrRFoW_qBV&sa=D&source=editors&ust=1740622331510117&usg=AOvVaw0BM_Sso-9Gjnl6qPNG7iFN"],"71":[115717,"かりま","https://www.google.com/url?q=https://youtu.be/SsmGqnqbXuE?si%3DaI39XdMy9Rzg9Q_i&sa=D&source=editors&ust=1740622331510539&usg=AOvVaw3CE0ihmDSiMdyA5kAwhfLH"],"72":[98705,"ラス","https://www.google.com/url?q=https://youtu.be/y1eKyKlghB0?si%3D1HrienBUNKvXod6F&sa=D&source=editors&ust=1740622331510704&usg=AOvVaw2bfAY--alomAaPoMyrblUs"],"73":[97671,"Panda","https://www.google.com/url?q=https://youtu.be/9K5qu3IYSOY?si%3DEhf9C9m9qlWjkXKZ&sa=D&source=editors&ust=1740622331532438&usg=AOvVaw2aD-zEsVnDHfnDT-ZV8aMJ"],"74":[91452,"Luckyo","https://www.google.com/url?q=https://www.youtube.com/watch?v%3Dt_fLFxc4ISg&sa=D&source=editors&ust=1740622331532984&usg=AOvVaw3O6X-fXULc9fiJmIckeZxA"],"75":[117358,"YUTM","https://www.google.com/url?q=https://youtu.be/PnfpKXoXxyE?si%3DVF-hMHRlbOnmhAsk&sa=D&source=editors&ust=1740622331533119&usg=AOvVaw3fC0VVsvvN076_l6LK4DGp"],"76":[120250,"Kazuya","https://www.google.com/url?q=https://youtu.be/5PNeVm30QsE?si%3D8VhyxFVB2oT2a3Q1&sa=D&source=editors&ust=1740622331533510&usg=AOvVaw3sU_mk3DOBFRnp8RrmrrdA"],"77":[104302,"¥146","https://www.google.com/url?q=https://youtu.be/CVacmUqEvLU?si%3DQyFhYDX59fBm_6H5&sa=D&source=editors&ust=1740622331563458&usg=AOvVaw1y-0HHGbyY5zB3gkdAJnOk"],"78":[101878,"Hoshiku","https://www.google.com/url?q=https://youtu.be/QN0oK_u2ETk?si%3Dc9kk9I1LFTd-fYNg&sa=D&source=editors&ust=1740622331564001&usg=AOvVaw2f6Whoe6eWEZmsTg44r9r-"],"79":[116748,"y","https://www.google.com/url?q=https://youtu.be/feE4G8YaUg8?si%3D0FsHwfRMsy-GreeA&sa=D&source=editors&ust=1740622331564687&usg=AOvVaw3YmST1b3lJoWLpbjaDnC-W"],"80":[117759,"ぐち","https://www.google.com/url?q=https://www.youtube.com/watch?v%3DHSYCPxmnIiA&sa=D&source=editors&ust=1740622331564923&usg=AOvVaw2ZxFCHLn-X2iRR3sRehajT"],"81":[100813,"ぐち","https://www.google.com/url?q=https://www.youtube.com/watch?v%3DzqVVRQ37bxc&sa=D&source=editors&ust=1740622331599317&usg=AOvVaw2Tcd95F4ZhGpv7euioZOqz"],"82":[95686,"Army","https://www.google.com/url?q=https://youtu.be/_-HypEbIVyI&sa=D&source=editors&ust=1740622331599909&usg=AOvVaw0PeJn6g144F0SUUIKGHUS4"],"83":[104332,"Lee","https://www.google.com/url?q=https://youtu.be/KfgZp1JfTPE&sa=D&source=editors&ust=1740622331600443&usg=AOvVaw11tpeWQNVGiBW2H50dZa2h"],"84":[123403,"ちずば","https://www.google.com/url?q=https://youtu.be/dx1JVopx0Pk?si%3DS6QZDWXXaSgSG4_o&sa=D&source=editors&ust=1740622331600922&usg=AOvVaw1tSgsbgVWORYgBjtCv41ng"],"85":[109170,"Panda","https://www.google.com/url?q=https://youtu.be/gTbOaUJhPYg?si%3DswPV0p5f_8vkDMlQ&sa=D&source=editors&ust=1740622331629524&usg=AOvVaw0HfkDtTQ6Wgwb8ZRLJmNQI"],"86":[97067,"lpsLaMuNe","https://www.google.com/url?q=https://drive.google.com/file/d/1MWqjrLv_deH6jJ8iXambiXD4OOXiI6Pt/view?usp%3Ddrive_link&sa=D&source=editors&ust=1740622331629990&usg=AOvVaw0M6kLY1j_Y8zUKDvZD08S9"],"87":[120914,"らくbot","https://www.google.com/url?q=https://youtu.be/J3v61p6_nzA?feature%3Dshared&sa=D&source=editors&ust=1740622331630129&usg=AOvVaw0zAwY0jzKbioat0rH1U8KF"],"88":[121612,"ぐち","https://www.google.com/url?q=https://www.youtube.com/watch?v%3DITlkV7BnO74&sa=D&source=editors&ust=1740622331630438&usg=AOvVaw3XBTxVWAn4I5zO4W7iW7hF"],"89":[107174,"Panda","https://www.google.com/url?q=https://youtu.be/0FD76oWpvvQ?si%3DZ2fl70x5YypRIsMu&sa=D&source=editors&ust=1740622331656365&usg=AOvVaw3IKrYdyelXqx9HsVBf3ECi"],"90":[130859,"kuzero","https://www.google.com/url?q=https://x.com/kuzerox_/status/1781224866592796702?s%3D46%26t%3Dn_XfioWCbx56plliCg1BSA&sa=D&source=editors&ust=1740622331656799&usg=AOvVaw2wyCXhP2f-b75osc-WSMAI"],"91":[110865,"nire","https://www.google.com/url?q=https://youtu.be/Ma0g61nhXw4?si%3DfDYMju2sPIvUF9jS&sa=D&source=editors&ust=1740622331657234&usg=AOvVaw3dsvcjfhHcfbhwVDKHb0UW"],"92":[122812,"ぐち","https://www.google.com/url?q=https://www.youtube.com/watch?v%3DBrufrzVYiRM&sa=D&source=editors&ust=1740622331657667&usg=AOvVaw2hz_hwLE2YNxEV0GxFpAZ1"],"93":[119913,"らくbot","https://www.google.com/url?q=https://youtu.be/5Bn6Tyit3a4?feature%3Dshared&sa=D&source=editors&ust=1740622331684010&usg=AOvVaw2sK47vdJXFpthfoBZ5C2e0"],"94":[119866,"Panda","https://www.google.com/url?q=https://youtu.be/ENIvSOTo9iY?si%3DIR2YqvCs8QALqmlk&sa=D&source=editors&ust=1740622331684343&usg=AOvVaw1ITQnN9LE2vX1i7UEa3yE2"],"95":[103114,"Pii","https://www.google.com/url?q=https://www.youtube.com/watch?v%3Dd5ydfEfO55Y&sa=D&source=editors&ust=1740622331684596&usg=AOvVaw1z9_YyFrul6BzvExz3bsoY"],"96":[154834,"ぐち","https://www.google.com/url?q=https://www.youtube.com/watch?v%3D5i2H4fu-0ZA&sa=D&source=editors&ust=1740622331684942&usg=AOvVaw1qwhSCGpVg9CNL4taQT3gP"]},"nita200":{"1":[71438,"Thomas","https://www.google.com/url?q=https://youtu.be/y5dRCIdjr-M&sa=D&source=editors&ust=1740622343313979&usg=AOvVaw1p_0skvMCc3-h59AEp5eHV"],"2":[73839,"Alberto","https://www.google.com/url?q=https://www.youtube.com/watch?v%3Df73861sWPVQ&sa=D&source=editors&ust=1740622343314440&usg=AOvVaw0Hu6y8Sf-Y2tNV42kPQeIb"],"3":[85593,"Technical","https://www.google.com/url?q=https://youtu.be/GPN2106tmLY&sa=D&source=editors&ust=1740622343314844&usg=AOvVaw0pNuVXQd0WucKu98rJ_Yh-"],"4":[79646,"Cream","https://www.google.com/url?q=https://www.youtube.com/watch?v%3D4xrSTVVtl-U&sa=D&source=editors&ust=1740622343315342&usg=AOvVaw1q-Fh6pvxrPX5uAdTqg09V"],"5":[76722,"核熱","https://www.google.com/url?q=https://youtu.be/5UKhurwDeXE&sa=D&source=editors&ust=1740622343345420&usg=AOvVaw3B4N0AR2UKEEAkABBPPQih"],"6":[90322,"Pianist15","https://www.google.com/url?q=https://youtu.be/F0dRyNZyfvY&sa=D&source=editors&ust=1740622343345945&usg=AOvVaw3SL2uTkDzDhjXWDvh2DEU2"],"7":[86667,"Alberto","https://www.google.com/url?q=https://www.youtube.com/watch?v%3Dap4MxWrDxJo&sa=D&source=editors&ust=1740622343346459&usg=AOvVaw0e_yKAg_nHtdoFAFKZNCHO"],"8":[88964,"Alberto","https://www.google.com/url?q=https://www.youtube.com/watch?v%3DQi_0uMwUyIM&sa=D&source=editors&ust=1740622343346968&usg=AOvVaw3qckeJKAcGMxAp98N4iT0o"],"9":[90585,"Army","https://www.google.com/url?q=https://www.youtube.com/watch?v%3Dn6yT_H2knqU&sa=D&source=editors&ust=1740622343378353&usg=AOvVaw0TbXpUCkcWxGamK3zOEfuo"],"10":[84877,"Thomas","https://www.google.com/url?q=https://youtu.be/3guO1hd2hKQ&sa=D&source=editors&ust=1740622343378773&usg=AOvVaw2M3dgqF5Y1kBcc6-KZVx2P"],"11":[87759,"Army","https://www.google.com/url?q=https://www.youtube.com/watch?v%3DgxMoMI54Iy0&sa=D&source=editors&ust=1740622343379190&usg=AOvVaw3OO_lhvbm8l_aGGiDrQ8h7"],"12":[78083,"Technical","https://www.google.com/url?q=https://www.youtube.com/watch?v%3D0gbTo_gAEKU&sa=D&source=editors&ust=1740622343379640&usg=AOvVaw3ZLlyRrHeai1FL-sj1uMO2"],"13":[90977,"Alberto","https://www.google.com/url?q=https://www.youtube.com/watch?v%3DCBgNUTuS2R4%26t&sa=D&source=editors&ust=1740622343408108&usg=AOvVaw3rERi97gkOWmAUbqz0DEN6"],"14":[83859,"Thomas","https://www.google.com/url?q=https://youtu.be/8mg6uNmCNFw&sa=D&source=editors&ust=1740622343408488&usg=AOvVaw0m1INxg3AHZtl2M0bVlZ1i"],"15":[89490,"Technical","https://www.google.com/url?q=https://www.youtube.com/watch?v%3DorNCAj0uGu8&sa=D&source=editors&ust=1740622343408873&usg=AOvVaw1T7OuVWoSA8vyBiYwuy92L"],"16":[94794,"Awoken","https://www.google.com/url?q=https://www.youtube.com/watch?v%3D4GwTh5qBa80&sa=D&source=editors&ust=1740622343409335&usg=AOvVaw2RP945Yqjt7QzP3vqNXY8M"],"17":[61736,"Citro","https://www.google.com/url?q=https://www.youtube.com/watch?v%3DQ8X4CNXZ3rg&sa=D&source=editors&ust=1740622343431813&usg=AOvVaw0agPlqv7I9rTfqUz3DGt-s"],"18":[64085,"Army","https://www.google.com/url?q=https://www.youtube.com/watch?v%3DHh0FRBUE8Bs&sa=D&source=editors&ust=1740622343432342&usg=AOvVaw1YYSiH6C42nHf2_sIxPC4S"],"19":[77830,"Thomas","https://www.google.com/url?q=https://youtu.be/xuTuDvPrMRs&sa=D&source=editors&ust=1740622343432838&usg=AOvVaw05Ne7vqXM6BrMECQqmOLbS"],"20":[74920,"Thomas","https://www.google.com/url?q=https://youtu.be/4B_SGSw9JDg&sa=D&source=editors&ust=1740622343433349&usg=AOvVaw3PQAp815pvXl-ZBNJpdXZR"],"21":[84193,"Panda","https://www.google.com/url?q=https://www.youtube.com/watch?v%3D7BtLnll9jXo&sa=D&source=editors&ust=1740622343465446&usg=AOvVaw28NH0YceQ7d1-jJwLtbTbH"],"22":[60737,"Falkmanhi","https://www.google.com/url?q=https://youtu.be/lDABzjPi6k4?si%3Dcp0RMHnM1WtGn-br&sa=D&source=editors&ust=1740622343465959&usg=AOvVaw3p3nnsXoxciAGvLvmJSi9h"],"23":[87867,"Technical","https://www.google.com/url?q=https://www.youtube.com/watch?v%3DYNZSxM08SgE&sa=D&source=editors&ust=1740622343466459&usg=AOvVaw2ThzqDkfehLpH7tXMmsipC"],"24":[89870,"Thomas","https://www.google.com/url?q=https://youtu.be/IVD_0WHa9L8&sa=D&source=editors&ust=1740622343466961&usg=AOvVaw3i8kvUwxesjL4EDRxflWb1"],"25":[84406,"Thomas","https://www.google.com/url?q=https://youtu.be/xDqh8FdnvuM&sa=D&source=editors&ust=1740622343494061&usg=AOvVaw0Mfv4TfqkfyFYeMqGoqAU9"],"26":[78252,"Army","https://www.google.com/url?q=https://youtu.be/JHIkCZj_8Sc?si%3D0Q57FBR-mP7hdzHU&sa=D&source=editors&ust=1740622343494536&usg=AOvVaw2b4iasnLz6yaharAUh6z1A"],"27":[85665,"Thomas","https://www.google.com/url?q=https://youtu.be/S0icciAGYN4&sa=D&source=editors&ust=1740622343494970&usg=AOvVaw0nhxzPMnaC8OJrziwFDiBy"],"28":[88294,"zill","https://www.google.com/url?q=https://www.youtube.com/watch?v%3Dc_gGoqQersE&sa=D&source=editors&ust=1740622343495405&usg=AOvVaw3iAPffcNT2ZycisfTtaauz"],"29":[75571,"alpha","https://www.google.com/url?q=https://youtu.be/cSsBd5Et7gM&sa=D&source=editors&ust=1740622343520010&usg=AOvVaw0_sesoRoc7cLKKEIcAKIPw"],"30":[91566,"konni","https://www.google.com/url?q=https://www.youtube.com/watch?v%3DAY-F1pDhaQc%26ab_channel%3Dkonni&sa=D&source=editors&ust=1740622343520481&usg=AOvVaw1gwGdoPlnMiOQJ1EhFUan5"],"31":[85964,"Verlust","https://www.google.com/url?q=https://www.youtube.com/watch?v%3DIvjgQHnbnNc&sa=D&source=editors&ust=1740622343520988&usg=AOvVaw1H01t2O5Hc5XgcFyEmbZEl"],"32":[0,"Alberto","https://www.google.com/url?q=https://www.youtube.com/watch?v%3Dago0_DOWSv4&sa=D&source=editors&ust=1740622343521524&usg=AOvVaw2qsK4ZpG8CYOh41eUSFC17"],"33":[79099,"Alberto","https://www.google.com/url?q=https://www.youtube.com/watch?v%3DQUYBKesTS6A&sa=D&source=editors&ust=1740622343551373&usg=AOvVaw3s4iNmiEdtRg4xedu0XaAy"],"34":[78803,"Prilin","https://www.google.com/url?q=https://youtu.be/0KL7i304frI&sa=D&source=editors&ust=1740622343551796&usg=AOvVaw0VqmKz2CLfRKIxESp4H7tp"],"35":[80475,"Alberto","https://www.google.com/url?q=https://www.youtube.com/watch?v%3DrEqZhiLUn8I&sa=D&source=editors&ust=1740622343552223&usg=AOvVaw2mmwYueJ7wS7nY8t1kAd6w"],"36":[84385,"Alberto","https://www.google.com/url?q=https://www.youtube.com/watch?v%3DJALQ-fubAgg&sa=D&source=editors&ust=1740622343552730&usg=AOvVaw3guxmXwVDrHzRFr-jFcsTL"],"37":[87775,"Alberto","https://www.google.com/url?q=https://www.youtube.com/watch?v%3Ddjsq8eJeX3c&sa=D&source=editors&ust=1740622343578572&usg=AOvVaw13kKKDE5Y4wjAI-afsYwm_"],"38":[63647,"alpha","https://www.google.com/url?q=https://youtu.be/Cklb0gRMpMs&sa=D&source=editors&ust=1740622343579069&usg=AOvVaw3hSUZhi6ya4ZXmKuq-4OjX"],"39":[79499,"Thomas","https://www.google.com/url?q=https://youtu.be/hq87QfJwbOE&sa=D&source=editors&ust=1740622343579599&usg=AOvVaw3KABZfgDGUtyK9e-RzARts"],"40":[83646,"Thomas","https://www.google.com/url?q=https://youtu.be/-9sz6sQkTL4&sa=D&source=editors&ust=1740622343580054&usg=AOvVaw0Ub_iCtSVIWbceJh6Kaadn"],"41":[0,"Army","https://www.google.com/url?q=https://www.youtube.com/watch?v%3Dsxwkdzy2YaM&sa=D&source=editors&ust=1740622343608378&usg=AOvVaw1AdG3hmylPRBjweE415N1c"],"42":[82061,"Falkmanhi","https://www.google.com/url?q=https://youtu.be/uAbctzbVOVM?si%3DCOFZIgal1tGOv_YO&sa=D&source=editors&ust=1740622343608826&usg=AOvVaw18HDqKozKMSTfuDBZoxWsy"],"43":[79265,"Technical","https://www.google.com/url?q=https://www.youtube.com/watch?v%3DB9-xZNhjWHM&sa=D&source=editors&ust=1740622343609295&usg=AOvVaw0iF7bNqU-CgtjCMnSLFlcZ"],"44":[74542,"Flour","https://www.google.com/url?q=https://youtu.be/gPiWbTpYFT0?si%3DWU4v1Unt_TTAvN8d&sa=D&source=editors&ust=1740622343609736&usg=AOvVaw2mFa8oju3s02RLUWVQAsTx"],"45":[82943,"Alberto","https://www.google.com/url?q=https://www.youtube.com/watch?v%3DEWAchm0O2yg&sa=D&source=editors&ust=1740622343638188&usg=AOvVaw0Rnc9gHiF0y84pbAi4P7zs"],"46":[81331,"Technical","https://www.google.com/url?q=https://www.youtube.com/watch?v%3DxXWsZJIfy6Q&sa=D&source=editors&ust=1740622343638748&usg=AOvVaw13vfqSLYm9k78y_AKGtJHT"],"47":[75946,"Alberto","https://www.google.com/url?q=https://youtu.be/HelApJ2fad8&sa=D&source=editors&ust=1740622343639326&usg=AOvVaw0moaG-iA_bfazz8p58fbCc"],"48":[63383,"Technical","https://www.google.com/url?q=https://youtu.be/PWG60Mysg2g&sa=D&source=editors&ust=1740622343639917&usg=AOvVaw08jwGvHxDHrN_CR_PhrMmy"],"49":[78988,"Technical","https://www.google.com/url?q=https://youtu.be/mb633avPz90&sa=D&source=editors&ust=1740622343670922&usg=AOvVaw26CiCfpJ-rRH-bScQzIayF"],"50":[59691,"Technical","https://www.google.com/url?q=https://youtu.be/rl22EgWS1SU&sa=D&source=editors&ust=1740622343671470&usg=AOvVaw1jSkni8rEHEDiLtp4t_Il8"],"51":[82304,"Mr. Cloud Kirby","https://www.google.com/url?q=https://youtu.be/pJaP5K5g7rc?si%3DLueT6DbXvj6INpWD&sa=D&source=editors&ust=1740622343672015&usg=AOvVaw2ipeuH15proGwtyXBaItfg"],"52":[77670,"konni","https://www.google.com/url?q=https://youtu.be/Go4m5gL7sNI&sa=D&source=editors&ust=1740622343672468&usg=AOvVaw2NKDcP2hz7ugjFH4zLoJ2A"],"53":[60945,"Technical","https://www.google.com/url?q=https://youtu.be/1jidjsRfWzw&sa=D&source=editors&ust=1740622343703055&usg=AOvVaw0CfLjw9za-k0eOSwwIkz6W"],"54":[80022,"Army","https://www.google.com/url?q=https://youtu.be/rGK9watUphg&sa=D&source=editors&ust=1740622343703490&usg=AOvVaw0Hevzv9h_GEb203zYSVcy_"],"55":[65734,"Alberto","https://www.google.com/url?q=https://www.youtube.com/watch?v%3DK2CGiVw0if0&sa=D&source=editors&ust=1740622343703892&usg=AOvVaw0EGH75EgsOVidwWVpefNmn"],"56":[87451,"olli","https://www.google.com/url?q=https://www.youtube.com/watch?v%3DsUS73zXOCL4&sa=D&source=editors&ust=1740622343704343&usg=AOvVaw0xTGUpw0KKNsjyrzBqrZih"],"57":[61489,"Thomas","https://www.google.com/url?q=https://youtu.be/j3LcEo0OFqg&sa=D&source=editors&ust=1740622343734879&usg=AOvVaw3fxztrJruDda3OuLYcnV8j"],"58":[68982,"Arito","https://www.google.com/url?q=https://x.com/Arito_RA/status/1839556674216251540?t%3DKJlBZyH5c4DZsIuHPnbKTw%26s%3D19&sa=D&source=editors&ust=1740622343735407&usg=AOvVaw1D1wyfMFKxgKCAj-FV1tc6"],"59":[66086,"Army","https://www.google.com/url?q=https://www.youtube.com/watch?v%3DFADsgIf1PF4&sa=D&source=editors&ust=1740622343735925&usg=AOvVaw2_XlLnjh6lJD45DkeRFB53"],"60":[108441,"Technical","https://www.google.com/url?q=https://www.youtube.com/watch?v%3DM23YvBOztVo&sa=D&source=editors&ust=1740622343736439&usg=AOvVaw0cknEG6uymWakFUO9jrTel"],"61":[87901,"Vincent","https://www.google.com/url?q=https://www.youtube.com/watch?v%3DS9Dhwh1lcHs&sa=D&source=editors&ust=1740622343766122&usg=AOvVaw3SeXRqEMpGlmKF0jCz9OQD"],"62":[71918,"Alberto","https://www.google.com/url?q=https://www.youtube.com/watch?v%3DEAyNdnuUQZo&sa=D&source=editors&ust=1740622343766541&usg=AOvVaw1t5SsekoH0ROWNuUM3d2eU"],"63":[68615,"ちーゃんねる","https://www.google.com/url?q=https://youtu.be/3dwQ6HV6KUg?si%3DzqRs18hm1hVY2yAE&sa=D&source=editors&ust=1740622343766957&usg=AOvVaw3xaq6I0EJsX9gy_CnA3_Za"],"64":[82835,"Pianist15","https://www.google.com/url?q=https://www.youtube.com/watch?v%3DGS2Lm1ra55c&sa=D&source=editors&ust=1740622343767364&usg=AOvVaw2yHJhnHVZeSCvU-EWwCSOa"],"65":[93136,"Army","https://www.google.com/url?q=https://www.youtube.com/watch?v%3DvgsxVwHK6wY&sa=D&source=editors&ust=1740622343798198&usg=AOvVaw1sb2uQIHWnsvycBCqxijka"],"66":[61988,"Army","https://www.google.com/url?q=https://www.youtube.com/watch?v%3DNX-9ZlTAfkI&sa=D&source=editors&ust=1740622343798575&usg=AOvVaw3TF7jnppRQ2TKlyjth4HbG"],"67":[94932,"Technical","https://www.google.com/url?q=https://www.youtube.com/watch?v%3DBl2QKUakucc&sa=D&source=editors&ust=1740622343798954&usg=AOvVaw3UAMQwIF0jWyNX_MO0mGfC"],"68":[112157,"Technical","https://www.google.com/url?q=https://youtu.be/2XzP96Xtu8o&sa=D&source=editors&ust=1740622343799401&usg=AOvVaw3p7Ii7xA77iBGpzwc7Skxh"],"69":[85634,"Alpaco","https://www.google.com/url?q=https://www.youtube.com/watch?v%3DbB6WHCtaEbw&sa=D&source=editors&ust=1740622343829213&usg=AOvVaw30vlYvNFYMxd0HinVr6zOJ"],"70":[89867,"Technical","https://www.google.com/url?q=https://youtu.be/Aqp0WsEftQg&sa=D&source=editors&ust=1740622343829724&usg=AOvVaw1PVvYywgFH74eiQUP3Teys"],"71":[83603,"かりま","https://www.google.com/url?q=https://youtu.be/nUfErmuXjeI?si%3DgkSuzYz_7zdBPuYI&sa=D&source=editors&ust=1740622343830226&usg=AOvVaw1ltv7TnWPGle-kb_63wvUM"],"72":[71832,"Elmer","https://www.google.com/url?q=https://www.youtube.com/watch?v%3DmONR8fosczg&sa=D&source=editors&ust=1740622343830753&usg=AOvVaw3q0tPVhHPa-uiTmTCaAOYD"],"73":[70782,"flour","https://www.google.com/url?q=https://youtu.be/40nPX6bIQ10?feature%3Dshared&sa=D&source=editors&ust=1740622343858241&usg=AOvVaw00ZhGmVpPMmemRuyZEekHx"],"74":[67552,"yellow","https://www.google.com/url?q=https://photos.app.goo.gl/GiJTaRwdMZNFbqid8&sa=D&source=editors&ust=1740622343858678&usg=AOvVaw2veeNsJwTzoqCW5jsUVR4j"],"75":[96112,"MSG8819","https://www.google.com/url?q=https://youtu.be/5t-lu68qcvU?si%3DG548LkhUD6DFARz3&sa=D&source=editors&ust=1740622343859067&usg=AOvVaw24eY5zRf7V36_g0lnVjNjN"],"76":[89968,"Technical","https://www.google.com/url?q=https://www.youtube.com/watch?v%3DU2OEePZGuK0&sa=D&source=editors&ust=1740622343859469&usg=AOvVaw1fhc0GQp_CvUfw1HA0bKR9"],"77":[75049,"SKaR","https://www.google.com/url?q=https://www.youtube.com/watch?v%3DEdsO8b4fxXU&sa=D&source=editors&ust=1740622343883297&usg=AOvVaw10-nBsXdlLh0GU8-LRpYkQ"],"78":[74579,"SKaR","https://www.google.com/url?q=https://www.youtube.com/watch?v%3DPBeKyhSYQJM&sa=D&source=editors&ust=1740622343883741&usg=AOvVaw2K7RRBh6m6q7IdKSTdUCQH"],"79":[91587,"Technical","https://www.google.com/url?q=https://youtu.be/dHQepUOZx5I&sa=D&source=editors&ust=1740622343884240&usg=AOvVaw1Pkjb5hCEJ5ocpWgPF_iwB"],"80":[84026,"Technical","https://www.google.com/url?q=https://youtu.be/KaauixuD1qo&sa=D&source=editors&ust=1740622343884780&usg=AOvVaw1r8DgmEChS0dLuNaa_7F_t"],"81":[73511,"Technical","https://www.google.com/url?q=https://youtu.be/CFcvUky3p_s&sa=D&source=editors&ust=1740622343914584&usg=AOvVaw3cCe9DAoMLUZdvzW1enylO"],"82":[70663,"Technical","https://www.google.com/url?q=https://youtu.be/aAvL3qGUurA&sa=D&source=editors&ust=1740622343914996&usg=AOvVaw2ZssCC0Ds27i0zaNxcGcV9"],"83":[75088,"zill","https://www.google.com/url?q=https://www.youtube.com/watch?v%3DRHkO3bUYjlI&sa=D&source=editors&ust=1740622343915416&usg=AOvVaw1nbYJ1wAWTNcDRN_E9bMnV"],"84":[88292,"Alberto","https://www.google.com/url?q=https://youtu.be/zeULHUTWtpw&sa=D&source=editors&ust=1740622343915828&usg=AOvVaw3zvvtzltHXNwYqccjXVyQQ"],"85":[78300,"Flour","https://www.google.com/url?q=https://youtu.be/Za3qhyLG9uQ?si%3D8i_-9piVYnYNnBjb&sa=D&source=editors&ust=1740622343935514&usg=AOvVaw1Had_BDO9KR16L39U0dDKn"],"86":[71976,"Kouta.","https://www.google.com/url?q=https://youtu.be/6i8DjHYIZGI&sa=D&source=editors&ust=1740622343935890&usg=AOvVaw0bx9mfpHw1C739cnqQoQiA"],"87":[88305,"Technical","https://www.google.com/url?q=https://youtu.be/EWqSPkIVWI0&sa=D&source=editors&ust=1740622343936330&usg=AOvVaw1aA3FzBK4dPmds_A4QU77Q"],"88":[87809,"zill","https://www.google.com/url?q=https://www.youtube.com/watch?v%3DqDLC5I8JAyQ&sa=D&source=editors&ust=1740622343936735&usg=AOvVaw1XZtKXJyvPwho62FPb5wSB"],"89":[77681,"Naoto","https://www.google.com/url?q=https://youtu.be/srtK1hqoMiQ?si%3DltoL4sPuucSXziej&sa=D&source=editors&ust=1740622343957849&usg=AOvVaw1wGrR6t1-Ry-7koMfulrNv"],"90":[108986,"Elmer","https://www.google.com/url?q=https://www.youtube.com/watch?v%3DdVsunL-FtUY%26ab_channel%3DElmer&sa=D&source=editors&ust=1740622343958313&usg=AOvVaw3FwTwWvGvZMV2lfUtN8vjZ"],"91":[79730,"Pianist15","https://www.google.com/url?q=https://youtu.be/9_eFGJXAsSQ?si%3Dej43TUingbdFJq0s%26t%3D229&sa=D&source=editors&ust=1740622343958735&usg=AOvVaw0ME2WrkeXfDYh9ZxMPD10J"],"92":[88713,"konni","https://www.google.com/url?q=https://youtu.be/nNkk0YpYi-0&sa=D&source=editors&ust=1740622343959183&usg=AOvVaw1vOno7uUU0rr0hSbCLWClX"],"93":[85808,"Flour","https://www.google.com/url?q=https://youtu.be/5z3azwF1grI?si%3DH0g4nFfIdmg6QF2W&sa=D&source=editors&ust=1740622343981719&usg=AOvVaw2OpcTlNSS6QVWg6Iis_xre"],"94":[89693,"Wood22","https://www.google.com/url?q=https://youtu.be/RiPPMRUN4f0?si%3DzqY6TD44QapX5Xte&sa=D&source=editors&ust=1740622343982071&usg=AOvVaw3FrTzoc95Ci7LOwKtpexlA"],"95":[76620,"konni","https://www.google.com/url?q=https://youtu.be/uQRudglSdvo&sa=D&source=editors&ust=1740622343982470&usg=AOvVaw1BIKd5TxxsX98stSHghcr2"],"96":[114981,"B Yoru","https://www.google.com/url?q=https://youtu.be/RYcskncidY4?si%3DCsztZJu2jT6Yx5WN&sa=D&source=editors&ust=1740622343982843&usg=AOvVaw3gJ3ncKQbQaOdlEj_H7uh8"]},"ta150":{"1":[94277,"しらぬい","https://www.youtube.com/watch?v=f178X-eHEto"],"2":[98995,"Vincent","https://www.youtube.com/watch?v=02TkOgMD-Qg"],"3":[108030,"Vincent","https://www.youtube.com/watch?v=EoehsIVq3-Q"],"4":[107080,"Panda","https://www.youtube.com/watch?v=WB59kvCa68w"],"5":[103723,"Vincent","https://www.youtube.com/watch?v=e-SOkLrSgpg"],"6":[121586,"なすの","https://www.youtube.com/watch?v=2CnwKPnLlTc"],"7":[113354,"Alberto","https://youtu.be/3ndwXMfV50s"],"8":[115279,"Yerson","https://www.youtube.com/watch?v=yssM9sKoevM"],"9":[116971,"Vincent","https://www.youtube.com/watch?v=hc3WYtlCbVg"],"10":[111951,"StervtL","https://www.youtube.com/watch?v=0KsT5AnwXAc"],"11":[115086,"Alberto","https://www.youtube.com/watch?v=jAEcZZ3Lj6M"],"12":[100545,"F。","https://www.youtube.com/watch?v=3ZnHO8Q0464"],"13":[119262,"F。","https://www.youtube.com/watch?v=r0k4n3oX19Y"],"14":[106413,"Army","https://www.youtube.com/watch?v=RDjIYAVE3NA"],"15":[117655,"Vincent","https://youtu.be/tibmjUAnRVg"],"16":[118454,"Alberto","https://youtu.be/HNT0st5ePqo"],"17":[83642,"Panda","https://www.youtube.com/watch?v=2R46yX3twqs"],"18":[58517,"Albert","https://www.youtube.com/watch?v=KVgc9D5R5EU"],"19":[59892,"StervtL","https://www.youtube.com/watch?v=uaEmg6ATdEo"],"20":[75569,"Alberto","https://youtu.be/lPMQF1NjN7Y?si=0ScZmSM6c5OG5O24"],"21":[71977,"Alphabet Soup","https://youtu.be/DA9BP3X391g"],"22":[76879,"Panda","https://youtu.be/JK10RFNKDeo"],"23":[55241,"JenZua","https://www.youtube.com/watch?v=wOngIj1x_Rw"],"24":[83413,"Technical","https://www.youtube.com/watch?v=E3bYUdaTGh4"],"25":[87316,"Panda","https://www.youtube.com/watch?v=RBukMzcLvLU"],"26":[81128,"Pii","https://www.youtube.com/watch?v=CSYslhqZgVA"],"27":[76130,"Alberto","https://www.youtube.com/watch?v=E4Qegv_QCCI"],"28":[83309,"Alberto","https://www.youtube.com/watch?v=wD0SK8CZnwc"],"29":[83992,"Alberto","https://www.youtube.com/watch?v=lGoatvaM7Jo"],"30":[72991,"Alberto",null],"31":[86082,"Pii","https://www.youtube.com/watch?v=xd5rI8wg0d4"],"32":[81673,"Hgt","https://www.youtube.com/watch?v=8XfhPNlIFsg"],"33":[56335,"kwartz","https://www.youtube.com/watch?v=T7RP6M-cGMU"],"34":[73025,"Army","https://www.youtube.com/watch?v=yYV9BnvqIqE"],"35":[73889,"しらぬい","https://www.youtube.com/watch?v=hsYvYs4PQmA"],"36":[100081,"Alberto","https://www.youtube.com/watch?v=l07fps_68nA"],"37":[110788,"StervtL","https://www.youtube.com/watch?v=5XNqlk0Fp-I"],"38":[121373,"Vincent","https://www.youtube.com/watch?v=9-n6nxPRrgk"],"39":[85569,"Vincent","https://www.youtube.com/watch?v=Fdw_09Kn-VE"],"40":[104738,"Alberto","https://www.youtube.com/watch?v=inc-eNkSo_U"],"41":[76926,"grace","https://www.youtube.com/watch?v=rg-R4BXxG8k"],"42":[79631,"JenZua",null],"43":[44731,"alpha","https://www.youtube.com/watch?v=7LSoZfVAKfk"],"44":[74917,"alpha","https://www.youtube.com/watch?v=JduphBt80w4"],"45":[76609,"Alberto","https://www.youtube.com/watch?v=5CjiHfzGhOY"],"46":[70407,"4laps2win","https://www.youtube.com/watch?v=vq3Lb62fRvg"],"47":[78871,"Alberto","https://youtu.be/f9V8qU5wJ9Q"],"48":[76949,"Army","https://www.youtube.com/watch?v=2l1KZIgyDAA"],"49":[72788,"Alberto",null],"50":[60361,"FA","https://www.youtube.com/watch?v=lNQsHaQDQeo"],"51":[76395,"Army","https://www.youtube.com/watch?v=GitYX9Ulem4"],"52":[56489,"Army","https://www.youtube.com/watch?v=2HGIfNhOeZI"],"53":[79651,"Vincent","https://www.youtube.com/watch?v=g0F5_VnykZw"],"54":[73865,"Army","https://www.youtube.com/watch?v=oYfJB0uDxXA"],"55":[58852,"Alberto","https://youtu.be/cTwX9-lIH6o"],"56":[75426,"Alberto","https://www.youtube.com/watch?v=QxgAJpeusGI"],"57":[61722,"Technical","https://youtu.be/DAi7K8LO8n0"],"58":[84193,"Panda","https://www.youtube.com/watch?v=5_mycIie7hA"],"59":[58262,"Army","https://www.youtube.com/watch?v=UGOl7374cHU"],"60":[64323,"JenZua","https://www.youtube.com/watch?v=wm4I5EoG7p4"],"61":[60995,"Panda",null],"62":[105773,"Technical","https://www.youtube.com/watch?v=qzkKfuwdH38"],"63":[84349,"Vincent","https://www.youtube.com/watch?v=69Ncs_NHgw0"],"64":[64209,"Alberto","https://www.youtube.com/watch?v=DfsfF8nbxLI"],"65":[61808,"4laps2win","https://www.youtube.com/watch?v=yXug6Wcc1W4"],"66":[79467,"Draygo","https://www.youtube.com/watch?v=R_2fYIrJ69g"],"67":[88528,"Army","https://www.youtube.com/watch?v=uUdDTH83dp4"],"68":[59359,"Pii","https://www.youtube.com/watch?v=sZuRmtDp3aQ"],"69":[87316,"grace","https://youtu.be/ghbJbUwcEwk"],"70":[108764,"Vincent","https://www.youtube.com/watch?v=7rrppUxcGVM"],"71":[81802,"Army","https://www.youtube.com/watch?v=AMbN23iCuok"],"72":[86018,"Army","https://www.youtube.com/watch?v=gbqlxONCMjM"],"73":[78541,"bup","https://www.youtube.com/watch?v=DM1LCf4iHX8"],"74":[69446,"Technical","https://www.youtube.com/watch?v=eo4gQN_U6K0"],"75":[66568,"Technical","https://www.youtube.com/watch?v=YF8bS0Gigic"],"76":[62066,"Mirai","https://www.youtube.com/watch?v=bWcGyRY4_pw"],"77":[91428,"Technical","https://www.youtube.com/watch?v=OnH5H0aeI7c"],"78":[85990,"Technical","https://www.youtube.com/watch?v=rsmsi1pijg4"],"79":[72953,"Alberto","https://www.youtube.com/watch?v=xXcLaw4z_Is"],"80":[70765,"Pii","https://www.youtube.com/watch?v=1hcEIph-d-0"],"81":[85178,"JenZua","https://www.youtube.com/watch?v=SffAUF6WAzE"],"82":[80774,"Alberto","https://www.youtube.com/watch?v=IHKLpZhVkq8"],"83":[70762,"Technical","https://www.youtube.com/watch?v=O63voitA39U"],"84":[68546,"Army","https://www.youtube.com/watch?v=5IQYxrVfgcw"],"85":[71672,"Matt","https://www.youtube.com/watch?v=14esHk9Mj8Y"],"86":[85431,"Technical","https://www.youtube.com/watch?v=2sQ1XiUBW7U"],"87":[74102,"Alberto","https://www.youtube.com/watch?v=TkrPTeY5GxI"],"88":[67131,"Panda","https://www.youtube.com/watch?v=UlcXd3DHfyk"],"89":[116882,"Alberto","https://www.youtube.com/watch?v=XTkxY9vTaqE"],"90":[119093,"Panda","https://www.youtube.com/watch?v=DM6ywJR6574"],"91":[103326,"ささゆき","https://www.youtube.com/watch?v=ozt-Pa2KhFQ"],"92":[128958,"くぜろ","https://www.youtube.com/watch?v=gCY74FrFL8E"],"93":[107664,"Vincent","https://www.youtube.com/watch?v=a4d6JyMhxcc"],"94":[117947,"Panda","https://www.youtube.com/watch?v=3-bI8lkPNMk"],"95":[116142,"Alberto","https://www.youtube.com/watch?v=fuOuQ2zMCZc"],"96":[82371,"Alberto","https://www.youtube.com/watch?v=I-x8UgdJEH4"]},"ta200":{"1":[67271,"Army","https://www.youtube.com/watch?v=yQ3iuP2FK_Y"],"2":[70557,"Alberto","https://www.youtube.com/watch?v=A5o_JmPuJd4"],"3":[81254,"Technical","https://www.youtube.com/watch?v=lfxb0P9GzGs"],"4":[75654,"Alberto","https://www.youtube.com/watch?v=9ul4y1JVfFc"],"5":[72662,"ろーる","https://www.youtube.com/watch?v=ebxaJ3YwTB4"],"6":[86141,"Army","https://www.youtube.com/watch?v=_ejgi-L7dNU"],"7":[81982,"grace","https://www.youtube.com/watch?v=BZspqX9FLlw"],"8":[85763,"Army","https://www.youtube.com/watch?v=gnLB33dlO6c"],"9":[87987,"Alberto","https://www.youtube.com/watch?v=H18b3ICqBq0"],"10":[81899,"Alberto","https://www.youtube.com/watch?v=NljYyNfHCnk"],"11":[81669,"Alberto","https://www.youtube.com/watch?v=Y0ST_uT47ZA"],"12":[75133,"Alberto","https://youtu.be/FHM6m2XV9lE"],"13":[88808,"Alberto","https://youtu.be/Aue4_okSihY"],"14":[79265,"Panda","https://www.youtube.com/watch?v=MvCvJWFIuao"],"15":[85874,"Vincent","https://www.youtube.com/watch?v=TeIoLPDqybw"],"16":[91513,"Technical","https://www.youtube.com/watch?v=jhRuarOet60"],"17":[58517,"Army","https://www.youtube.com/watch?v=iZ1gkLY5gFs"],"18":[82953,"もぺち","https://www.youtube.com/watch?v=nRMGYjzX2pE"],"19":[106080,"Vincent","https://www.youtube.com/watch?v=sPcC6Syo2xg"],"20":[105563,"Vincent","https://www.youtube.com/watch?v=nwEpePGCDoI"],"21":[112431,"Army","https://www.youtube.com/watch?v=M8ddFvmWRZA"],"22":[72833,"Alpaco","https://youtu.be/CK9E7sR6MyE"],"23":[114778,"Panda","https://www.youtube.com/watch?v=_OUJ0odWlfc"],"24":[120477,"k","https://www.youtube.com/watch?v=vAJn8NJFnEE"],"25":[109988,"StervtL","https://www.youtube.com/watch?v=ThkwR41lQn0"],"26":[106298,"Alberto","https://www.youtube.com/watch?v=2NyImxWD2Jg"],"27":[110477,"Alberto","https://www.youtube.com/watch?v=X2PVFC-pTUo"],"28":[117482,"Vincent","https://www.youtube.com/watch?v=TCljaLkAT_o"],"29":[100997,"ありす","https://www.youtube.com/watch?v=OYRVbRIF7z8"],"30":[117960,"Pii","https://www.youtube.com/watch?v=QshLk8KJUkE"],"31":[112441,"Panda","https://youtu.be/gXOWJEBcTv4"],"32":[79196,"Vincent","https://www.youtube.com/watch?v=0S8s-zAZ7cM"],"33":[101253,"Army","https://youtu.be/szygfU_3FZI"],"34":[98467,"Army","https://www.youtube.com/watch?v=ahTFf2US1Gk"],"35":[73889,"ろーる","https://www.youtube.com/watch?v=bDFYqheit2k"],"36":[76211,"Army","https://www.youtube.com/watch?v=DZwUTCWdmJ0"],"37":[80588,"Pii","https://www.youtube.com/watch?v=YlrDXJb1goo"],"38":[84881,"Alberto","https://www.youtube.com/watch?v=XQh1VytSd7Y"],"39":[61981,"alpha","https://www.youtube.com/watch?v=GbyytniAzxc"],"40":[76926,"Alberto","https://www.youtube.com/watch?v=WqyZso1MoGk"],"41":[106905,"エル","https://youtu.be/vm1y3MLKWKg"],"42":[61836,"JenZua","https://youtu.be/6eAsFElRIww"],"43":[101432,"Army","https://www.youtube.com/watch?v=yeiaXQGKjKg"],"44":[105286,"Alberto","https://www.youtube.com/watch?v=TFgBm9oBEps"],"45":[95976,"Army","https://www.youtube.com/watch?v=SItTncntHfs"],"46":[102158,"Alberto","https://www.youtube.com/watch?v=FlSM-lU90fE"],"47":[103489,"Army","https://www.youtube.com/watch?v=K5ztD9tN5do"],"48":[99680,"Army","https://www.youtube.com/watch?v=a2UN8qyxnnE"],"49":[83189,"SorNano","https://www.youtube.com/watch?v=QDDubUQnEmc"],"50":[109376,"Army","https://youtu.be/ZtTb2Fu2M0A"],"51":[79900,"Army","https://www.youtube.com/watch?v=D17_4QRLIW4"],"52":[111619,"Vincent",null],"53":[100464,"Alberto","https://www.youtube.com/watch?v=mrBvbPjaOJM"],"54":[85014,"Vincent","https://www.youtube.com/watch?v=TDycDWSEQUw"],"55":[104094,"Vincent","https://www.youtube.com/watch?v=-hV9bi9AyhA"],"56":[85897,"Alberto","https://www.youtube.com/watch?v=nJPxQn8xH7M"],"57":[111764,"ヒビキ","https://www.youtube.com/watch?v=yShSL3hXlGI"],"58":[82481,"Panda","https://www.youtube.com/watch?v=AQ1cCF2Na48"],"59":[90525,"Vincent","https://www.youtube.com/watch?v=YBl29dKpvzc"],"60":[87642,"Army","https://www.youtube.com/watch?v=4C9eoybAJ2U"],"61":[138596,"F。","https://www.youtube.com/watch?v=6MpTi-ccdZg"],"62":[119382,"Alberto","https://www.youtube.com/watch?v=OgTqCBR5hds"],"63":[85971,"Army","https://www.youtube.com/watch?v=QV14OtCKpQs"],"64":[86945,"fairy","https://www.youtube.com/watch?v=hGX9UBnajd4"],"65":[113631,"stove","https://www.youtube.com/watch?v=VlX3zrTbAe8"],"66":[126799,"¥146","https://www.youtube.com/watch?v=80F4-lQbimo"],"67":[80255,"Army",null],"68":[126997,"Panda",null],"69":[142604,"aybzq","https://www.youtube.com/watch?v=0SZ3ibJ-yNI"],"70":[115207,"Vincent","https://www.youtube.com/watch?v=ehcpVhYo2z0"],"71":[122853,"Panda","https://www.youtube.com/watch?v=iEGfIk16daE"],"72":[109453,"Vincent","https://www.youtube.com/watch?v=Yez3Y_evdc8"],"73":[96718,"Alberto","https://www.youtube.com/watch?v=CbNGPC9ZOA4"],"74":[94766,"Panda","https://www.youtube.com/watch?v=_-wSdyRnv6A"],"75":[85011,"Vincent",null],"76":[115472,"StervtL","https://www.youtube.com/watch?v=tI3cbIM751I"],"77":[117052,"YOS","https://www.youtube.com/watch?v=qrhY5WOMyLQ"],"78":[101889,"ささゆき","https://www.youtube.com/watch?v=IfXdK_GsZGM"],"79":[96957,"Pii","https://www.youtube.com/watch?v=oeR2rXeIoXs"],"80":[113193,"F。","https://www.youtube.com/watch?v=hZLsyzuHzLA"],"81":[115682,"Vincent","https://www.youtube.com/watch?v=eAH5yRLCf0A"],"82":[97508,"Panda","https://www.youtube.com/watch?v=nXOLHE3KXxc"],"83":[93951,"Army","https://www.youtube.com/watch?v=ujVoiS_NYEQ"],"84":[101918,"Jamie","https://www.youtube.com/watch?v=Sdbx8Go4Moc"],"85":[119749,"AK","https://youtu.be/21Y_6UDjIyY?feature=shared"],"86":[105460,"ささゆき","https://www.youtube.com/watch?v=NGafpCcKgRQ"],"87":[92261,"¥146","https://www.youtube.com/watch?v=p2UXpeH6dns"],"88":[67131,"Pii","https://www.youtube.com/watch?v=RDJ3utAS2jw"],"89":[85655,"JenZua","https://www.youtube.com/watch?v=ehx9Qe6jHZ4"],"90":[83897,"Vincent","https://www.youtube.com/watch?v=NzD7Lo6Ijik"],"91":[73929,"Alberto","https://www.youtube.com/watch?v=L7zEvupkSnM"],"92":[104532,"Zae","https://www.youtube.com/watch?v=NhtvBImFYSc"],"93":[76118,"Army","https://www.youtube.com/watch?v=Ldu2Byu7nGA"],"94":[83776,"Bruh",null],"95":[82371,"Army","https://www.youtube.com/watch?v=I-x8UgdJEH4"],"96":[115976,"Alberto","https://www.youtube.com/watch?v=U_qgqgVAArM"]}}}