{"default":{"lang":"en","nita150":{"1":"","2":"","3":"","4":"","5":"","6":"","7":"","8":"","9":"","10":"","11":"","12":"","13":"","14":"","15":"","16":"","17":"","18":"","19":"","20":"","21":"","22":"","23":"","24":"","25":"","26":"","27":"","28":"","29":"","30":"","31":"","32":"","33":"","34":"","35":"","36":"","37":"","38":"","39":"","40":"","41":"","42":"","43":"","44":"","45":"","46":"","47":"","48":"","49":"","50":"","51":"","52":"","53":"","54":"","55":"","56":"","57":"","58":"","59":"","60":"","61":"","62":"","63":"","64":"","65":"","66":"","67":"","68":"","69":"","70":"","71":"","72":"","73":"","74":"","75":"","76":"","77":"","78":"","79":"","80":"","81":"","82":"","83":"","84":"","85":"","86":"","87":"","88":"","89":"","90":"","91":"","92":"","93":"","94":"","95":"","96":""},"nita200":{"1":"","2":"","3":"","4":"","5":"","6":"","7":"","8":"","9":"","10":"","11":"","12":"","13":"","14":"","15":"","16":"","17":"","18":"","19":"","20":"","21":"","22":"","23":"","24":"","25":"","26":"","27":"","28":"","29":"","30":"","31":"","32":"","33":"","34":"","35":"","36":"","37":"","38":"","39":"","40":"","41":"","42":"","43":"","44":"","45":"","46":"","47":"","48":"","49":"","50":"","51":"","52":"","53":"","54":"","55":"","56":"","57":"","58":"","59":"","60":"","61":"","62":"","63":"","64":"","65":"","66":"","67":"","68":"","69":"","70":"","71":"","72":"","73":"","74":"","75":"","76":"","77":"","78":"","79":"","80":"","81":"","82":"","83":"","84":"","85":"","86":"","87":"","88":"","89":"","90":"","91":"","92":"","93":"","94":"","95":"","96":""},"ta150":{"1":"","2":"","3":"","4":"","5":"","6":"","7":"","8":"","9":"","10":"","11":"","12":"","13":"","14":"","15":"","16":"","17":"","18":"","19":"","20":"","21":"","22":"","23":"","24":"","25":"","26":"","27":"","28":"","29":"","30":"","31":"","32":"","33":"","34":"","35":"","36":"","37":"","38":"","39":"","40":"","41":"","42":"","43":"","44":"","45":"","46":"","47":"","48":"","49":"","50":"","51":"","52":"","53":"","54":"","55":"","56":"","57":"","58":"","59":"","60":"","61":"","62":"","63":"","64":"","65":"","66":"","67":"","68":"","69":"","70":"","71":"","72":"","73":"","74":"","75":"","76":"","77":"","78":"","79":"","80":"","81":"","82":"","83":"","84":"","85":"","86":"","87":"","88":"","89":"","90":"","91":"","92":"","93":"","94":"","95":"","96":""},"ta200":{"1":"","2":"","3":"","4":"","5":"","6":"","7":"","8":"","9":"","10":"","11":"","12":"","13":"","14":"","15":"","16":"","17":"","18":"","19":"","20":"","21":"","22":"","23":"","24":"","25":"","26":"","27":"","28":"","29":"","30":"","31":"","32":"","33":"","34":"","35":"","36":"","37":"","38":"","39":"","40":"","41":"","42":"","43":"","44":"","45":"","46":"","47":"","48":"","49":"","50":"","51":"","52":"","53":"","54":"","55":"","56":"","57":"","58":"","59":"","60":"","61":"","62":"","63":"","64":"","65":"","66":"","67":"","68":"","69":"","70":"","71":"","72":"","73":"","74":"","75":"","76":"","77":"","78":"","79":"","80":"","81":"","82":"","83":"","84":"","85":"","86":"","87":"","88":"","89":"","90":"","91":"","92":"","93":"","94":"","95":"","96":""}},"tracks":{"ja":["マリオカートスタジアム","ウォーターパーク","スイーツキャニオン","ドッスンいせき","マリオサーキット","キノピオハーバー","ねじれマンション","ヘイホーこうざん","サンシャインくうこう","ドルフィンみさき","エレクトロドリーム","ワリオスノーマウンテン","スカイガーデン","ホネホネさばく","クッパキャッスル","レインボーロード","Wii モーモーカントリー","GBA マリオサーキット","DS プクプクビーチ","N64 キノピオハイウェイ","GC カラカラさばく","SFC ドーナツへいや3","N64 ピーチサーキット","3DS DKジャングル","DS ワリオスタジアム","GC シャーベットランド","3DS ミュージックパーク","N64 ヨッシーバレー","DS チクタクロック","3DS パックンスライダー","Wii グラグラかざん","N64 レインボーロード","GC ヨッシーサーキット","エキサイトバイク","ドラゴンロード","ミュートシティ","Wii ワリオこうざん","SFC レインボーロード","ツルツルツイスター","ハイラルサーキット","GC ベビィパーク","GBA チーズランド","ネイチャーロード","どうぶつの森","3DS ネオクッパシティ","GBA リボンロード","リンリンメトロ","ビッグブルー","Tour パリプロムナード","3DS キノピオサーキット","N64 チョコマウンテン","Wii ココナッツモール","Tour トーキョースクランブル","DS キノコリッジウェイ","GBA スカイガーデン","ニンニンドージョー","Tour ニューヨークドリーム","SFC マリオサーキット 3","N64 カラカラさばく","DS ワルイージピンボール","Tour シドニーサンシャイン","GBA スノーランド","Wii キノコキャニオン","アイスビルディング","Tour ロンドンアベニュー","GBA テレサレイク","3DS ロックロックマウンテン","Wii メイプルツリーハウス","Tour ベルリンシュトラーセ","DS ピーチガーデン","メリーメリーマウンテン","3DS レインボーロード","Tour アムステルダムブルーム","GBA リバーサイドパーク","Wii DKスノーボードクロス","ヨッシーアイランド","Tour バンコクラッシュ","DS マリオサーキット","GC ワルイージスタジアム","Tour シンガポールスプラッシュ","Tour アテネポリス","GC デイジークルーザー","Wii ムーンリッジ&ハイウェイ","シャボンロード","Tour ロサンゼルスコースト","GBA サンセットこうや","Wii ノコノコみさき","Tour バンクーバーバレー","Tour ローマアバンティ","GC DKマウンテン","Wii デイジーサーキット","パックンしんでん","Tour マドリードグランデ","3DS ロゼッタプラネット","SFC クッパじょう 3","Wii レインボーロード"],"en":["Mario Kart Stadium","Water Park","Sweet Sweet Canyon","Thwomp Ruins","Mario Circuit","Toad Harbor","Twisted Mansion","Shy Guy Falls","Sunshine Airport","Dolphin Shoals","Electrodrome","Mount Wario","Cloudtop Cruise","Bone-Dry Dunes","Bowser's Castle","Rainbow Road","Wii Moo Moo Meadows","GBA Mario Circuit","DS Cheep Cheep Beach","N64 Toad's Turnpike","GC Dry Dry Desert","SFC Donut Plains 3","N64 Royal Raceway","3DS DK Jungle","DS Wario Stadium","GC Sherbet Land","3DS Music Park","N64 Yoshi Valley","DS Tick-Tock Clock","3DS Pilanha Plant Slide","Wii Grumble Volcano","N64 Rainbow Road","GC Yoshi Circuit","Excitebike Arena","Dragon Driftway","Mute City","Wii Wario's Gold Mine","SFC Rainbow Road","Ice Ice Outpost","Hyrule Circuit","GC Baby Park","GBA Cheese Land","Wild Woods","Animal Crossing","3DS Neo Bowser City","GBA Ribbon Road","Super Bell Subway","Big Blue","Tour Paris Promenade","3DS Toad Circuit","N64 Choco Mountain","Wii Coconut Mall","Tour Tokyo Blur","DS Shroom Ridge","GBA Sky Garden","Ninja Hideaway","Tour New York Minute","SFC Mario Circuit 3","N64 Kalimali Desert","DS Waluigi Pinball","Tour Sydney Sprint","GBA Snow Land","Wii Mushroom Gorge","Sky-high Sundae","Tour London Loop","GBA Boo Lake","3DS Rock Rock Mountain","Wii Maple Treeway","Tour Berlin Byways","DS Peach Gardens","Merry Mountain","3DS Rainbow Road","Tour Amsterdam Drift","GBA Riverside Park","Wii DK Summit","Yoshi's Island","Tour Bangkok Rush","Ds Mario Circuit","GC Waluigi Stadium","Tour Singapore Speedway","Tour Athens Dash","GC Daisy Cruiser","Wii Moonview Highway","Squeaky Clean Sprint","Tour Los Angeles Laps","GBA Sunset Wilds","Wii Koopa Cape","Tour Vancouver Velocity","Tour Rome Avanti","GC DK Mountain","Wii Daisy Circuit","Tour Pilanha Plant Cove","Tour Madrid Drive","3DS Rosalina's Ice World","SFC Bowser Castle 3","Wii Rainbow Road"],"raw":{"1":"","2":"","3":"","4":"","5":"","6":"","7":"","8":"","9":"","10":"","11":"","12":"","13":"","14":"","15":"","16":"","17":"","18":"","19":"","20":"","21":"","22":"","23":"","24":"","25":"","26":"","27":"","28":"","29":"","30":"","31":"","32":"","33":"","34":"","35":"","36":"","37":"","38":"","39":"","40":"","41":"","42":"","43":"","44":"","45":"","46":"","47":"","48":"","49":"","50":"","51":"","52":"","53":"","54":"","55":"","56":"","57":"","58":"","59":"","60":"","61":"","62":"","63":"","64":"","65":"","66":"","67":"","68":"","69":"","70":"","71":"","72":"","73":"","74":"","75":"","76":"","77":"","78":"","79":"","80":"","81":"","82":"","83":"","84":"","85":"","86":"","87":"","88":"","89":"","90":"","91":"","92":"","93":"","94":"","95":"","96":""}},"messages":{"en":{"notregistered":"You haven't registered this track's time yet.","illegalformat":"Invalid time format.","tracknotexists":"Track doesn't exist.","sameasbest":"Time is the same as the best time.","fasterthanwr":"Your time is faster than current WR. \nPlease submit your WR on https://mkwrs.com/mk8dx/ Current WR: ","difference":"Difference","yourtime":"Your time","slowerthanbest":"Your time is slower than your best time. Your best: "},"ja":{"notregistered":"このトラックでのタイムが未申請です。","illegalformat":"タイムのフォーマットが無効です。","tracknotexists":"トラックが存在しません。","sameasbest":"ベストタイムと同じです。","fasterthanwr":"あなたのタイムは現在のWRより速いです。\nhttps://mkwrs.com/mk8dx/ であなたのタイムを申請してください。 WR: ","difference":"差","yourtime":"あなたのタイム","slowerthanbest":"あなたのタイムはあなたのベストタイムより遅いです。ベスト: "}},"wr":{"nita150":{"1":[99332,"かたゆ","https://www.google.com/url?q=https://youtu.be/uTPigvK0RBU?si%3D1VrBQ76dL4VPjO6l&sa=D&source=editors&ust=1749955155335253&usg=AOvVaw0WpKWrWPWyx_J480lrFMO7"],"2":[101327,"Panda","https://www.google.com/url?q=https://youtu.be/EBg0Zw73qak?si%3DhkdsMaJ9677jteIl&sa=D&source=editors&ust=1749955155335483&usg=AOvVaw1ycvO98RnT-n_ziccecZUh"],"3":[113549,"Gra","https://www.google.com/url?q=https://youtu.be/Xvp5eV2Wp8k?si%3Ddv7EZWBouNCaZBum&sa=D&source=editors&ust=1749955155335764&usg=AOvVaw0GxFd2jmzN2I6jzkQ9_v4d"],"4":[111820,"Panda","https://www.google.com/url?q=https://youtu.be/_ekFsiz841I?si%3DlUGFeZlUfUR79Htd&sa=D&source=editors&ust=1749955155335856&usg=AOvVaw3QCiWUWJN-8JusUdkalA5h"],"5":[107911,"Panda","https://www.google.com/url?q=https://youtu.be/GtzbC25DPKg?si%3DAFxXQ0NsX6MFkc-p&sa=D&source=editors&ust=1749955155350487&usg=AOvVaw0sMGvxXJYsF57gZjBe5FeW"],"6":[124610,"chigerungo","https://www.google.com/url?q=https://youtu.be/Z5QIjnNkWMU&sa=D&source=editors&ust=1749955155350700&usg=AOvVaw2soJ69-n6EmWYSbJxfudxx"],"7":[118644,"Panda","https://www.google.com/url?q=https://youtu.be/uZ-2vRgeDZI?si%3D7GYGKwhDVYnNVcbF&sa=D&source=editors&ust=1749955155350933&usg=AOvVaw3DdQYZHz7eF3pOTGCzk89C"],"8":[117956,"Isaac","https://www.google.com/url?q=https://www.youtube.com/watch?v%3DbYNQNHqjs_c&sa=D&source=editors&ust=1749955155351123&usg=AOvVaw2LLGpx4Cv7HEphGubKhl56"],"9":[120357,"らくbot","https://www.google.com/url?q=https://youtu.be/wqJecs3OU6M?feature%3Dshared&sa=D&source=editors&ust=1749955155367492&usg=AOvVaw21EnJRSTT_9Cknq1g8Vvfy"],"10":[116736,"piyopotechi","https://www.google.com/url?q=https://www.youtube.com/watch?v%3DK_NLHMKKoQo&sa=D&source=editors&ust=1749955155367822&usg=AOvVaw3uUIC30KqMqkd7i-opzXpY"],"11":[120429,"らくbot","https://www.google.com/url?q=https://youtu.be/umy1WwRb28g?feature%3Dshared&sa=D&source=editors&ust=1749955155368102&usg=AOvVaw3WoNs4hjPIv5S6xZW5L1nx"],"12":[103262,"龍神","https://www.google.com/url?q=https://youtu.be/f06bm_4ynYQ?si%3DSeOdMM2FjkCWy794&sa=D&source=editors&ust=1749955155368273&usg=AOvVaw2__mqjzhpvuhLlufzf53-n"],"13":[121968,"にら","https://www.google.com/url?q=https://youtu.be/UbOk9prR4kE&sa=D&source=editors&ust=1749955155383561&usg=AOvVaw3hyDiDa2QTstAdGQEyiv9D"],"14":[111278,"らくbot","https://www.google.com/url?q=https://youtu.be/lVlF1ov0uYo?feature%3Dshared&sa=D&source=editors&ust=1749955155383795&usg=AOvVaw3IRRj9r9W5UikvsFTLbFiL"],"15":[122417,"えくすと","https://www.google.com/url?q=https://youtu.be/0iTjzJ4LLe8?si%3DQYc3gn5F2iDmF149&sa=D&source=editors&ust=1749955155384058&usg=AOvVaw1psynP2Xi-cBx0vqGk2SKt"],"16":[120960,"ゆて","https://www.google.com/url?q=https://youtu.be/sIuzDGCYE4U?feature%3Dshared&sa=D&source=editors&ust=1749955155384143&usg=AOvVaw3J3cfIStWNTIwdvRTEOGhL"],"17":[86731,"ちくちくぴろんぴろん","https://www.google.com/url?q=https://www.youtube.com/watch?v%3DHPBx-7AJqnQ&sa=D&source=editors&ust=1749955155401558&usg=AOvVaw2EGBZ14uI7TzYWeEKfFcBI"],"18":[87146,"Panda","https://www.google.com/url?q=https://www.youtube.com/watch?v%3DBzB5PrrhhTE&sa=D&source=editors&ust=1749955155402029&usg=AOvVaw0SqkEyAWQ7o49HUDhokFve"],"19":[109257,"らくbot","https://www.google.com/url?q=https://youtu.be/jPZAhlTUuzk?feature%3Dshared&sa=D&source=editors&ust=1749955155402434&usg=AOvVaw29gzCHgvHl0aHQCk14qCFv"],"20":[107564,"ちくちくぴろんぴろん","https://www.google.com/url?q=https://youtu.be/IukL5ot0UqQ&sa=D&source=editors&ust=1749955155403086&usg=AOvVaw05u7rVtsYO1twePtkJntWP"],"21":[120166,"ちくちくぴろんぴろん","https://www.google.com/url?q=https://www.youtube.com/watch?v%3DYNFGjPQEmQo&sa=D&source=editors&ust=1749955155419187&usg=AOvVaw0tw4q4iyRvA88JqleEOGq5"],"22":[77001,"alpaco ","https://www.google.com/url?q=https://www.youtube.com/watch?v%3DR8vvcq9cm4Y&sa=D&source=editors&ust=1749955155419369&usg=AOvVaw2B1c4a3pZmVhfpp74mxxEq"],"23":[118752,"らくbot","https://www.google.com/url?q=https://youtu.be/eb-yJ5vDZf8?feature%3Dshared&sa=D&source=editors&ust=1749955155419458&usg=AOvVaw2u86lZcsSQDSRSXRkBNg3O"],"24":[123342,"Alberto","https://www.google.com/url?q=https://www.youtube.com/watch?v%3DzpyzZRW6oTk&sa=D&source=editors&ust=1749955155419642&usg=AOvVaw229taGUIiUL1v2yaIp7qjQ"],"25":[112486,"Lee","https://www.google.com/url?q=https://youtu.be/UdEbgF3ivCw&sa=D&source=editors&ust=1749955155434866&usg=AOvVaw199FSlHihCp4qw7TmFQFQU"],"26":[109804,"Mana","https://www.google.com/url?q=https://youtu.be/PueVnqjqSVs?si%3DpbA6BCL59Awpayyw&sa=D&source=editors&ust=1749955155435176&usg=AOvVaw0n1sbBIbnIUYF-02NAtBuX"],"27":[112021,"ちくちくぴろんぴろん","https://www.google.com/url?q=https://x.com/chikupilon_mk/status/1864282328950005973&sa=D&source=editors&ust=1749955155435360&usg=AOvVaw0QYUgBt4qOX2sDIDPHFoz7"],"28":[122460,"ちくちくぴろんぴろん","https://www.google.com/url?q=https://youtu.be/f0UoTSz1Ofg&sa=D&source=editors&ust=1749955155435537&usg=AOvVaw1Vc8kwKT33SJDZD6HJD_-Y"],"29":[103377,"すとーぶ","https://www.google.com/url?q=https://www.youtube.com/watch?v%3D4_R8Wymo_sU&sa=D&source=editors&ust=1749955155451198&usg=AOvVaw1CXfOANCDNANjRn_z2Lkk9"],"30":[123211,"Fuga","https://www.google.com/url?q=https://youtu.be/BSoCORqLH1s?si%3DBQCmOowf70Sd8S8s&sa=D&source=editors&ust=1749955155451314&usg=AOvVaw2CH6dTEEB6GRM2NYNhTh3i"],"31":[114936,"quartz","https://www.google.com/url?q=https://youtu.be/MnhtY7vyZvw?si%3DtqaOEq6dvHfWot6e&sa=D&source=editors&ust=1749955155451491&usg=AOvVaw3YGRsIMNrE1-c6yKVF2L7w"],"32":[80882,"Lafu","https://www.google.com/url?q=https://youtu.be/pxlH4W47108&sa=D&source=editors&ust=1749955155451811&usg=AOvVaw2iolSbvxxtDsij_V0NwomG"],"33":[105992,"calna","https://www.google.com/url?q=https://youtu.be/DUV4PQ55gPc?si%3D_wzroJqVuMNLkb74&sa=D&source=editors&ust=1749955155467124&usg=AOvVaw2_jA_FBHs17B8kMBWp5jw2"],"34":[102540,"まいす","https://www.google.com/url?q=https://www.youtube.com/live/g588doI23Nk?t%3D1h23m44s&sa=D&source=editors&ust=1749955155467386&usg=AOvVaw2pER6YD-0sMvTiuoJbdAb1"],"35":[104976,"Mana","https://www.google.com/url?q=https://youtu.be/683C5dJT0kk?si%3DUxL6XcyL_VjfghGF&sa=D&source=editors&ust=1749955155467585&usg=AOvVaw2p3DgfGZRnvbcUbWaKu8tg"],"36":[115892,"ふじほたる","https://www.google.com/url?q=https://youtu.be/vQLKOFuChxI&sa=D&source=editors&ust=1749955155467812&usg=AOvVaw3osfd55xqKfKSMvctFgl0c"],"37":[123551,"Panda","https://www.google.com/url?q=https://www.youtube.com/watch?v%3DKQtMUnHG9jg&sa=D&source=editors&ust=1749955155482717&usg=AOvVaw37QoK0t0la5mX1WfJpsiq2"],"38":[88456,"Jotrix","https://www.google.com/url?q=https://youtu.be/eYRy1iKpxSg&sa=D&source=editors&ust=1749955155482915&usg=AOvVaw0STQz9SjlxcF4Quk_bdYUl"],"39":[106998,"aybzq","https://www.google.com/url?q=https://youtu.be/NV-226w_RlM?si%3DMM3CpKBY-6owDrk6&sa=D&source=editors&ust=1749955155483213&usg=AOvVaw15FeU0ypyBv7DsZbyiLIjd"],"40":[110785,"Byron","https://www.google.com/url?q=https://youtu.be/_L_310B1Kzo&sa=D&source=editors&ust=1749955155483348&usg=AOvVaw0Sot2XOIsroF2ltxt8qNbL"],"41":[64257,"なきりおと","https://www.google.com/url?q=https://youtu.be/0hGaJeMKSQY?si%3D6snGYKPyGZbbIeuK&sa=D&source=editors&ust=1749955155498813&usg=AOvVaw2dp_Qj9BYkrNDAcTs10w7p"],"42":[108094,"Panda","https://www.google.com/url?q=https://www.youtube.com/watch?v%3DI4w6Z5CmsO8&sa=D&source=editors&ust=1749955155499007&usg=AOvVaw1e-H0rqyd8AYb4dQgwz-tQ"],"43":[107675,"ちくちくぴろんぴろん","https://www.google.com/url?q=https://m.youtube.com/watch?v%3Dd3iZOK31GUc&sa=D&source=editors&ust=1749955155499348&usg=AOvVaw3-EoeAmA4-3gjmjn4237iW"],"44":[100935,"ziline","https://www.google.com/url?q=https://youtu.be/iDtpYRvgnCo?si%3D5_iQhWQB35H_FoKX&sa=D&source=editors&ust=1749955155499569&usg=AOvVaw1g9gStnEEHPJdrvsgOwpTS"],"45":[106187,"Panda","https://www.google.com/url?q=https://www.youtube.com/watch?v%3DJ2JJ2p6qjy8&sa=D&source=editors&ust=1749955155516239&usg=AOvVaw2nM2Eh1qNzopMaeCNRHA1j"],"46":[110701,"¥146","https://www.google.com/url?q=https://youtu.be/J029EQKelFU?si%3Dcleo5lmtfYWU_bEP&sa=D&source=editors&ust=1749955155516442&usg=AOvVaw0OX92dCWvLRQ9263y46xvG"],"47":[103997,"かりま","https://www.google.com/url?q=https://youtu.be/hqBpX3DaZJw?si%3DzYbdW6dmjoICGHoP&sa=D&source=editors&ust=1749955155516779&usg=AOvVaw1s7aqJs32hzMoRpP57IhiX"],"48":[86263,"shi","https://www.google.com/url?q=https://twitter.com/shihomk8dx/status/1825813114899804300?t%3D5dUm1EPLs7-YBMUMqAUNTQ%26s%3D19&sa=D&source=editors&ust=1749955155516860&usg=AOvVaw1TJ9fhGKvu2r8eiUKp8Wd4"],"49":[111756,"ぐち","https://www.google.com/url?q=https://www.youtube.com/watch?v%3DKWsuSpC-VMA&sa=D&source=editors&ust=1749955155534791&usg=AOvVaw0_Z8yVIvrh7FQWY1Ls98_s"],"50":[83940,"shi","https://www.google.com/url?q=https://youtu.be/XBcW6S27JYc?si%3DdBYLUDOS2pMR9dMC&sa=D&source=editors&ust=1749955155535160&usg=AOvVaw1v4UYJMkdPaRHSmoDUHKug"],"51":[113621,"¥146","https://www.google.com/url?q=https://youtu.be/svey1E3XzA8?si%3DmouOOY2rTWfL9-Vf&sa=D&source=editors&ust=1749955155535524&usg=AOvVaw0EvyiLBmpTDay1xYWwA--s"],"52":[103695,"らくbot","https://www.google.com/url?q=https://youtu.be/1lw8j0yqrLo?feature%3Dshared&sa=D&source=editors&ust=1749955155535836&usg=AOvVaw0az4zXs-xw1AWbYl5UyKfp"],"53":[87486,"ぼあさん","https://www.google.com/url?q=https://youtu.be/M4eGjW_cUnk?si%3DMeNu13ezwwQ7AZ1l&sa=D&source=editors&ust=1749955155560474&usg=AOvVaw0cv5gkv04BheG94knP-pBY"],"54":[107773,"おいもsilver","https://www.google.com/url?q=https://youtu.be/KxQNcJuGxfA?si%3Dyy6kfNc8CgoGblCh&sa=D&source=editors&ust=1749955155560682&usg=AOvVaw0Rvl5LNWkLxAFryrRCJjTS"],"55":[89996,"Wish","https://www.google.com/url?q=https://youtu.be/pd17P_HObfo?feature%3Dshared&sa=D&source=editors&ust=1749955155560901&usg=AOvVaw0HLkhm5uGgKLUuybxOKiGW"],"56":[113902,"hana","https://www.google.com/url?q=https://youtu.be/ZrXD1Um_Ygc?si%3DbP0FkOGl5ECU7gU3&sa=D&source=editors&ust=1749955155561071&usg=AOvVaw0onuxxMv9FD2VpayIk5oOU"],"57":[84539,"ころまる","https://www.google.com/url?q=https://youtu.be/CmrktePXgyg?si%3DoS3p6pWxX3fV8V3l&sa=D&source=editors&ust=1749955155580470&usg=AOvVaw2pE6VyIihVfBU1HWQCkrIs"],"58":[95476,"ぼあさん","https://www.google.com/url?q=https://youtu.be/1vcIslhd9dA?si%3D-Vf3gWTF34jNnhhJ&sa=D&source=editors&ust=1749955155580564&usg=AOvVaw3nDYsvHH_L8gI45p6OvcX3"],"59":[93381,"まめ","https://www.google.com/url?q=https://youtu.be/AhXqDJZ0IWg?si%3DicTtDLkGFKEXOaZl&sa=D&source=editors&ust=1749955155580871&usg=AOvVaw3HLK0Yy5ELTRn-SQpmofN5"],"60":[140341,"らくbot","https://www.google.com/url?q=https://youtu.be/r6y1qY0Z-F0?feature%3Dshared&sa=D&source=editors&ust=1749955155580960&usg=AOvVaw0h9VN2DNBhVVRX_SXKbtBp"],"61":[122827,"Panda","https://www.google.com/url?q=https://youtu.be/pSkfnteexcs?si%3DUKygTIw3FkMaw4jt&sa=D&source=editors&ust=1749955155595195&usg=AOvVaw3Sgqd4Eso6sp6tgxcNgk-Y"],"62":[96247,"Panda","https://www.google.com/url?q=https://youtu.be/WJAnQ1WUZBI?si%3D5kipTEfeonUY4bFk&sa=D&source=editors&ust=1749955155595413&usg=AOvVaw0vrdLzcze_czAmV7JK8E7V"],"63":[95704,"shiho","https://www.google.com/url?q=https://youtu.be/p5pdBYBMzps?feature%3Dshared&sa=D&source=editors&ust=1749955155595598&usg=AOvVaw0MtzakpAYLzoyWngWul6j1"],"64":[115611,"ゆうき","https://www.google.com/url?q=https://youtu.be/DLMDakzML3E&sa=D&source=editors&ust=1749955155595877&usg=AOvVaw2XTSkLisEsoIU-sol2u60X"],"65":[131308,"かりま","https://www.google.com/url?q=https://youtu.be/9QN9GIrVufk?si%3D8xnooOq812sj8RY-&sa=D&source=editors&ust=1749955155610757&usg=AOvVaw2dAfntlYMoaRV-Iw9A2LSl"],"66":[82874,"ヨシ","https://www.google.com/url?q=https://youtu.be/FJk5O6LDtBo?si%3DyqwvMkiFCfsglzVB&sa=D&source=editors&ust=1749955155610942&usg=AOvVaw0dyN3qP7nb6ldQCYgEDbof"],"67":[135863,"らくbot","https://www.google.com/url?q=https://youtu.be/ISeXZIc4vpk?feature%3Dshared&sa=D&source=editors&ust=1749955155611032&usg=AOvVaw0yIVjM0tX215vWEW_WWxec"],"68":[145512,"aybzq","https://www.google.com/url?q=https://youtu.be/hssGI2m_AOc?si%3DYUsuY1iQ_kGj89ff&sa=D&source=editors&ust=1749955155611210&usg=AOvVaw1s1EL5y0WfsgII4E42xmtQ"],"69":[119394,"らくbot","https://www.google.com/url?q=https://youtu.be/4EqrJRRWkTQ?feature%3Dshared&sa=D&source=editors&ust=1749955155626799&usg=AOvVaw0JdyIc1qSKs8AqzzKYl15Q"],"70":[127733,"ラス","https://www.google.com/url?q=https://youtu.be/SaLiBuQ41os?si%3DJDZYiBkrRFoW_qBV&sa=D&source=editors&ust=1749955155627010&usg=AOvVaw1YbMohZ69NS8ljDz4P1DME"],"71":[115717,"かりま","https://www.google.com/url?q=https://youtu.be/SsmGqnqbXuE?si%3DaI39XdMy9Rzg9Q_i&sa=D&source=editors&ust=1749955155627279&usg=AOvVaw31MSVqf6D_19EueFeDwYJd"],"72":[98705,"ラス","https://www.google.com/url?q=https://youtu.be/y1eKyKlghB0?si%3D1HrienBUNKvXod6F&sa=D&source=editors&ust=1749955155627377&usg=AOvVaw26Jr28DbKsOGhcHmA9ck94"],"73":[97671,"Panda","https://www.google.com/url?q=https://youtu.be/9K5qu3IYSOY?si%3DEhf9C9m9qlWjkXKZ&sa=D&source=editors&ust=1749955155652529&usg=AOvVaw3wUsiXx7r3axQjSE8B8p2F"],"74":[91452,"Luckyo","https://www.google.com/url?q=https://www.youtube.com/watch?v%3Dt_fLFxc4ISg&sa=D&source=editors&ust=1749955155653240&usg=AOvVaw1QFcysWLSk-xSApB56f8bN"],"75":[116343,"YUTM","https://www.google.com/url?q=https://youtu.be/ADpKTE5yX7Y?si%3D2tMWrkhAoTUnK5rW&sa=D&source=editors&ust=1749955155653511&usg=AOvVaw0ZUzbNtDQWS_ldYFGjUmnE"],"76":[120250,"Kazuya","https://www.google.com/url?q=https://youtu.be/5PNeVm30QsE?si%3D8VhyxFVB2oT2a3Q1&sa=D&source=editors&ust=1749955155654130&usg=AOvVaw3Q1BI1A0JQU_QXzAe7PBvu"],"77":[104302,"¥146","https://www.google.com/url?q=https://youtu.be/CVacmUqEvLU?si%3DQyFhYDX59fBm_6H5&sa=D&source=editors&ust=1749955155671586&usg=AOvVaw3BXLAVGj3gvF1kdT3z4jqF"],"78":[101878,"Hoshiku","https://www.google.com/url?q=https://youtu.be/QN0oK_u2ETk?si%3Dc9kk9I1LFTd-fYNg&sa=D&source=editors&ust=1749955155671800&usg=AOvVaw3bR92XadOdjxdtkChJafko"],"79":[116748,"y","https://www.google.com/url?q=https://youtu.be/feE4G8YaUg8?si%3D0FsHwfRMsy-GreeA&sa=D&source=editors&ust=1749955155672064&usg=AOvVaw1X9X5ShSwriBFSGMB81u3K"],"80":[117759,"ぐち","https://www.google.com/url?q=https://www.youtube.com/watch?v%3DHSYCPxmnIiA&sa=D&source=editors&ust=1749955155672155&usg=AOvVaw1GpE4BQjXC_cyhpXKeE4C4"],"81":[100813,"ぐち","https://www.google.com/url?q=https://www.youtube.com/watch?v%3DzqVVRQ37bxc&sa=D&source=editors&ust=1749955155686525&usg=AOvVaw1q3Wn6XpIVXVVJPVH26_Xj"],"82":[95686,"Army","https://www.google.com/url?q=https://youtu.be/_-HypEbIVyI&sa=D&source=editors&ust=1749955155686792&usg=AOvVaw1spKzlq_kHmQVko5mta5Qi"],"83":[104332,"Lee","https://www.google.com/url?q=https://youtu.be/KfgZp1JfTPE&sa=D&source=editors&ust=1749955155686971&usg=AOvVaw2jKsKrUWmU-1QjCAFotzEG"],"84":[123403,"ちずば","https://www.google.com/url?q=https://youtu.be/dx1JVopx0Pk?si%3DS6QZDWXXaSgSG4_o&sa=D&source=editors&ust=1749955155687241&usg=AOvVaw2VvGoNdzxP-UK4Bp_TERRA"],"85":[109170,"Panda","https://www.google.com/url?q=https://youtu.be/gTbOaUJhPYg?si%3DswPV0p5f_8vkDMlQ&sa=D&source=editors&ust=1749955155701621&usg=AOvVaw1dAm1dJlqf6Gujm3k7YqQa"],"86":[97067,"lpsLaMuNe","https://www.google.com/url?q=https://drive.google.com/file/d/1MWqjrLv_deH6jJ8iXambiXD4OOXiI6Pt/view?usp%3Ddrive_link&sa=D&source=editors&ust=1749955155701932&usg=AOvVaw0E89TvkPkcKRxZldfhCeLL"],"87":[120914,"らくbot","https://www.google.com/url?q=https://youtu.be/J3v61p6_nzA?feature%3Dshared&sa=D&source=editors&ust=1749955155702028&usg=AOvVaw3aONOKnGo2v2P2CueEtQGC"],"88":[121612,"ぐち","https://www.google.com/url?q=https://www.youtube.com/watch?v%3DITlkV7BnO74&sa=D&source=editors&ust=1749955155702208&usg=AOvVaw0qdsbaAmL9-Or043IGIrpP"],"89":[107155,"さばとら","https://www.google.com/url?q=https://youtu.be/JsGB4Jg4W84&sa=D&source=editors&ust=1749955155717330&usg=AOvVaw3H4bFyD_sYL3OZgqSEAmHG"],"90":[129783,"kuzero","https://www.google.com/url?q=https://youtu.be/YU-TnMriawY?si%3D3K1TWITrPAM1LvXZ&sa=D&source=editors&ust=1749955155717503&usg=AOvVaw07gLXk-FKVY0BBFzdAx0pX"],"91":[110456,"fairy","https://www.google.com/url?q=https://youtu.be/gx_otn9EGU8?si%3DDSOYpIn5xFfue6Hy&sa=D&source=editors&ust=1749955155717684&usg=AOvVaw0Zx_I-v-wUIWqrx7exWE-S"],"92":[122570,"Alpaco","https://www.google.com/url?q=https://youtu.be/Ez4ausrZ2AQ&sa=D&source=editors&ust=1749955155717888&usg=AOvVaw1szCaKguaP-BNY9RYKRmzm"],"93":[119913,"らくbot","https://www.google.com/url?q=https://youtu.be/5Bn6Tyit3a4?feature%3Dshared&sa=D&source=editors&ust=1749955155736241&usg=AOvVaw0VyEqvmb3b3_jLXQDJyJfX"],"94":[119739,"えくすと","https://www.google.com/url?q=https://youtu.be/9FTlzjZrID4?si%3DFdlRu4NWXEJ2yf0i&sa=D&source=editors&ust=1749955155736602&usg=AOvVaw0QL24GJaOlxM0Qw9k_vtXu"],"95":[102796,"faz","https://www.google.com/url?q=https://youtu.be/bPrU5kcYDqg?si%3DZaDU5_VHICkbuRm8&sa=D&source=editors&ust=1749955155736775&usg=AOvVaw1_80EkV1MYCivvfuWg1hg2"],"96":[154668,"Yoshiyoshi","https://www.google.com/url?q=https://youtu.be/OtwxgpFGcNM?si%3DmF28hZwYUuHhDD_S&sa=D&source=editors&ust=1749955155736864&usg=AOvVaw0RMsPksTp7gm_ChwSvooaT"]},"nita200":{"1":[71438,"Thomas","https://www.google.com/url?q=https://youtu.be/y5dRCIdjr-M&sa=D&source=editors&ust=1749955165538149&usg=AOvVaw1jnomjKNZBiOknC89vDZtB"],"2":[73839,"Alberto","https://www.google.com/url?q=https://www.youtube.com/watch?v%3Df73861sWPVQ&sa=D&source=editors&ust=1749955165538813&usg=AOvVaw3U1uGCH2sZOPhp7a85HOQS"],"3":[87136,"amber","https://www.google.com/url?q=https://www.youtube.com/watch?v%3DCv0gYU9bb6U&sa=D&source=editors&ust=1749955165539474&usg=AOvVaw3EroaXvEX4Uk77_f0o0BjO"],"4":[79815,"Alberto","https://www.google.com/url?q=https://youtu.be/ZFQGk2OO1Yo&sa=D&source=editors&ust=1749955165540162&usg=AOvVaw07iOHL5JHFyC8tXs6MLZHg"],"5":[76722,"核熱","https://www.google.com/url?q=https://youtu.be/5UKhurwDeXE&sa=D&source=editors&ust=1749955165582893&usg=AOvVaw2Ozz4N1YLmt1fcxo3GrgJf"],"6":[92719,"amber","https://www.google.com/url?q=https://www.youtube.com/watch?v%3D5Xis8FjDgGI&sa=D&source=editors&ust=1749955165583478&usg=AOvVaw1eObxwjI-EVPT7DiR3li_8"],"7":[87754,"alpha","https://www.google.com/url?q=https://www.youtube.com/watch?v%3DNcbaAei_G1Y%26t&sa=D&source=editors&ust=1749955165584160&usg=AOvVaw0BtGPjivabxDvyD268MWKg"],"8":[90403,"alpha","https://www.google.com/url?q=https://www.youtube.com/watch?v%3DDMWyfhpEp_k&sa=D&source=editors&ust=1749955165584993&usg=AOvVaw1ki5eL9ickCFURS9hQm6vC"],"9":[93449,"Ander","https://www.google.com/url?q=https://www.youtube.com/watch?v%3D7gn304OKeqU&sa=D&source=editors&ust=1749955165637514&usg=AOvVaw2cAdFcGzxusqIyuAR2STd3"],"10":[84877,"Thomas","https://www.google.com/url?q=https://youtu.be/3guO1hd2hKQ&sa=D&source=editors&ust=1749955165638236&usg=AOvVaw0n18eCk4wnKZ1y2uXkancF"],"11":[87759,"Army","https://www.google.com/url?q=https://www.youtube.com/watch?v%3DgxMoMI54Iy0&sa=D&source=editors&ust=1749955165638859&usg=AOvVaw2ZQG4IAgB8n0dT959QTsXg"],"12":[78083,"Technical","https://www.google.com/url?q=https://www.youtube.com/watch?v%3D0gbTo_gAEKU&sa=D&source=editors&ust=1749955165639467&usg=AOvVaw1qlxxDHUMrf9stTSEDp8oe"],"13":[90977,"Alberto","https://www.google.com/url?q=https://www.youtube.com/watch?v%3DCBgNUTuS2R4%26t&sa=D&source=editors&ust=1749955165687131&usg=AOvVaw1YSxhG6_Zkf6TnfP71inNV"],"14":[83859,"Thomas","https://www.google.com/url?q=https://youtu.be/8mg6uNmCNFw&sa=D&source=editors&ust=1749955165688081&usg=AOvVaw2CGTEMC5Xbp207W-HMIDBd"],"15":[89490,"Technical","https://www.google.com/url?q=https://www.youtube.com/watch?v%3DorNCAj0uGu8&sa=D&source=editors&ust=1749955165689022&usg=AOvVaw3v7SHOAO853dwkTd_Fx1uP"],"16":[94794,"Awoken","https://www.google.com/url?q=https://www.youtube.com/watch?v%3D4GwTh5qBa80&sa=D&source=editors&ust=1749955165689954&usg=AOvVaw1lXADlOp6E4x-P19bzDwgc"],"17":[62562,"Alex","https://www.google.com/url?q=https://youtu.be/F14zci3Pa7w?si%3DcV08Qmts-M4zFyJd&sa=D&source=editors&ust=1749955165731806&usg=AOvVaw2cH1mb3C7pN8SixRjY49x9"],"18":[65173,"Alberto","https://www.google.com/url?q=https://www.youtube.com/watch?v%3D9FbAUlv21PY&sa=D&source=editors&ust=1749955165732424&usg=AOvVaw00lQnbcT9kateRd_EHV2dP"],"19":[77830,"Thomas","https://www.google.com/url?q=https://youtu.be/xuTuDvPrMRs&sa=D&source=editors&ust=1749955165733065&usg=AOvVaw3QLmTZAaiLq5HR7QFAFmRt"],"20":[75777,"alpha","https://www.google.com/url?q=https://www.youtube.com/watch?v%3D0-sFjjp6mC0&sa=D&source=editors&ust=1749955165733686&usg=AOvVaw3oPfbxt0Fve6Y-oJxe9orJ"],"21":[84193,"Panda","https://www.google.com/url?q=https://www.youtube.com/watch?v%3D7BtLnll9jXo&sa=D&source=editors&ust=1749955165776339&usg=AOvVaw2PZftkh6GTCIto5VBSB4q7"],"22":[60737,"Falkmanhi","https://www.google.com/url?q=https://youtu.be/lDABzjPi6k4?si%3Dcp0RMHnM1WtGn-br&sa=D&source=editors&ust=1749955165776960&usg=AOvVaw16K3UJORr8eehkxK9G-MEy"],"23":[90520,"amber","https://www.google.com/url?q=https://www.youtube.com/watch?v%3DK3UlfQPKwuI&sa=D&source=editors&ust=1749955165777568&usg=AOvVaw0ZdfuMxShasQu2W167KHu1"],"24":[89870,"Thomas","https://www.google.com/url?q=https://youtu.be/IVD_0WHa9L8&sa=D&source=editors&ust=1749955165778256&usg=AOvVaw12gsR4cW4H24ZVXbSJegZ2"],"25":[83824,"Army","https://www.google.com/url?q=https://youtu.be/9PHQqwVyhqE?si%3D32aSn9XAtv1qyf8f&sa=D&source=editors&ust=1749955165823746&usg=AOvVaw02ZAnQvcc2BmSSYcXN4EO6"],"26":[81660,"alpha","https://www.google.com/url?q=https://www.youtube.com/watch?v%3DNk8Ke7i7yaY&sa=D&source=editors&ust=1749955165824392&usg=AOvVaw2wDT6NoRFmgacN2lODz3hx"],"27":[86985,"alpha","https://www.google.com/url?q=https://www.youtube.com/watch?v%3DypLSowOz1Oo&sa=D&source=editors&ust=1749955165824998&usg=AOvVaw0-9z8vtW1iQO26B9lbrKca"],"28":[91413,"Eternal","https://www.google.com/url?q=https://youtu.be/Zdvl53UgBz4&sa=D&source=editors&ust=1749955165825627&usg=AOvVaw18W3FpUPbhQabfRegtWSca"],"29":[76409,"Elmer","https://www.google.com/url?q=https://www.youtube.com/watch?v%3DBg-OJkVIhEs&sa=D&source=editors&ust=1749955165864521&usg=AOvVaw0NGbDxDZy6UoFudLWs326T"],"30":[90758,"Anthony","https://www.google.com/url?q=https://www.youtube.com/watch?v%3DGmYNRS8nmEY&sa=D&source=editors&ust=1749955165865168&usg=AOvVaw1S3hjOmGwtRsKTJ0naRWYV"],"31":[85212,"Alberto","https://www.google.com/url?q=https://youtu.be/SJX6WVbqRMA&sa=D&source=editors&ust=1749955165865795&usg=AOvVaw3dVAnsRmh-O_MXltrnd-nU"],"32":[0,"Alvin","https://www.google.com/url?q=https://youtu.be/oYKmKErkFCs?feature%3Dshared&sa=D&source=editors&ust=1749955165866389&usg=AOvVaw1MpLJZHZ3dgsqIrnQAfgOr"],"33":[78819,"Army","https://www.google.com/url?q=https://www.youtube.com/watch?v%3DQfbIMBt96QQ&sa=D&source=editors&ust=1749955165917282&usg=AOvVaw1H8rZIBmo-7zcdctyIGPbQ"],"34":[78803,"Prilin","https://www.google.com/url?q=https://youtu.be/0KL7i304frI&sa=D&source=editors&ust=1749955165917975&usg=AOvVaw21O25mTVEcQg9YYLKBl3BF"],"35":[80475,"Alberto","https://www.google.com/url?q=https://www.youtube.com/watch?v%3DrEqZhiLUn8I&sa=D&source=editors&ust=1749955165918657&usg=AOvVaw1IWg0DP4mQSYZrnmZT3tp9"],"36":[84385,"Alberto","https://www.google.com/url?q=https://www.youtube.com/watch?v%3DJALQ-fubAgg&sa=D&source=editors&ust=1749955165919280&usg=AOvVaw2DksTsx_E1M5WYSDLPikd4"],"37":[87775,"Alberto","https://www.google.com/url?q=https://www.youtube.com/watch?v%3Ddjsq8eJeX3c&sa=D&source=editors&ust=1749955165954082&usg=AOvVaw3YepqUv6iRLFLlSFidc0cx"],"38":[63647,"alpha","https://www.google.com/url?q=https://youtu.be/Cklb0gRMpMs&sa=D&source=editors&ust=1749955165954730&usg=AOvVaw0lqYoT5ansR4MwP3FwkCdA"],"39":[79279,"ラス","https://www.google.com/url?q=https://youtu.be/YbbiiGutuJI?si%3DOgjVVZV86kRxTIp4&sa=D&source=editors&ust=1749955165955345&usg=AOvVaw1F0Dv2Ru1jff-iTCNmG271"],"40":[83646,"Thomas","https://www.google.com/url?q=https://youtu.be/-9sz6sQkTL4&sa=D&source=editors&ust=1749955165955973&usg=AOvVaw3-ilgFWawRtC4ajk7g0Jcu"],"41":[0,"Army","https://www.google.com/url?q=https://www.youtube.com/watch?v%3Dsxwkdzy2YaM&sa=D&source=editors&ust=1749955166002156&usg=AOvVaw0MClsP5UNFK0x2_AhdJ3AP"],"42":[82061,"Falkmanhi","https://www.google.com/url?q=https://youtu.be/uAbctzbVOVM?si%3DCOFZIgal1tGOv_YO&sa=D&source=editors&ust=1749955166003187&usg=AOvVaw1GsQUwU0_oMmPasxXynE1F"],"43":[79265,"Technical","https://www.google.com/url?q=https://www.youtube.com/watch?v%3DB9-xZNhjWHM&sa=D&source=editors&ust=1749955166004271&usg=AOvVaw1a3XMECtqiCNCshhtIvjdd"],"44":[74542,"Flour","https://www.google.com/url?q=https://youtu.be/gPiWbTpYFT0?si%3DWU4v1Unt_TTAvN8d&sa=D&source=editors&ust=1749955166005283&usg=AOvVaw3fd92Vuzy_WyBOESl257pc"],"45":[82943,"Alberto","https://www.google.com/url?q=https://www.youtube.com/watch?v%3DEWAchm0O2yg&sa=D&source=editors&ust=1749955166049034&usg=AOvVaw2je_oF0s9rcf_9-lKPBnmz"],"46":[81331,"Technical","https://www.google.com/url?q=https://www.youtube.com/watch?v%3DxXWsZJIfy6Q&sa=D&source=editors&ust=1749955166049749&usg=AOvVaw1iBx-qNtrZoRzDifDenZDw"],"47":[75946,"Alberto","https://www.google.com/url?q=https://youtu.be/HelApJ2fad8&sa=D&source=editors&ust=1749955166050405&usg=AOvVaw2A9e-ZCoDw9gZXZMWeatPh"],"48":[63383,"Alberto","https://www.google.com/url?q=https://www.youtube.com/watch?v%3D8uTBmGkLM5k&sa=D&source=editors&ust=1749955166051043&usg=AOvVaw1UyoBd490Oe8VvhUIyeTaz"],"49":[78988,"Technical","https://www.google.com/url?q=https://youtu.be/mb633avPz90&sa=D&source=editors&ust=1749955166096885&usg=AOvVaw1eTUgoimVnMlgHPrZCsZ-4"],"50":[59691,"Technical","https://www.google.com/url?q=https://youtu.be/rl22EgWS1SU&sa=D&source=editors&ust=1749955166097718&usg=AOvVaw11hzi-0AjI-CZOex4lPe4Y"],"51":[82304,"Mr. Cloud Kirby","https://www.google.com/url?q=https://youtu.be/pJaP5K5g7rc?si%3DLueT6DbXvj6INpWD&sa=D&source=editors&ust=1749955166098558&usg=AOvVaw3a6yhKWcbgJuFILuW2oAHF"],"52":[77510,"Thomas","https://www.google.com/url?q=https://youtu.be/fP_wlYFupjA&sa=D&source=editors&ust=1749955166099418&usg=AOvVaw19-Q9jeAzpCQn79tUKckZ5"],"53":[60945,"Technical","https://www.google.com/url?q=https://youtu.be/1jidjsRfWzw&sa=D&source=editors&ust=1749955166147243&usg=AOvVaw3n2d4NCzzUf9tjWk_wmYGL"],"54":[80022,"Army","https://www.google.com/url?q=https://youtu.be/rGK9watUphg&sa=D&source=editors&ust=1749955166147955&usg=AOvVaw1FjiXp_rCp7-Fi4tsNvEc2"],"55":[65734,"Alberto","https://www.google.com/url?q=https://www.youtube.com/watch?v%3DK2CGiVw0if0&sa=D&source=editors&ust=1749955166148644&usg=AOvVaw1JhI8A-aLsxUHYYwBDXYz8"],"56":[87151,"SKaR","https://www.google.com/url?q=https://www.youtube.com/watch?v%3DQbO8BZHXLF8&sa=D&source=editors&ust=1749955166149255&usg=AOvVaw0qdRxj0JjqVsT-x7Hd_GbV"],"57":[61489,"Thomas","https://www.google.com/url?q=https://youtu.be/j3LcEo0OFqg&sa=D&source=editors&ust=1749955166199709&usg=AOvVaw316GJhRrKli1jjjAlKBqnz"],"58":[68982,"Arito","https://www.google.com/url?q=https://x.com/Arito_RA/status/1839556674216251540?t%3DKJlBZyH5c4DZsIuHPnbKTw%26s%3D19&sa=D&source=editors&ust=1749955166200598&usg=AOvVaw3koeRKm3oZL3LgnNj8DPdb"],"59":[66086,"Army","https://www.google.com/url?q=https://www.youtube.com/watch?v%3DFADsgIf1PF4&sa=D&source=editors&ust=1749955166201578&usg=AOvVaw35OiKXiOxwfBOKM0OU3ptY"],"60":[108441,"Technical","https://www.google.com/url?q=https://www.youtube.com/watch?v%3DM23YvBOztVo&sa=D&source=editors&ust=1749955166202477&usg=AOvVaw1RHpxHhaomvl5UHHfiNfz4"],"61":[87901,"Vincent","https://www.google.com/url?q=https://www.youtube.com/watch?v%3DS9Dhwh1lcHs&sa=D&source=editors&ust=1749955166249936&usg=AOvVaw1PapqTtEl4n2FC9ci_CBLY"],"62":[71710,"Thomas","https://www.google.com/url?q=https://youtu.be/6WAsMUFViYE&sa=D&source=editors&ust=1749955166250511&usg=AOvVaw27SjD9AdjaVD2Cv0XCNjyJ"],"63":[68079,"Alvin","https://www.google.com/url?q=https://www.instagram.com/reel/DHSh0VUTqRt/?igsh%3DMXVzb2QwcjNveWNuaA%3D%3D&sa=D&source=editors&ust=1749955166251153&usg=AOvVaw3cXoLluH2SuVuBLddJ9GIV"],"64":[82670,"Technical","https://www.google.com/url?q=https://www.youtube.com/watch?v%3DaSPU07_0gjg&sa=D&source=editors&ust=1749955166251742&usg=AOvVaw0HJP-hhupBrr4xqyvwJNsL"],"65":[92822,"Technical","https://www.google.com/url?q=https://www.youtube.com/watch?v%3DrcbP1a5tODQ&sa=D&source=editors&ust=1749955166302111&usg=AOvVaw3XWXsy6q0uCZIGqyoyYMLq"],"66":[61988,"Army","https://www.google.com/url?q=https://www.youtube.com/watch?v%3DNX-9ZlTAfkI&sa=D&source=editors&ust=1749955166303027&usg=AOvVaw3er7L6ZFLAqd3tzhVhERLG"],"67":[94932,"Technical","https://www.google.com/url?q=https://www.youtube.com/watch?v%3DBl2QKUakucc&sa=D&source=editors&ust=1749955166303878&usg=AOvVaw2nl8bEej6TjR-7WV31qQ7i"],"68":[112157,"Technical","https://www.google.com/url?q=https://youtu.be/2XzP96Xtu8o&sa=D&source=editors&ust=1749955166304684&usg=AOvVaw2eVf972lGPiGTT445XSUgE"],"69":[85351,"Army","https://www.google.com/url?q=https://www.youtube.com/watch?v%3DXyOYFoVmH0k&sa=D&source=editors&ust=1749955166348039&usg=AOvVaw02LoFex3uVu_D_-fhZQa9n"],"70":[89738,"Thomas","https://www.google.com/url?q=https://youtu.be/S7oXz3rfrkA&sa=D&source=editors&ust=1749955166348728&usg=AOvVaw18SJDzuOnFlAlVElD9LhMs"],"71":[83603,"かりま","https://www.google.com/url?q=https://youtu.be/nUfErmuXjeI?si%3DgkSuzYz_7zdBPuYI&sa=D&source=editors&ust=1749955166349471&usg=AOvVaw09xWSKlIYapC_6pkw5gHbr"],"72":[71832,"Elmer","https://www.google.com/url?q=https://www.youtube.com/watch?v%3DmONR8fosczg&sa=D&source=editors&ust=1749955166350226&usg=AOvVaw3E0KSQuGBzCzn0XgAwmMWc"],"73":[70399,"Thomas","https://www.google.com/url?q=https://youtu.be/r0RyNW2ybXw&sa=D&source=editors&ust=1749955166395623&usg=AOvVaw072U-x78E6fBpfN_W03Ou7"],"74":[67552,"yellow","https://www.google.com/url?q=https://photos.app.goo.gl/GiJTaRwdMZNFbqid8&sa=D&source=editors&ust=1749955166396407&usg=AOvVaw3Bg0kXTK13-0fE4llpsjG3"],"75":[95136,"Alvin","https://www.google.com/url?q=https://youtu.be/d_OUAsJUyYM?si%3D2nnsTyofbh3sI24w&sa=D&source=editors&ust=1749955166397196&usg=AOvVaw1Awyh06XACw7osN2XGqQ5v"],"76":[89770,"Thomas","https://www.google.com/url?q=https://youtu.be/k40F4M5QQEE&sa=D&source=editors&ust=1749955166397998&usg=AOvVaw1k_GH0-5pQb-Uj0FqDZcfS"],"77":[74885,"Thomas","https://www.google.com/url?q=https://youtu.be/XzD0SZKA9-4&sa=D&source=editors&ust=1749955166434047&usg=AOvVaw2leFUdBEj6zG-qsoKkMNJQ"],"78":[74579,"SKaR","https://www.google.com/url?q=https://www.youtube.com/watch?v%3DPBeKyhSYQJM&sa=D&source=editors&ust=1749955166434666&usg=AOvVaw1YoAYWAbEA01D60asPvQ_P"],"79":[91299,"Thomas","https://www.google.com/url?q=https://youtu.be/qCa0g74l9hs&sa=D&source=editors&ust=1749955166435243&usg=AOvVaw0N72AJRUABSYpGhLKnIwkQ"],"80":[83974,"Thomas","https://www.google.com/url?q=https://youtu.be/J2hKza3gzk4&sa=D&source=editors&ust=1749955166435843&usg=AOvVaw3KkF6eghZu_mqs4fVmvyY5"],"81":[73511,"Technical","https://www.google.com/url?q=https://youtu.be/CFcvUky3p_s&sa=D&source=editors&ust=1749955166474957&usg=AOvVaw2i3Y1j_lRZEQKw3HyuH6t0"],"82":[70663,"Technical","https://www.google.com/url?q=https://youtu.be/aAvL3qGUurA&sa=D&source=editors&ust=1749955166475656&usg=AOvVaw3C-LncvWRI_t5xfgShAYjC"],"83":[75088,"zill","https://www.google.com/url?q=https://www.youtube.com/watch?v%3DRHkO3bUYjlI&sa=D&source=editors&ust=1749955166476302&usg=AOvVaw2K4qS-ZOlPwOgby1fyO-A2"],"84":[88231,"konni","https://www.google.com/url?q=https://www.youtube.com/watch?v%3Dy4jUD3mD0h8&sa=D&source=editors&ust=1749955166476878&usg=AOvVaw3ej9EgUl6_DNqN0J76ILW0"],"85":[78300,"Flour","https://www.google.com/url?q=https://youtu.be/Za3qhyLG9uQ?si%3D8i_-9piVYnYNnBjb&sa=D&source=editors&ust=1749955166515686&usg=AOvVaw28zpS8X0FsYQlSdUr9ee7e"],"86":[71976,"Kouta.","https://www.google.com/url?q=https://youtu.be/6i8DjHYIZGI&sa=D&source=editors&ust=1749955166516561&usg=AOvVaw38L7IEYsVz-gvoYGwyNZpy"],"87":[88305,"Technical","https://www.google.com/url?q=https://youtu.be/EWqSPkIVWI0&sa=D&source=editors&ust=1749955166517386&usg=AOvVaw28QJCHOWiGar8psVzk0gDh"],"88":[87809,"zill","https://www.google.com/url?q=https://www.youtube.com/watch?v%3DqDLC5I8JAyQ&sa=D&source=editors&ust=1749955166518188&usg=AOvVaw3HabQ9fdlurKqepJsiWhCO"],"89":[77681,"Naoto","https://www.google.com/url?q=https://youtu.be/srtK1hqoMiQ?si%3DltoL4sPuucSXziej&sa=D&source=editors&ust=1749955166545496&usg=AOvVaw3ZJZ6Zmzx2wPGQucepkYyf"],"90":[108884,"Toshiki","https://www.google.com/url?q=https://youtu.be/HlH1Muwoyr0&sa=D&source=editors&ust=1749955166546087&usg=AOvVaw22M08r20PcMfScDJGq7Yzh"],"91":[79377,"Samuel","https://www.google.com/url?q=https://www.youtube.com/watch?v%3D0h9bB-imYUA&sa=D&source=editors&ust=1749955166546725&usg=AOvVaw1xsmUCgOpWQqTrdik83Yek"],"92":[88713,"konni","https://www.google.com/url?q=https://youtu.be/nNkk0YpYi-0&sa=D&source=editors&ust=1749955166547385&usg=AOvVaw0WlkolefyvrTUOyipY0CAi"],"93":[85808,"Flour","https://www.google.com/url?q=https://youtu.be/5z3azwF1grI?si%3DH0g4nFfIdmg6QF2W&sa=D&source=editors&ust=1749955166579692&usg=AOvVaw1twJu-7XoKi0yGMWi8zzKn"],"94":[89693,"Wood22","https://www.google.com/url?q=https://youtu.be/RiPPMRUN4f0?si%3DzqY6TD44QapX5Xte&sa=D&source=editors&ust=1749955166580166&usg=AOvVaw2q4yFzZF6W4NHJ7oO0m-qn"],"95":[76535,"Elmer","https://www.google.com/url?q=https://youtu.be/dWy8PNb9pkQ&sa=D&source=editors&ust=1749955166580741&usg=AOvVaw1GgcxuOZv6zl5tcmxGdB5p"],"96":[114981,"B Yoru","https://www.google.com/url?q=https://youtu.be/RYcskncidY4?si%3DCsztZJu2jT6Yx5WN&sa=D&source=editors&ust=1749955166581300&usg=AOvVaw3pqV8-NzdQDTDWyqGPE0s7"]},"ta150":{"1":[94277,"しらぬい","https://www.youtube.com/watch?v=f178X-eHEto"],"2":[98995,"Vincent","https://www.youtube.com/watch?v=02TkOgMD-Qg"],"3":[108030,"Vincent","https://www.youtube.com/watch?v=EoehsIVq3-Q"],"4":[107080,"Panda","https://www.youtube.com/watch?v=WB59kvCa68w"],"5":[103723,"Vincent","https://www.youtube.com/watch?v=e-SOkLrSgpg"],"6":[121586,"なすの","https://www.youtube.com/watch?v=2CnwKPnLlTc"],"7":[113354,"Alberto","https://youtu.be/3ndwXMfV50s"],"8":[115279,"Yerson","https://www.youtube.com/watch?v=yssM9sKoevM"],"9":[116971,"Vincent","https://www.youtube.com/watch?v=hc3WYtlCbVg"],"10":[111951,"StervtL","https://www.youtube.com/watch?v=0KsT5AnwXAc"],"11":[115086,"Alberto","https://www.youtube.com/watch?v=jAEcZZ3Lj6M"],"12":[100545,"F。","https://www.youtube.com/watch?v=3ZnHO8Q0464"],"13":[119262,"F。","https://www.youtube.com/watch?v=r0k4n3oX19Y"],"14":[106413,"Army","https://www.youtube.com/watch?v=RDjIYAVE3NA"],"15":[117655,"Vincent","https://youtu.be/tibmjUAnRVg"],"16":[118454,"Alberto","https://youtu.be/HNT0st5ePqo"],"17":[83642,"Panda","https://www.youtube.com/watch?v=2R46yX3twqs"],"18":[58517,"Albert","https://www.youtube.com/watch?v=KVgc9D5R5EU"],"19":[59892,"StervtL","https://www.youtube.com/watch?v=uaEmg6ATdEo"],"20":[75569,"Alberto","https://youtu.be/lPMQF1NjN7Y?si=0ScZmSM6c5OG5O24"],"21":[71977,"Alphabet Soup","https://youtu.be/DA9BP3X391g"],"22":[76879,"Panda","https://youtu.be/JK10RFNKDeo"],"23":[55241,"JenZua","https://www.youtube.com/watch?v=wOngIj1x_Rw"],"24":[83413,"Technical","https://www.youtube.com/watch?v=E3bYUdaTGh4"],"25":[87316,"Panda","https://www.youtube.com/watch?v=RBukMzcLvLU"],"26":[81128,"Pii","https://www.youtube.com/watch?v=CSYslhqZgVA"],"27":[76130,"Alberto","https://www.youtube.com/watch?v=E4Qegv_QCCI"],"28":[83309,"Alberto","https://www.youtube.com/watch?v=wD0SK8CZnwc"],"29":[83992,"Alberto","https://www.youtube.com/watch?v=lGoatvaM7Jo"],"30":[72991,"Alberto",null],"31":[86082,"Pii","https://www.youtube.com/watch?v=xd5rI8wg0d4"],"32":[81673,"Hgt","https://www.youtube.com/watch?v=8XfhPNlIFsg"],"33":[56335,"kwartz","https://www.youtube.com/watch?v=T7RP6M-cGMU"],"34":[73025,"Army","https://www.youtube.com/watch?v=yYV9BnvqIqE"],"35":[73889,"しらぬい","https://www.youtube.com/watch?v=hsYvYs4PQmA"],"36":[100081,"Alberto","https://www.youtube.com/watch?v=l07fps_68nA"],"37":[110788,"StervtL","https://www.youtube.com/watch?v=5XNqlk0Fp-I"],"38":[121373,"Vincent","https://www.youtube.com/watch?v=9-n6nxPRrgk"],"39":[85569,"Vincent","https://www.youtube.com/watch?v=Fdw_09Kn-VE"],"40":[104738,"Alberto","https://www.youtube.com/watch?v=inc-eNkSo_U"],"41":[76926,"grace","https://www.youtube.com/watch?v=rg-R4BXxG8k"],"42":[79631,"JenZua",null],"43":[44731,"alpha","https://www.youtube.com/watch?v=7LSoZfVAKfk"],"44":[74917,"alpha","https://www.youtube.com/watch?v=JduphBt80w4"],"45":[76609,"Alberto","https://www.youtube.com/watch?v=5CjiHfzGhOY"],"46":[70407,"4laps2win","https://www.youtube.com/watch?v=vq3Lb62fRvg"],"47":[78871,"Alberto","https://youtu.be/f9V8qU5wJ9Q"],"48":[76949,"Army","https://www.youtube.com/watch?v=2l1KZIgyDAA"],"49":[72788,"Alberto",null],"50":[60361,"FA","https://www.youtube.com/watch?v=lNQsHaQDQeo"],"51":[76395,"Army","https://www.youtube.com/watch?v=GitYX9Ulem4"],"52":[56489,"Army","https://www.youtube.com/watch?v=2HGIfNhOeZI"],"53":[79651,"Vincent","https://www.youtube.com/watch?v=g0F5_VnykZw"],"54":[73865,"Army","https://www.youtube.com/watch?v=oYfJB0uDxXA"],"55":[58852,"Alberto","https://youtu.be/cTwX9-lIH6o"],"56":[75426,"Alberto","https://www.youtube.com/watch?v=QxgAJpeusGI"],"57":[61722,"Technical","https://youtu.be/DAi7K8LO8n0"],"58":[84193,"Panda","https://www.youtube.com/watch?v=5_mycIie7hA"],"59":[58262,"Army","https://www.youtube.com/watch?v=UGOl7374cHU"],"60":[64323,"JenZua","https://www.youtube.com/watch?v=wm4I5EoG7p4"],"61":[60995,"Panda",null],"62":[105773,"Technical","https://www.youtube.com/watch?v=qzkKfuwdH38"],"63":[84349,"Vincent","https://www.youtube.com/watch?v=69Ncs_NHgw0"],"64":[64209,"Alberto","https://www.youtube.com/watch?v=DfsfF8nbxLI"],"65":[61808,"4laps2win","https://www.youtube.com/watch?v=yXug6Wcc1W4"],"66":[79467,"Draygo","https://www.youtube.com/watch?v=R_2fYIrJ69g"],"67":[88528,"Army","https://www.youtube.com/watch?v=uUdDTH83dp4"],"68":[59359,"Pii","https://www.youtube.com/watch?v=sZuRmtDp3aQ"],"69":[87316,"grace","https://youtu.be/ghbJbUwcEwk"],"70":[108764,"Vincent","https://www.youtube.com/watch?v=7rrppUxcGVM"],"71":[81802,"Army","https://www.youtube.com/watch?v=AMbN23iCuok"],"72":[86018,"Army","https://www.youtube.com/watch?v=gbqlxONCMjM"],"73":[78541,"bup","https://www.youtube.com/watch?v=DM1LCf4iHX8"],"74":[69446,"Technical","https://www.youtube.com/watch?v=eo4gQN_U6K0"],"75":[66568,"Technical","https://www.youtube.com/watch?v=YF8bS0Gigic"],"76":[62066,"Mirai","https://www.youtube.com/watch?v=bWcGyRY4_pw"],"77":[91428,"Technical","https://www.youtube.com/watch?v=OnH5H0aeI7c"],"78":[85990,"Technical","https://www.youtube.com/watch?v=rsmsi1pijg4"],"79":[72953,"Alberto","https://www.youtube.com/watch?v=xXcLaw4z_Is"],"80":[70765,"Pii","https://www.youtube.com/watch?v=1hcEIph-d-0"],"81":[85178,"JenZua","https://www.youtube.com/watch?v=SffAUF6WAzE"],"82":[80774,"Alberto","https://www.youtube.com/watch?v=IHKLpZhVkq8"],"83":[70762,"Technical","https://www.youtube.com/watch?v=O63voitA39U"],"84":[68546,"Army","https://www.youtube.com/watch?v=5IQYxrVfgcw"],"85":[71672,"Matt","https://www.youtube.com/watch?v=14esHk9Mj8Y"],"86":[85431,"Technical","https://www.youtube.com/watch?v=2sQ1XiUBW7U"],"87":[74102,"Alberto","https://www.youtube.com/watch?v=TkrPTeY5GxI"],"88":[67131,"Panda","https://www.youtube.com/watch?v=UlcXd3DHfyk"],"89":[116882,"Alberto","https://www.youtube.com/watch?v=XTkxY9vTaqE"],"90":[119093,"Panda","https://www.youtube.com/watch?v=DM6ywJR6574"],"91":[103326,"ささゆき","https://www.youtube.com/watch?v=ozt-Pa2KhFQ"],"92":[128958,"くぜろ","https://www.youtube.com/watch?v=gCY74FrFL8E"],"93":[107664,"Vincent","https://www.youtube.com/watch?v=a4d6JyMhxcc"],"94":[117947,"Panda","https://www.youtube.com/watch?v=3-bI8lkPNMk"],"95":[116142,"Alberto","https://www.youtube.com/watch?v=fuOuQ2zMCZc"],"96":[82371,"Alberto","https://www.youtube.com/watch?v=I-x8UgdJEH4"]},"ta200":{"1":[67271,"Army","https://www.youtube.com/watch?v=yQ3iuP2FK_Y"],"2":[70557,"Alberto","https://www.youtube.com/watch?v=A5o_JmPuJd4"],"3":[81254,"Technical","https://www.youtube.com/watch?v=lfxb0P9GzGs"],"4":[75654,"Alberto","https://www.youtube.com/watch?v=9ul4y1JVfFc"],"5":[72662,"ろーる","https://www.youtube.com/watch?v=ebxaJ3YwTB4"],"6":[86141,"Army","https://www.youtube.com/watch?v=_ejgi-L7dNU"],"7":[81982,"grace","https://www.youtube.com/watch?v=BZspqX9FLlw"],"8":[85763,"Army","https://www.youtube.com/watch?v=gnLB33dlO6c"],"9":[87987,"Alberto","https://www.youtube.com/watch?v=H18b3ICqBq0"],"10":[81899,"Alberto","https://www.youtube.com/watch?v=NljYyNfHCnk"],"11":[81669,"Alberto","https://www.youtube.com/watch?v=Y0ST_uT47ZA"],"12":[75133,"Alberto","https://youtu.be/FHM6m2XV9lE"],"13":[88808,"Alberto","https://youtu.be/Aue4_okSihY"],"14":[79265,"Panda","https://www.youtube.com/watch?v=MvCvJWFIuao"],"15":[85874,"Vincent","https://www.youtube.com/watch?v=TeIoLPDqybw"],"16":[91513,"Technical","https://www.youtube.com/watch?v=jhRuarOet60"],"17":[58517,"Army","https://www.youtube.com/watch?v=iZ1gkLY5gFs"],"18":[82953,"もぺち","https://www.youtube.com/watch?v=nRMGYjzX2pE"],"19":[106080,"Vincent","https://www.youtube.com/watch?v=sPcC6Syo2xg"],"20":[105563,"Vincent","https://www.youtube.com/watch?v=nwEpePGCDoI"],"21":[112431,"Army","https://www.youtube.com/watch?v=M8ddFvmWRZA"],"22":[72833,"Alpaco","https://youtu.be/CK9E7sR6MyE"],"23":[114778,"Panda","https://www.youtube.com/watch?v=_OUJ0odWlfc"],"24":[120477,"k","https://www.youtube.com/watch?v=vAJn8NJFnEE"],"25":[109988,"StervtL","https://www.youtube.com/watch?v=ThkwR41lQn0"],"26":[106298,"Alberto","https://www.youtube.com/watch?v=2NyImxWD2Jg"],"27":[110477,"Alberto","https://www.youtube.com/watch?v=X2PVFC-pTUo"],"28":[117482,"Vincent","https://www.youtube.com/watch?v=TCljaLkAT_o"],"29":[100997,"ありす","https://www.youtube.com/watch?v=OYRVbRIF7z8"],"30":[117960,"Pii","https://www.youtube.com/watch?v=QshLk8KJUkE"],"31":[112441,"Panda","https://youtu.be/gXOWJEBcTv4"],"32":[79196,"Vincent","https://www.youtube.com/watch?v=0S8s-zAZ7cM"],"33":[101253,"Army","https://youtu.be/szygfU_3FZI"],"34":[98467,"Army","https://www.youtube.com/watch?v=ahTFf2US1Gk"],"35":[73889,"ろーる","https://www.youtube.com/watch?v=bDFYqheit2k"],"36":[76211,"Army","https://www.youtube.com/watch?v=DZwUTCWdmJ0"],"37":[80588,"Pii","https://www.youtube.com/watch?v=YlrDXJb1goo"],"38":[84881,"Alberto","https://www.youtube.com/watch?v=XQh1VytSd7Y"],"39":[61981,"alpha","https://www.youtube.com/watch?v=GbyytniAzxc"],"40":[76926,"Alberto","https://www.youtube.com/watch?v=WqyZso1MoGk"],"41":[106905,"エル","https://youtu.be/vm1y3MLKWKg"],"42":[61836,"JenZua","https://youtu.be/6eAsFElRIww"],"43":[101432,"Army","https://www.youtube.com/watch?v=yeiaXQGKjKg"],"44":[105286,"Alberto","https://www.youtube.com/watch?v=TFgBm9oBEps"],"45":[95976,"Army","https://www.youtube.com/watch?v=SItTncntHfs"],"46":[102158,"Alberto","https://www.youtube.com/watch?v=FlSM-lU90fE"],"47":[103489,"Army","https://www.youtube.com/watch?v=K5ztD9tN5do"],"48":[99680,"Army","https://www.youtube.com/watch?v=a2UN8qyxnnE"],"49":[83189,"SorNano","https://www.youtube.com/watch?v=QDDubUQnEmc"],"50":[109376,"Army","https://youtu.be/ZtTb2Fu2M0A"],"51":[79900,"Army","https://www.youtube.com/watch?v=D17_4QRLIW4"],"52":[111619,"Vincent",null],"53":[100464,"Alberto","https://www.youtube.com/watch?v=mrBvbPjaOJM"],"54":[85014,"Vincent","https://www.youtube.com/watch?v=TDycDWSEQUw"],"55":[104094,"Vincent","https://www.youtube.com/watch?v=-hV9bi9AyhA"],"56":[85897,"Alberto","https://www.youtube.com/watch?v=nJPxQn8xH7M"],"57":[111764,"ヒビキ","https://www.youtube.com/watch?v=yShSL3hXlGI"],"58":[82481,"Panda","https://www.youtube.com/watch?v=AQ1cCF2Na48"],"59":[90525,"Vincent","https://www.youtube.com/watch?v=YBl29dKpvzc"],"60":[87642,"Army","https://www.youtube.com/watch?v=4C9eoybAJ2U"],"61":[138596,"F。","https://www.youtube.com/watch?v=6MpTi-ccdZg"],"62":[119382,"Alberto","https://www.youtube.com/watch?v=OgTqCBR5hds"],"63":[85971,"Army","https://www.youtube.com/watch?v=QV14OtCKpQs"],"64":[86945,"fairy","https://www.youtube.com/watch?v=hGX9UBnajd4"],"65":[113631,"stove","https://www.youtube.com/watch?v=VlX3zrTbAe8"],"66":[126799,"¥146","https://www.youtube.com/watch?v=80F4-lQbimo"],"67":[80255,"Army",null],"68":[126997,"Panda",null],"69":[142604,"aybzq","https://www.youtube.com/watch?v=0SZ3ibJ-yNI"],"70":[115207,"Vincent","https://www.youtube.com/watch?v=ehcpVhYo2z0"],"71":[122853,"Panda","https://www.youtube.com/watch?v=iEGfIk16daE"],"72":[109453,"Vincent","https://www.youtube.com/watch?v=Yez3Y_evdc8"],"73":[96718,"Alberto","https://www.youtube.com/watch?v=CbNGPC9ZOA4"],"74":[94766,"Panda","https://www.youtube.com/watch?v=_-wSdyRnv6A"],"75":[85011,"Vincent",null],"76":[115472,"StervtL","https://www.youtube.com/watch?v=tI3cbIM751I"],"77":[117052,"YOS","https://www.youtube.com/watch?v=qrhY5WOMyLQ"],"78":[101889,"ささゆき","https://www.youtube.com/watch?v=IfXdK_GsZGM"],"79":[96957,"Pii","https://www.youtube.com/watch?v=oeR2rXeIoXs"],"80":[113193,"F。","https://www.youtube.com/watch?v=hZLsyzuHzLA"],"81":[115682,"Vincent","https://www.youtube.com/watch?v=eAH5yRLCf0A"],"82":[97508,"Panda","https://www.youtube.com/watch?v=nXOLHE3KXxc"],"83":[93951,"Army","https://www.youtube.com/watch?v=ujVoiS_NYEQ"],"84":[101918,"Jamie","https://www.youtube.com/watch?v=Sdbx8Go4Moc"],"85":[119749,"AK","https://youtu.be/21Y_6UDjIyY?feature=shared"],"86":[105460,"ささゆき","https://www.youtube.com/watch?v=NGafpCcKgRQ"],"87":[92261,"¥146","https://www.youtube.com/watch?v=p2UXpeH6dns"],"88":[67131,"Pii","https://www.youtube.com/watch?v=RDJ3utAS2jw"],"89":[85655,"JenZua","https://www.youtube.com/watch?v=ehx9Qe6jHZ4"],"90":[83897,"Vincent","https://www.youtube.com/watch?v=NzD7Lo6Ijik"],"91":[73929,"Alberto","https://www.youtube.com/watch?v=L7zEvupkSnM"],"92":[104532,"Zae","https://www.youtube.com/watch?v=NhtvBImFYSc"],"93":[76118,"Army","https://www.youtube.com/watch?v=Ldu2Byu7nGA"],"94":[83776,"Bruh",null],"95":[82371,"Army","https://www.youtube.com/watch?v=I-x8UgdJEH4"],"96":[115976,"Alberto","https://www.youtube.com/watch?v=U_qgqgVAArM"]}}}