{"default":{"lang":"en","nita150":{"1":"","2":"","3":"","4":"","5":"","6":"","7":"","8":"","9":"","10":"","11":"","12":"","13":"","14":"","15":"","16":"","17":"","18":"","19":"","20":"","21":"","22":"","23":"","24":"","25":"","26":"","27":"","28":"","29":"","30":"","31":"","32":"","33":"","34":"","35":"","36":"","37":"","38":"","39":"","40":"","41":"","42":"","43":"","44":"","45":"","46":"","47":"","48":"","49":"","50":"","51":"","52":"","53":"","54":"","55":"","56":"","57":"","58":"","59":"","60":"","61":"","62":"","63":"","64":"","65":"","66":"","67":"","68":"","69":"","70":"","71":"","72":"","73":"","74":"","75":"","76":"","77":"","78":"","79":"","80":"","81":"","82":"","83":"","84":"","85":"","86":"","87":"","88":"","89":"","90":"","91":"","92":"","93":"","94":"","95":"","96":""},"nita200":{"1":"","2":"","3":"","4":"","5":"","6":"","7":"","8":"","9":"","10":"","11":"","12":"","13":"","14":"","15":"","16":"","17":"","18":"","19":"","20":"","21":"","22":"","23":"","24":"","25":"","26":"","27":"","28":"","29":"","30":"","31":"","32":"","33":"","34":"","35":"","36":"","37":"","38":"","39":"","40":"","41":"","42":"","43":"","44":"","45":"","46":"","47":"","48":"","49":"","50":"","51":"","52":"","53":"","54":"","55":"","56":"","57":"","58":"","59":"","60":"","61":"","62":"","63":"","64":"","65":"","66":"","67":"","68":"","69":"","70":"","71":"","72":"","73":"","74":"","75":"","76":"","77":"","78":"","79":"","80":"","81":"","82":"","83":"","84":"","85":"","86":"","87":"","88":"","89":"","90":"","91":"","92":"","93":"","94":"","95":"","96":""},"ta150":{"1":"","2":"","3":"","4":"","5":"","6":"","7":"","8":"","9":"","10":"","11":"","12":"","13":"","14":"","15":"","16":"","17":"","18":"","19":"","20":"","21":"","22":"","23":"","24":"","25":"","26":"","27":"","28":"","29":"","30":"","31":"","32":"","33":"","34":"","35":"","36":"","37":"","38":"","39":"","40":"","41":"","42":"","43":"","44":"","45":"","46":"","47":"","48":"","49":"","50":"","51":"","52":"","53":"","54":"","55":"","56":"","57":"","58":"","59":"","60":"","61":"","62":"","63":"","64":"","65":"","66":"","67":"","68":"","69":"","70":"","71":"","72":"","73":"","74":"","75":"","76":"","77":"","78":"","79":"","80":"","81":"","82":"","83":"","84":"","85":"","86":"","87":"","88":"","89":"","90":"","91":"","92":"","93":"","94":"","95":"","96":""},"ta200":{"1":"","2":"","3":"","4":"","5":"","6":"","7":"","8":"","9":"","10":"","11":"","12":"","13":"","14":"","15":"","16":"","17":"","18":"","19":"","20":"","21":"","22":"","23":"","24":"","25":"","26":"","27":"","28":"","29":"","30":"","31":"","32":"","33":"","34":"","35":"","36":"","37":"","38":"","39":"","40":"","41":"","42":"","43":"","44":"","45":"","46":"","47":"","48":"","49":"","50":"","51":"","52":"","53":"","54":"","55":"","56":"","57":"","58":"","59":"","60":"","61":"","62":"","63":"","64":"","65":"","66":"","67":"","68":"","69":"","70":"","71":"","72":"","73":"","74":"","75":"","76":"","77":"","78":"","79":"","80":"","81":"","82":"","83":"","84":"","85":"","86":"","87":"","88":"","89":"","90":"","91":"","92":"","93":"","94":"","95":"","96":""}},"tracks":{"ja":["マリオカートスタジアム","ウォーターパーク","スイーツキャニオン","ドッスンいせき","マリオサーキット","キノピオハーバー","ねじれマンション","ヘイホーこうざん","サンシャインくうこう","ドルフィンみさき","エレクトロドリーム","ワリオスノーマウンテン","スカイガーデン","ホネホネさばく","クッパキャッスル","レインボーロード","Wii モーモーカントリー","GBA マリオサーキット","DS プクプクビーチ","N64 キノピオハイウェイ","GC カラカラさばく","SFC ドーナツへいや3","N64 ピーチサーキット","3DS DKジャングル","DS ワリオスタジアム","GC シャーベットランド","3DS ミュージックパーク","N64 ヨッシーバレー","DS チクタクロック","3DS パックンスライダー","Wii グラグラかざん","N64 レインボーロード","GC ヨッシーサーキット","エキサイトバイク","ドラゴンロード","ミュートシティ","Wii ワリオこうざん","SFC レインボーロード","ツルツルツイスター","ハイラルサーキット","GC ベビィパーク","GBA チーズランド","ネイチャーロード","どうぶつの森","3DS ネオクッパシティ","GBA リボンロード","リンリンメトロ","ビッグブルー","Tour パリプロムナード","3DS キノピオサーキット","N64 チョコマウンテン","Wii ココナッツモール","Tour トーキョースクランブル","DS キノコリッジウェイ","GBA スカイガーデン","ニンニンドージョー","Tour ニューヨークドリーム","SFC マリオサーキット 3","N64 カラカラさばく","DS ワルイージピンボール","Tour シドニーサンシャイン","GBA スノーランド","Wii キノコキャニオン","アイスビルディング","Tour ロンドンアベニュー","GBA テレサレイク","3DS ロックロックマウンテン","Wii メイプルツリーハウス","Tour ベルリンシュトラーセ","DS ピーチガーデン","メリーメリーマウンテン","3DS レインボーロード","Tour アムステルダムブルーム","GBA リバーサイドパーク","Wii DKスノーボードクロス","ヨッシーアイランド","Tour バンコクラッシュ","DS マリオサーキット","GC ワルイージスタジアム","Tour シンガポールスプラッシュ","Tour アテネポリス","GC デイジークルーザー","Wii ムーンリッジ&ハイウェイ","シャボンロード","Tour ロサンゼルスコースト","GBA サンセットこうや","Wii ノコノコみさき","Tour バンクーバーバレー","Tour ローマアバンティ","GC DKマウンテン","Wii デイジーサーキット","パックンしんでん","Tour マドリードグランデ","3DS ロゼッタプラネット","SFC クッパじょう 3","Wii レインボーロード"],"en":["Mario Kart Stadium","Water Park","Sweet Sweet Canyon","Thwomp Ruins","Mario Circuit","Toad Harbor","Twisted Mansion","Shy Guy Falls","Sunshine Airport","Dolphin Shoals","Electrodrome","Mount Wario","Cloudtop Cruise","Bone-Dry Dunes","Bowser's Castle","Rainbow Road","Wii Moo Moo Meadows","GBA Mario Circuit","DS Cheep Cheep Beach","N64 Toad's Turnpike","GC Dry Dry Desert","SFC Donut Plains 3","N64 Royal Raceway","3DS DK Jungle","DS Wario Stadium","GC Sherbet Land","3DS Music Park","N64 Yoshi Valley","DS Tick-Tock Clock","3DS Pilanha Plant Slide","Wii Grumble Volcano","N64 Rainbow Road","GC Yoshi Circuit","Excitebike Arena","Dragon Driftway","Mute City","Wii Wario's Gold Mine","SFC Rainbow Road","Ice Ice Outpost","Hyrule Circuit","GC Baby Park","GBA Cheese Land","Wild Woods","Animal Crossing","3DS Neo Bowser City","GBA Ribbon Road","Super Bell Subway","Big Blue","Tour Paris Promenade","3DS Toad Circuit","N64 Choco Mountain","Wii Coconut Mall","Tour Tokyo Blur","DS Shroom Ridge","GBA Sky Garden","Ninja Hideaway","Tour New York Minute","SFC Mario Circuit 3","N64 Kalimali Desert","DS Waluigi Pinball","Tour Sydney Sprint","GBA Snow Land","Wii Mushroom Gorge","Sky-high Sundae","Tour London Loop","GBA Boo Lake","3DS Rock Rock Mountain","Wii Maple Treeway","Tour Berlin Byways","DS Peach Gardens","Merry Mountain","3DS Rainbow Road","Tour Amsterdam Drift","GBA Riverside Park","Wii DK Summit","Yoshi's Island","Tour Bangkok Rush","Ds Mario Circuit","GC Waluigi Stadium","Tour Singapore Speedway","Tour Athens Dash","GC Daisy Cruiser","Wii Moonview Highway","Squeaky Clean Sprint","Tour Los Angeles Laps","GBA Sunset Wilds","Wii Koopa Cape","Tour Vancouver Velocity","Tour Rome Avanti","GC DK Mountain","Wii Daisy Circuit","Tour Pilanha Plant Cove","Tour Madrid Drive","3DS Rosalina's Ice World","SFC Bowser Castle 3","Wii Rainbow Road"],"raw":{"1":"","2":"","3":"","4":"","5":"","6":"","7":"","8":"","9":"","10":"","11":"","12":"","13":"","14":"","15":"","16":"","17":"","18":"","19":"","20":"","21":"","22":"","23":"","24":"","25":"","26":"","27":"","28":"","29":"","30":"","31":"","32":"","33":"","34":"","35":"","36":"","37":"","38":"","39":"","40":"","41":"","42":"","43":"","44":"","45":"","46":"","47":"","48":"","49":"","50":"","51":"","52":"","53":"","54":"","55":"","56":"","57":"","58":"","59":"","60":"","61":"","62":"","63":"","64":"","65":"","66":"","67":"","68":"","69":"","70":"","71":"","72":"","73":"","74":"","75":"","76":"","77":"","78":"","79":"","80":"","81":"","82":"","83":"","84":"","85":"","86":"","87":"","88":"","89":"","90":"","91":"","92":"","93":"","94":"","95":"","96":""}},"messages":{"en":{"notregistered":"You haven't registered this track's time yet.","illegalformat":"Invalid time format.","tracknotexists":"Track doesn't exist.","sameasbest":"Time is the same as the best time.","fasterthanwr":"Your time is faster than current WR. \nPlease submit your WR on https://mkwrs.com/mk8dx/ Current WR: ","difference":"Difference","yourtime":"Your time","slowerthanbest":"Your time is slower than your best time. Your best: "},"ja":{"notregistered":"このトラックでのタイムが未申請です。","illegalformat":"タイムのフォーマットが無効です。","tracknotexists":"トラックが存在しません。","sameasbest":"ベストタイムと同じです。","fasterthanwr":"あなたのタイムは現在のWRより速いです。\nhttps://mkwrs.com/mk8dx/ であなたのタイムを申請してください。 WR: ","difference":"差","yourtime":"あなたのタイム","slowerthanbest":"あなたのタイムはあなたのベストタイムより遅いです。ベスト: "}},"wr":{"nita150":{"1":[99745,"かたゆ","https://www.google.com/url?q=https://www.youtube.com/watch?v%3DlQH-iX37plc&sa=D&source=editors&ust=1730081583538216&usg=AOvVaw2FQq5GVt8l7PRCRpZL0HZ9"],"2":[101327,"Panda","https://www.google.com/url?q=https://youtu.be/EBg0Zw73qak?si%3DhkdsMaJ9677jteIl&sa=D&source=editors&ust=1730081583538527&usg=AOvVaw1EOvc6liqy6S3iq2RjSKp6"],"3":[113826,"Panda","https://www.google.com/url?q=https://youtu.be/o1tcOkob-1Q?si%3DOP8qqn-G2cZdkzlo&sa=D&source=editors&ust=1730081583538711&usg=AOvVaw3zVWRrudPWU3qCrorqZYd8"],"4":[111820,"Panda","https://www.google.com/url?q=https://youtu.be/_ekFsiz841I?si%3DlUGFeZlUfUR79Htd&sa=D&source=editors&ust=1730081583538866&usg=AOvVaw13RlnyyGhp8mYXZo7jvjq7"],"5":[107911,"Panda","https://www.google.com/url?q=https://youtu.be/GtzbC25DPKg?si%3DAFxXQ0NsX6MFkc-p&sa=D&source=editors&ust=1730081583554533&usg=AOvVaw3MeheG5QypJfjddHKE2HVX"],"6":[124858,"ton","https://www.google.com/url?q=https://youtu.be/qM_V9xneC0g&sa=D&source=editors&ust=1730081583554722&usg=AOvVaw02wKoQK9ir6upLUqIDQG6g"],"7":[118644,"Panda","https://www.google.com/url?q=https://youtu.be/uZ-2vRgeDZI?si%3D7GYGKwhDVYnNVcbF&sa=D&source=editors&ust=1730081583554891&usg=AOvVaw2C9CZS2Y27xL5iBjZkoJ3s"],"8":[117970,"Isaac","https://www.google.com/url?q=https://www.youtube.com/watch?v%3Df44zN-8Jzmc&sa=D&source=editors&ust=1730081583555064&usg=AOvVaw1dYsupNMgnow1voRx81y2e"],"9":[120357,"らくbot","https://www.google.com/url?q=https://youtu.be/wqJecs3OU6M?feature%3Dshared&sa=D&source=editors&ust=1730081583571519&usg=AOvVaw1QpeRg5Mxb3ooKi94oOtUT"],"10":[116975,"piyopotecni","https://www.google.com/url?q=https://youtu.be/3D4awky_PKk&sa=D&source=editors&ust=1730081583571807&usg=AOvVaw2YvGj76jy1lgACKapgvF9P"],"11":[120429,"らくbot","https://www.google.com/url?q=https://youtu.be/umy1WwRb28g?feature%3Dshared&sa=D&source=editors&ust=1730081583572066&usg=AOvVaw1Obx-SROGd06xo4iwW2YRV"],"12":[103553,"StervtL","https://www.google.com/url?q=https://youtu.be/0eNt-KRGyik?si%3DpqvpUJur7d7PWGSU&sa=D&source=editors&ust=1730081583572315&usg=AOvVaw2Dj62AprMcTGMLGGW5Ty3L"],"13":[121968,"にら","https://www.google.com/url?q=https://youtu.be/UbOk9prR4kE&sa=D&source=editors&ust=1730081583589525&usg=AOvVaw3UNaBFYFifdUN57pSFLURq"],"14":[111413,"ぷらぷら","https://www.google.com/url?q=https://youtu.be/431YVpaHOao?si%3D12yb2Wl6KVmcTRuj&sa=D&source=editors&ust=1730081583589839&usg=AOvVaw3TFyOVfgw90ambwUwY-hKU"],"15":[122470,"Panda","https://www.google.com/url?q=https://youtu.be/W0Pf86x2ELo?si%3Da0iMb3h7hmey8kiv&sa=D&source=editors&ust=1730081583590120&usg=AOvVaw0xTgAOb399HmJBJBztPHbI"],"16":[121524,"¥146","https://www.google.com/url?q=https://youtu.be/Equf18lDPRo?si%3Dsw16ohf4I69i8m5N&sa=D&source=editors&ust=1730081583590409&usg=AOvVaw2_ZYWcB82mdFXy6DlWELHM"],"17":[86780,"Panda","https://www.google.com/url?q=https://youtu.be/g7bVEkfHZmc?si%3D9IvV5iN6AntQwKZH&sa=D&source=editors&ust=1730081583606048&usg=AOvVaw1P7ad3JzMYb3hDBkAUWlR_"],"18":[87146,"Panda","https://www.google.com/url?q=https://www.youtube.com/watch?v%3DBzB5PrrhhTE&sa=D&source=editors&ust=1730081583606313&usg=AOvVaw2yvhVeK7Ssigy0fBUqibeX"],"19":[109335,"nire","https://www.google.com/url?q=https://youtu.be/JitQKJc2giU?si%3DYqp0Ug2niGQ7Tgoe&sa=D&source=editors&ust=1730081583606479&usg=AOvVaw0blJUi2UElE7zIRiI1S_r_"],"20":[107703,"Panda","https://www.google.com/url?q=https://youtu.be/v0hnBMK_g6Q?si%3DYMo4YtwQ2agZru1p&sa=D&source=editors&ust=1730081583606642&usg=AOvVaw3fNgeNyiuGo51LVXAfzRkj"],"21":[120486,"Panda","https://www.google.com/url?q=https://www.youtube.com/watch?v%3Dzel3p5VK1jA&sa=D&source=editors&ust=1730081583624791&usg=AOvVaw3MMYrfg5aojQnpSro8fuNa"],"22":[77180,"Pii","https://www.google.com/url?q=https://www.youtube.com/watch?v%3Dncj3YGdrD_Y&sa=D&source=editors&ust=1730081583625023&usg=AOvVaw3xO7KDIqthLeD2k2_ivU1T"],"23":[118798,"ラス","https://www.google.com/url?q=https://youtu.be/8OVyWTfrBsw?si%3DuMh6VsgTxhn8yAxJ&sa=D&source=editors&ust=1730081583625260&usg=AOvVaw1e12Cajo_3mnl7v7qEc1fF"],"24":[123342,"Alberto","https://www.google.com/url?q=https://www.youtube.com/watch?v%3DzpyzZRW6oTk&sa=D&source=editors&ust=1730081583625461&usg=AOvVaw1iAQwMIkuUhR0ZayIDsO6A"],"25":[112687,"aybzq","https://www.google.com/url?q=https://youtu.be/2sxgKS8D5qQ?si%3D94gQJQF6_bje3mcx&sa=D&source=editors&ust=1730081583640571&usg=AOvVaw16uNSkAbD6X0uap2k5GTux"],"26":[109804,"Mana","https://www.google.com/url?q=https://youtu.be/PueVnqjqSVs?si%3DpbA6BCL59Awpayyw&sa=D&source=editors&ust=1730081583640779&usg=AOvVaw28Ua7QE04XR0UevIx8PqC5"],"27":[112799,"えくすと","https://www.google.com/url?q=https://youtu.be/AwLELgS-y3k?si%3DFG3ERDPbH17WL3HA&sa=D&source=editors&ust=1730081583640959&usg=AOvVaw222z75LEaVUvpXzJQpJDB1"],"28":[122579,"Panda","https://www.google.com/url?q=https://youtu.be/rk4_FAUauEc?si%3Dw4U3bYednyINLu3s&sa=D&source=editors&ust=1730081583641035&usg=AOvVaw2WXEhNFJ-sfq9nzia5A2wF"],"29":[103377,"すとーぶ","https://www.google.com/url?q=https://www.youtube.com/watch?v%3D4_R8Wymo_sU&sa=D&source=editors&ust=1730081583659384&usg=AOvVaw3e9ww2EgN9h46XeiLoC1OD"],"30":[123211,"Fuga","https://www.google.com/url?q=https://youtu.be/BSoCORqLH1s?si%3DBQCmOowf70Sd8S8s&sa=D&source=editors&ust=1730081583659504&usg=AOvVaw0ovJEOxcXy2XoDZbx2Lw00"],"31":[115341,"quartz","https://www.google.com/url?q=https://www.youtube.com/watch?v%3DYIM0BrZL01I&sa=D&source=editors&ust=1730081583659670&usg=AOvVaw2bYBOkJD9ukVmyHxke9lKH"],"32":[80998,"Lafu","https://www.google.com/url?q=https://youtu.be/jPeco-FUwUo&sa=D&source=editors&ust=1730081583659964&usg=AOvVaw2rDlTj0AWfKnNP8cqOOjkk"],"33":[105992,"calna","https://www.google.com/url?q=https://youtu.be/DUV4PQ55gPc?si%3D_wzroJqVuMNLkb74&sa=D&source=editors&ust=1730081583677963&usg=AOvVaw3NWTy49ReiiFgAAwQVq2Cw"],"34":[102747,"Yoshiyoshi","https://www.google.com/url?q=https://youtu.be/rOPobkqoFag?si%3D-7-y9SkkFXGZvHnF&sa=D&source=editors&ust=1730081583678122&usg=AOvVaw0iRqWNrFBa7sQ0_9XdYiNf"],"35":[105354,"calna","https://www.google.com/url?q=https://youtu.be/X9Uq8uNmAL0?si%3Ds1eloejCUNWxaYJ3&sa=D&source=editors&ust=1730081583678586&usg=AOvVaw3Xs3WhFJpRCHwI-uZYM-cQ"],"36":[115911,"ふじほたる","https://www.google.com/url?q=https://youtu.be/eL5rgVxjAJQ&sa=D&source=editors&ust=1730081583678728&usg=AOvVaw2oyZvqkQeE4W8H0r9LUXJ4"],"37":[123551,"Panda","https://www.google.com/url?q=https://www.youtube.com/watch?v%3DKQtMUnHG9jg&sa=D&source=editors&ust=1730081583699860&usg=AOvVaw3zksMZ_Yei6Z_8eC39hMR9"],"38":[88456,"Jotrix","https://www.google.com/url?q=https://youtu.be/eYRy1iKpxSg&sa=D&source=editors&ust=1730081583700066&usg=AOvVaw37z7UEZDYl3YyimMUjSJGo"],"39":[107409,"とれいん。","https://www.google.com/url?q=https://www.youtube.com/watch?v%3DKIOwI-HfrXE&sa=D&source=editors&ust=1730081583700368&usg=AOvVaw2OyK6McrPlmV9DKC4YEMlM"],"40":[110981,"究極攻略ch","https://www.google.com/url?q=https://www.youtube.com/watch?v%3DDLpuUC_fEQ8&sa=D&source=editors&ust=1730081583700455&usg=AOvVaw2cEWqQSodFmDLdKJqHZUOJ"],"41":[64849,"Sorata","https://www.google.com/url?q=https://youtu.be/BAedyom4r3c&sa=D&source=editors&ust=1730081583716360&usg=AOvVaw3OWALT___oOv48hSLjsldZ"],"42":[108094,"Panda","https://www.google.com/url?q=https://www.youtube.com/watch?v%3DI4w6Z5CmsO8&sa=D&source=editors&ust=1730081583716569&usg=AOvVaw3Qrfopad5O3Uw3trHBNTt2"],"43":[107925,"らくbot","https://www.google.com/url?q=https://youtu.be/PkxmmLgBn28?feature%3Dshared&sa=D&source=editors&ust=1730081583716777&usg=AOvVaw3qf_84WuMHPlb1zpogKF6e"],"44":[100935,"ziline","https://www.google.com/url?q=https://youtu.be/iDtpYRvgnCo?si%3D5_iQhWQB35H_FoKX&sa=D&source=editors&ust=1730081583717034&usg=AOvVaw0gi7cex-gJSzEyTdtKIqTs"],"45":[106187,"Panda","https://www.google.com/url?q=https://www.youtube.com/watch?v%3DJ2JJ2p6qjy8&sa=D&source=editors&ust=1730081583731713&usg=AOvVaw01BewLS03jUiukHnkckmWS"],"46":[110701,"¥146","https://www.google.com/url?q=https://youtu.be/J029EQKelFU?si%3Dcleo5lmtfYWU_bEP&sa=D&source=editors&ust=1730081583731919&usg=AOvVaw1nFtlyogV67qyrXXYYPJI7"],"47":[104196,"sugar","https://www.google.com/url?q=https://youtu.be/aPxNG5eH0HU&sa=D&source=editors&ust=1730081583732174&usg=AOvVaw1GdPesnOCrjwiWxmOcr_bL"],"48":[86263,"shi","https://www.google.com/url?q=https://twitter.com/shihomk8dx/status/1825813114899804300?t%3D5dUm1EPLs7-YBMUMqAUNTQ%26s%3D19&sa=D&source=editors&ust=1730081583732259&usg=AOvVaw1l-HGb95hYwyY8RWepichT"],"49":[111756,"ぐち","https://www.google.com/url?q=https://www.youtube.com/watch?v%3DKWsuSpC-VMA&sa=D&source=editors&ust=1730081583747328&usg=AOvVaw14v6RAtRgd7odlvoXnVIVo"],"50":[84337,"ぼあさん","https://www.google.com/url?q=https://vt.tiktok.com/ZSNTHB93V/&sa=D&source=editors&ust=1730081583747507&usg=AOvVaw1j6V9xfbRGoTQGk3OaNNpS"],"51":[113834,"ラス","https://www.google.com/url?q=https://youtu.be/_WdGba1EAJ0?si%3DUBpHd6SKPzE5BWg4&sa=D&source=editors&ust=1730081583747668&usg=AOvVaw0LeL1YYbpfl8ydmVSG6J20"],"52":[103756,"ichigo","https://www.google.com/url?q=https://youtu.be/IeCCtzLnukk?si%3D0RaJ0WveAMA09TLl&sa=D&source=editors&ust=1730081583747823&usg=AOvVaw03wE7j-MrPjUaFEY5639lo"],"53":[87486,"ぼあさん","https://www.google.com/url?q=https://youtu.be/M4eGjW_cUnk?si%3DMeNu13ezwwQ7AZ1l&sa=D&source=editors&ust=1730081583763394&usg=AOvVaw2nhdumO--ktcLn5cCvc6ja"],"54":[107922,"ましゅ","https://www.google.com/url?q=https://youtu.be/4stwmH-wxpg?si%3DJiDhbLcePw182-1Z&sa=D&source=editors&ust=1730081583763686&usg=AOvVaw3wxNJVL7mty_c9E2BJIp_0"],"55":[90434,"sugar","https://www.google.com/url?q=https://youtu.be/YAWOACKnYpk&sa=D&source=editors&ust=1730081583763932&usg=AOvVaw2uAK8Nfu1Lw8lNnNE-FIkT"],"56":[113949,"なきりおと","https://www.google.com/url?q=https://youtu.be/2rAdExPtt1w?si%3DdLU0EoDjoNU2Z2Z4&sa=D&source=editors&ust=1730081583764112&usg=AOvVaw0Rr1wDBB-bJTIOiC3hbltj"],"57":[84597,"Panda","https://www.google.com/url?q=https://youtu.be/S2h54_Sl9jM?si%3DM5kheBh-1jpRdaTr&sa=D&source=editors&ust=1730081583779222&usg=AOvVaw2crnlj5-F3PHb8_auw9X4w"],"58":[95794,"ラス","https://www.google.com/url?q=https://youtu.be/TWnbD54vew8?si%3Der35cWckglMzMKM2&sa=D&source=editors&ust=1730081583779420&usg=AOvVaw1hmsTzb4Q5e67LhzRy89xA"],"59":[93700,"Panda","https://www.google.com/url?q=https://youtu.be/53aZavl4l10?si%3DDLnDdiGezFNiVjGg&sa=D&source=editors&ust=1730081583779671&usg=AOvVaw2NbBt0uvyDcuGfQXD4nSad"],"60":[140341,"らくbot","https://www.google.com/url?q=https://youtu.be/r6y1qY0Z-F0?feature%3Dshared&sa=D&source=editors&ust=1730081583779977&usg=AOvVaw3_mR24c8RZHqgYHBtvul6w"],"61":[122827,"Panda","https://www.google.com/url?q=https://youtu.be/pSkfnteexcs?si%3DUKygTIw3FkMaw4jt&sa=D&source=editors&ust=1730081583795842&usg=AOvVaw0YKyyTVqHJIrm6At4nrzda"],"62":[96247,"Panda","https://www.google.com/url?q=https://youtu.be/WJAnQ1WUZBI?si%3D5kipTEfeonUY4bFk&sa=D&source=editors&ust=1730081583796025&usg=AOvVaw0tA5AFeuddSLmSOmOJyFYC"],"63":[95837,"fairy","https://www.google.com/url?q=https://www.youtube.com/watch?v%3DOnyzC_FlWAA&sa=D&source=editors&ust=1730081583796202&usg=AOvVaw25noi1ZjeQTs1O1ijaPWEg"],"64":[116270,"あぃす","https://www.google.com/url?q=https://youtu.be/5KfkyCWTtLE?si%3DZ48nV30aEiyaignb&sa=D&source=editors&ust=1730081583796457&usg=AOvVaw03PZRvIGRgOcCjno57dz7x"],"65":[131544,"¥146","https://www.google.com/url?q=https://youtu.be/LriFQ4bJBrA?si%3DIS7O-UhDMzdCYAXG&sa=D&source=editors&ust=1730081583812447&usg=AOvVaw0LeaZmJHjs1fLLY9cabMmq"],"66":[83381,"Euan","https://www.google.com/url?q=https://youtu.be/a2JBzzqF5dg?si&sa=D&source=editors&ust=1730081583812625&usg=AOvVaw2diBRo_GmkMMOiA4qp_XPf"],"67":[135863,"らくbot","https://www.google.com/url?q=https://youtu.be/ISeXZIc4vpk?feature%3Dshared&sa=D&source=editors&ust=1730081583812791&usg=AOvVaw1Ryyv7lr23Np1FL8P42sCJ"],"68":[145937,"aybzq","https://www.google.com/url?q=https://youtu.be/RvYHwSBSpmg?si%3D_oZ1eHOlajz0N-K5&sa=D&source=editors&ust=1730081583813004&usg=AOvVaw3uvPkB3MgQulnIRVvY_iaA"],"69":[119394,"らくbot","https://www.google.com/url?q=https://youtu.be/4EqrJRRWkTQ?feature%3Dshared&sa=D&source=editors&ust=1730081583828091&usg=AOvVaw0_DxrR-dddOkB__E41Ft65"],"70":[127733,"ラス","https://www.google.com/url?q=https://youtu.be/SaLiBuQ41os?si%3DJDZYiBkrRFoW_qBV&sa=D&source=editors&ust=1730081583828397&usg=AOvVaw2BMgvy9plENmOb0tr66S4B"],"71":[117204,"Panda","https://www.google.com/url?q=https://youtu.be/nttQd-ly4jo?si%3DexZOgQa47yXXtnSY&sa=D&source=editors&ust=1730081583828569&usg=AOvVaw2uzneaQ94pm9uEZxiidHCL"],"72":[98705,"ラス","https://www.google.com/url?q=https://youtu.be/y1eKyKlghB0?si%3D1HrienBUNKvXod6F&sa=D&source=editors&ust=1730081583828742&usg=AOvVaw2COTopOqzVFi9N4IzpEmFk"],"73":[97671,"Panda","https://www.google.com/url?q=https://youtu.be/9K5qu3IYSOY?si%3DEhf9C9m9qlWjkXKZ&sa=D&source=editors&ust=1730081583843854&usg=AOvVaw0bbYvqfsbinvCzRSSd2Q4E"],"74":[91452,"Luckyo","https://www.google.com/url?q=https://www.youtube.com/watch?v%3Dt_fLFxc4ISg&sa=D&source=editors&ust=1730081583844147&usg=AOvVaw2KvGPf-S6Zz8RsK9rB_UUS"],"75":[117595,"YUTM","https://www.google.com/url?q=https://youtu.be/KwmJHj8kvfg?si%3DAeLoKUfWAb4ZZBIh&sa=D&source=editors&ust=1730081583844228&usg=AOvVaw3Ju3KB2HeVopRDkurtxfEK"],"76":[120250,"Kazuya","https://www.google.com/url?q=https://youtu.be/5PNeVm30QsE?si%3D8VhyxFVB2oT2a3Q1&sa=D&source=editors&ust=1730081583844413&usg=AOvVaw2h_nL27GitoLqC4mkB0KQr"],"77":[104451,"Panda","https://www.google.com/url?q=https://www.youtube.com/watch?v%3DoYzdRq492-k&sa=D&source=editors&ust=1730081583860451&usg=AOvVaw3cfVbdrFTFlLDpzHuWT7k_"],"78":[101878,"Hoshiku","https://www.google.com/url?q=https://youtu.be/QN0oK_u2ETk?si%3Dc9kk9I1LFTd-fYNg&sa=D&source=editors&ust=1730081583860627&usg=AOvVaw2OSMddqJP938qxy0DdKrx0"],"79":[117379,"y","https://www.google.com/url?q=https://youtu.be/qJantlGALJU?feature%3Dshared&sa=D&source=editors&ust=1730081583860885&usg=AOvVaw0dwBjjkps-tfrwH6-GV3Wd"],"80":[117759,"ぐち","https://www.google.com/url?q=https://www.youtube.com/watch?v%3DHSYCPxmnIiA&sa=D&source=editors&ust=1730081583860964&usg=AOvVaw0N5FSfc3jfmIfe1rl1L46A"],"81":[100813,"ぐち","https://www.google.com/url?q=https://www.youtube.com/watch?v%3DzqVVRQ37bxc&sa=D&source=editors&ust=1730081583876035&usg=AOvVaw2DlhfSb-07qys2U8f8i5MY"],"82":[95686,"Army","https://www.google.com/url?q=https://youtu.be/_-HypEbIVyI&sa=D&source=editors&ust=1730081583876224&usg=AOvVaw2jx7qhQcX4jtzQIt6VMw9P"],"83":[104539,"ましゅ","https://www.google.com/url?q=https://youtu.be/zHX_Tb29zRA?si%3DhIr-jwvg7NRkkzDe&sa=D&source=editors&ust=1730081583876393&usg=AOvVaw0IULBPTuUCT8FY5YObX-si"],"84":[123403,"ちずば","https://www.google.com/url?q=https://youtu.be/dx1JVopx0Pk?si%3DS6QZDWXXaSgSG4_o&sa=D&source=editors&ust=1730081583876563&usg=AOvVaw0r7WAaoHqzuzKeFhxNhoL-"],"85":[109170,"Panda","https://www.google.com/url?q=https://youtu.be/gTbOaUJhPYg?si%3DswPV0p5f_8vkDMlQ&sa=D&source=editors&ust=1730081583891868&usg=AOvVaw2MrWSABlp0F4YDskMcXO0d"],"86":[97096,"あおりんご","https://www.google.com/url?q=https://youtu.be/gaxyww0xDGw?si%3D5e20Rgd1YCmgCoku&sa=D&source=editors&ust=1730081583892065&usg=AOvVaw3cw0ZovGPhIDSGE81vZwyQ"],"87":[120914,"らくbot","https://www.google.com/url?q=https://youtu.be/J3v61p6_nzA?feature%3Dshared&sa=D&source=editors&ust=1730081583892236&usg=AOvVaw2pa3jysGXpPOMDKjguTA8Y"],"88":[121612,"ぐち","https://www.google.com/url?q=https://www.youtube.com/watch?v%3DITlkV7BnO74&sa=D&source=editors&ust=1730081583892411&usg=AOvVaw23V4tVTQEIgdRM96DKa7LK"],"89":[107174,"Panda","https://www.google.com/url?q=https://youtu.be/0FD76oWpvvQ?si%3DZ2fl70x5YypRIsMu&sa=D&source=editors&ust=1730081583908188&usg=AOvVaw11ceGI1cqr38w68pjmxo3s"],"90":[130859,"kuzero","https://www.google.com/url?q=https://x.com/kuzerox_/status/1781224866592796702?s%3D46%26t%3Dn_XfioWCbx56plliCg1BSA&sa=D&source=editors&ust=1730081583908383&usg=AOvVaw1lLljhQ7D-4jFFYBBRjT8g"],"91":[110865,"nire","https://www.google.com/url?q=https://youtu.be/Ma0g61nhXw4?si%3DfDYMju2sPIvUF9jS&sa=D&source=editors&ust=1730081583908621&usg=AOvVaw3aZZq-FZW9eC70qqsaRXF8"],"92":[122812,"ぐち","https://www.google.com/url?q=https://www.youtube.com/watch?v%3DBrufrzVYiRM&sa=D&source=editors&ust=1730081583908856&usg=AOvVaw1RNVFr-o_wqJJIbX2YfSUj"],"93":[119924,"すとーぶ","https://www.google.com/url?q=https://youtu.be/QzzP53exnqo?si%3DMJUoBJNtFgiTDUlW&sa=D&source=editors&ust=1730081583924337&usg=AOvVaw3K8bT_G_amEaTY1PGrgw3o"],"94":[119866,"Panda","https://www.google.com/url?q=https://youtu.be/ENIvSOTo9iY?si%3DIR2YqvCs8QALqmlk&sa=D&source=editors&ust=1730081583924520&usg=AOvVaw2jZuoh3Efbpy0btdd_oo5f"],"95":[103114,"Pii","https://www.google.com/url?q=https://www.youtube.com/watch?v%3Dd5ydfEfO55Y&sa=D&source=editors&ust=1730081583924699&usg=AOvVaw252HdDBbaioti7UrKqKTJC"],"96":[154834,"ぐち","https://www.google.com/url?q=https://www.youtube.com/watch?v%3D5i2H4fu-0ZA&sa=D&source=editors&ust=1730081583924925&usg=AOvVaw3OrlqENOZNA0LoneGj7WMF"]},"nita200":{"1":[71520,"konni","https://www.google.com/url?q=https://youtu.be/lQfgBwaEBPw&sa=D&source=editors&ust=1730081596174082&usg=AOvVaw0FchSPpoiXIyyfo3CwFysl"],"2":[72917,"velg","https://www.google.com/url?q=https://www.youtube.com/watch?v%3DiH2AN6GwNaQ%26ab_channel%3Dvelg&sa=D&source=editors&ust=1730081596174738&usg=AOvVaw0HNrvDl05F3mLXOgRns8tO"],"3":[86150,"Menschenie","https://www.google.com/url?q=https://youtu.be/4FJHwa02pXg&sa=D&source=editors&ust=1730081596175443&usg=AOvVaw1W_7cNElYgS2r3yKhzq35x"],"4":[79646,"Cream","https://www.google.com/url?q=https://www.youtube.com/watch?v%3D4xrSTVVtl-U&sa=D&source=editors&ust=1730081596176101&usg=AOvVaw3zrNdISPyAicmi6XffjckE"],"5":[76722,"核熱","https://www.google.com/url?q=https://youtu.be/5UKhurwDeXE&sa=D&source=editors&ust=1730081596219439&usg=AOvVaw3_a--aq3qkYb-HUkFp2Uch"],"6":[90322,"Pianist15","https://www.google.com/url?q=https://youtu.be/F0dRyNZyfvY&sa=D&source=editors&ust=1730081596219973&usg=AOvVaw0Pkk5-K6r5Vjpzcsn7LF7L"],"7":[86781,"Technical","https://www.google.com/url?q=https://www.youtube.com/watch?v%3DieIiyjpfcb0&sa=D&source=editors&ust=1730081596220545&usg=AOvVaw0sqOl5fBfk7S2yxt7agSc1"],"8":[88964,"Alberto","https://www.google.com/url?q=https://www.youtube.com/watch?v%3DQi_0uMwUyIM&sa=D&source=editors&ust=1730081596221214&usg=AOvVaw0jdJsaqIp9nc47k3igC1Gt"],"9":[90585,"Army","https://www.google.com/url?q=https://www.youtube.com/watch?v%3Dn6yT_H2knqU&sa=D&source=editors&ust=1730081596259657&usg=AOvVaw2cOVj-oba9HMcqUzyGEgnR"],"10":[84888,"Cream","https://www.google.com/url?q=https://www.youtube.com/watch?v%3DCfSECFdUGMk&sa=D&source=editors&ust=1730081596260314&usg=AOvVaw089gd-HpdiItA7M2GaiLwP"],"11":[87759,"Army","https://www.google.com/url?q=https://www.youtube.com/watch?v%3DgxMoMI54Iy0&sa=D&source=editors&ust=1730081596261013&usg=AOvVaw2i6AVMkMAahoSxPIxOOINl"],"12":[78083,"Technical","https://www.google.com/url?q=https://www.youtube.com/watch?v%3D0gbTo_gAEKU&sa=D&source=editors&ust=1730081596261666&usg=AOvVaw2HUHjGRiEltj8cRcnRNSEz"],"13":[90977,"Alberto","https://www.google.com/url?q=https://www.youtube.com/watch?v%3DCBgNUTuS2R4%26t&sa=D&source=editors&ust=1730081596308207&usg=AOvVaw0i0EvA_hSSeHMJqUBNRD5H"],"14":[84007,"Technical","https://www.google.com/url?q=https://www.youtube.com/watch?v%3DpRuHSyWmXOw&sa=D&source=editors&ust=1730081596308932&usg=AOvVaw0WYhqVn-OTTAPrKjYGDMEc"],"15":[89490,"Technical","https://www.google.com/url?q=https://www.youtube.com/watch?v%3DorNCAj0uGu8&sa=D&source=editors&ust=1730081596309651&usg=AOvVaw0nRg2WjVHPJ7UkVZBD3u2e"],"16":[94794,"Awoken","https://www.google.com/url?q=https://www.youtube.com/watch?v%3D4GwTh5qBa80&sa=D&source=editors&ust=1730081596310464&usg=AOvVaw0b6HNLL0qSPa6CJKesGMPX"],"17":[61736,"Citro","https://www.google.com/url?q=https://www.youtube.com/watch?v%3DQ8X4CNXZ3rg&sa=D&source=editors&ust=1730081596342319&usg=AOvVaw2PzrRvHXfWoC7gfeCx_3OP"],"18":[64188,"Verlust","https://www.google.com/url?q=https://youtu.be/xRxkUpdMzR4&sa=D&source=editors&ust=1730081596343024&usg=AOvVaw2KCqZfXEznuLZCRAma1bxh"],"19":[77900,"Alberto","https://www.google.com/url?q=https://www.youtube.com/watch?v%3DPlpTOWznABo&sa=D&source=editors&ust=1730081596343684&usg=AOvVaw3JXIbCSYoB3chfpmAIwo7V"],"20":[75000,"Technical","https://www.google.com/url?q=https://www.youtube.com/watch?v%3DyZ6phvDYa_U&sa=D&source=editors&ust=1730081596344347&usg=AOvVaw1m56k6B4BUEu2v_B3B5fQN"],"21":[84193,"Panda","https://www.google.com/url?q=https://www.youtube.com/watch?v%3D7BtLnll9jXo&sa=D&source=editors&ust=1730081596390854&usg=AOvVaw2KNh5-DwsheRulZbjEORBq"],"22":[60774,"Alberto","https://www.google.com/url?q=https://www.youtube.com/watch?v%3D3wJvcPZJiYg&sa=D&source=editors&ust=1730081596391506&usg=AOvVaw0ZDiUoSkOqfDE7iESJSMCe"],"23":[88346,"Verlust","https://www.google.com/url?q=https://www.youtube.com/watch?v%3DXU4IjaoKc9w&sa=D&source=editors&ust=1730081596392135&usg=AOvVaw2MwLGAAaTtu_vl5rjDH9oI"],"24":[89879,"Lufti","https://www.google.com/url?q=https://youtu.be/GCh0hqauo6M&sa=D&source=editors&ust=1730081596392756&usg=AOvVaw09wmMf6pFZ7NkhDmwnqMQa"],"25":[84449,"Elmer","https://www.google.com/url?q=https://youtu.be/bhnBJ4GGYhc&sa=D&source=editors&ust=1730081596425822&usg=AOvVaw35ZBGtd8Oh3whTRNqm2Sg7"],"26":[78252,"Army","https://www.google.com/url?q=https://youtu.be/JHIkCZj_8Sc?si%3D0Q57FBR-mP7hdzHU&sa=D&source=editors&ust=1730081596426407&usg=AOvVaw2Wi1uJQkeZCtPy0x4EYIQ4"],"27":[85875,"Elmer","https://www.google.com/url?q=https://www.youtube.com/watch?v%3Dmw8cM0ndRmE&sa=D&source=editors&ust=1730081596426986&usg=AOvVaw3jkvB7mwYkm5Q6u4dEj8kL"],"28":[88389,"Technical","https://www.google.com/url?q=https://www.youtube.com/watch?v%3DIjb0Iu2-XZc&sa=D&source=editors&ust=1730081596427581&usg=AOvVaw2AxrgIewdyyHEfDf5tcMDM"],"29":[75571,"alpha","https://www.google.com/url?q=https://youtu.be/cSsBd5Et7gM&sa=D&source=editors&ust=1730081596466792&usg=AOvVaw1ZYHOK_QkEdHg4bEWzg0IS"],"30":[91566,"konni","https://www.google.com/url?q=https://www.youtube.com/watch?v%3DAY-F1pDhaQc%26ab_channel%3Dkonni&sa=D&source=editors&ust=1730081596467500&usg=AOvVaw3tIRZgDNRtz19uvSCBjCwk"],"31":[85964,"Verlust","https://www.google.com/url?q=https://www.youtube.com/watch?v%3DIvjgQHnbnNc&sa=D&source=editors&ust=1730081596468214&usg=AOvVaw0cDM-EA_QMxXTomQQOCaqG"],"32":[0,"Alberto","https://www.google.com/url?q=https://www.youtube.com/watch?v%3Dago0_DOWSv4&sa=D&source=editors&ust=1730081596468872&usg=AOvVaw2LkNeiWHHLigWj69fEKxG2"],"33":[79099,"Alberto","https://www.google.com/url?q=https://www.youtube.com/watch?v%3DQUYBKesTS6A&sa=D&source=editors&ust=1730081596513144&usg=AOvVaw3hvaRYDLYDw_WKYIhTBka3"],"34":[78803,"Prilin","https://www.google.com/url?q=https://youtu.be/0KL7i304frI&sa=D&source=editors&ust=1730081596513779&usg=AOvVaw12ND_2AtaeLr9Q_RLZAp86"],"35":[80475,"Alberto","https://www.google.com/url?q=https://www.youtube.com/watch?v%3DrEqZhiLUn8I&sa=D&source=editors&ust=1730081596514396&usg=AOvVaw1kJRhkHMH3g5tR5Lz65hhz"],"36":[84385,"Alberto","https://www.google.com/url?q=https://www.youtube.com/watch?v%3DJALQ-fubAgg&sa=D&source=editors&ust=1730081596514961&usg=AOvVaw040fHZsB_Nsvv2xtWtO91t"],"37":[87775,"Alberto","https://www.google.com/url?q=https://www.youtube.com/watch?v%3Ddjsq8eJeX3c&sa=D&source=editors&ust=1730081596547046&usg=AOvVaw0OhZDagNv2wUuuexvdyDFv"],"38":[63647,"alpha","https://www.google.com/url?q=https://youtu.be/Cklb0gRMpMs&sa=D&source=editors&ust=1730081596547720&usg=AOvVaw2dITf8NFJVhXaBE5Pv57GF"],"39":[79536,"Technical","https://www.google.com/url?q=https://www.youtube.com/watch?v%3DBAZ4onGZBHI&sa=D&source=editors&ust=1730081596548364&usg=AOvVaw2cDF1xL2SWTzsqenWutXtj"],"40":[84139,"Technical","https://www.google.com/url?q=https://www.youtube.com/watch?v%3DUcX0yi_zdik&sa=D&source=editors&ust=1730081596548992&usg=AOvVaw2kXwKTN480GEP-f7eJdxy2"],"41":[0,"Technical","https://www.google.com/url?q=https://www.youtube.com/watch?v%3D7xFb0XMwPFU&sa=D&source=editors&ust=1730081596588438&usg=AOvVaw2mjkvxTaMUmDsyw2T7mZk_"],"42":[82208,"Technical","https://www.google.com/url?q=https://www.youtube.com/watch?v%3DwzDkL7JMXmI&sa=D&source=editors&ust=1730081596589136&usg=AOvVaw3T1PTDBi6-MpBLY1I25Liu"],"43":[79265,"Technical","https://www.google.com/url?q=https://www.youtube.com/watch?v%3DB9-xZNhjWHM&sa=D&source=editors&ust=1730081596589815&usg=AOvVaw3kBbAXUu3oQsD31j0TVDaK"],"44":[74542,"Flour","https://www.google.com/url?q=https://youtu.be/gPiWbTpYFT0?si%3DWU4v1Unt_TTAvN8d&sa=D&source=editors&ust=1730081596590436&usg=AOvVaw1by4JoHnmBzzd2hwdTNpww"],"45":[82943,"Alberto","https://www.google.com/url?q=https://www.youtube.com/watch?v%3DEWAchm0O2yg&sa=D&source=editors&ust=1730081596626330&usg=AOvVaw0Mq1o9G_CTYa5iqY7GNXBq"],"46":[81331,"Technical","https://www.google.com/url?q=https://www.youtube.com/watch?v%3DxXWsZJIfy6Q&sa=D&source=editors&ust=1730081596626984&usg=AOvVaw1LcYzFDXkf5ogeR21OyKgd"],"47":[75946,"Alberto","https://www.google.com/url?q=https://youtu.be/HelApJ2fad8&sa=D&source=editors&ust=1730081596627712&usg=AOvVaw1f1FYjg3WPnsyHULe9E2Ph"],"48":[63383,"Technical","https://www.google.com/url?q=https://youtu.be/PWG60Mysg2g&sa=D&source=editors&ust=1730081596628394&usg=AOvVaw1apPQmFjzIQc-IGU15akX4"],"49":[78988,"Technical","https://www.google.com/url?q=https://youtu.be/mb633avPz90&sa=D&source=editors&ust=1730081596667443&usg=AOvVaw1xkC3kK_VYB6qC8a8jUM1r"],"50":[59691,"Technical","https://www.google.com/url?q=https://youtu.be/rl22EgWS1SU&sa=D&source=editors&ust=1730081596668167&usg=AOvVaw30W3KbC0Cx6EPDCM3bsobJ"],"51":[82304,"Mr. Cloud Kirby","https://www.google.com/url?q=https://youtu.be/pJaP5K5g7rc?si%3DLueT6DbXvj6INpWD&sa=D&source=editors&ust=1730081596668849&usg=AOvVaw2IHG7fXmxXsfIPFpcybcib"],"52":[77693,"Byron","https://www.google.com/url?q=https://www.youtube.com/watch?v%3DC6qEcrYwpYk&sa=D&source=editors&ust=1730081596669522&usg=AOvVaw3nWkRaJK5cik6AqKexOtY9"],"53":[60945,"Technical","https://www.google.com/url?q=https://youtu.be/1jidjsRfWzw&sa=D&source=editors&ust=1730081596711636&usg=AOvVaw3FuiZyBSLKrdnaKXuCFt_q"],"54":[80022,"Army","https://www.google.com/url?q=https://youtu.be/rGK9watUphg&sa=D&source=editors&ust=1730081596712249&usg=AOvVaw05MJDYBP1QysYyYawe4E03"],"55":[65734,"Alberto","https://www.google.com/url?q=https://www.youtube.com/watch?v%3DK2CGiVw0if0&sa=D&source=editors&ust=1730081596712867&usg=AOvVaw3v-SKOjC1RktigppGnVftd"],"56":[87451,"olli","https://www.google.com/url?q=https://www.youtube.com/watch?v%3DsUS73zXOCL4&sa=D&source=editors&ust=1730081596713519&usg=AOvVaw0smHvDbxuom9BpBge_hZmn"],"57":[61523,"Technical","https://www.google.com/url?q=https://www.youtube.com/watch?v%3D79jjslKqm78&sa=D&source=editors&ust=1730081596756264&usg=AOvVaw3_cIvUHV-IkcaTfCH95Hjy"],"58":[69141,"Army","https://www.google.com/url?q=https://www.youtube.com/watch?v%3DwSiUCALGoTo&sa=D&source=editors&ust=1730081596756898&usg=AOvVaw0wjNWHP1iGSiF4Qy-UfoAx"],"59":[66163,"zill","https://www.google.com/url?q=https://www.youtube.com/watch?v%3Dmk5VCBu13A8&sa=D&source=editors&ust=1730081596757574&usg=AOvVaw34PdHKOArX-IhEloJsRK9s"],"60":[108441,"Technical","https://www.google.com/url?q=https://www.youtube.com/watch?v%3DM23YvBOztVo&sa=D&source=editors&ust=1730081596758249&usg=AOvVaw2ahXBL0foXT4zmx91CSdw5"],"61":[87901,"Vincent","https://www.google.com/url?q=https://www.youtube.com/watch?v%3DS9Dhwh1lcHs&sa=D&source=editors&ust=1730081596801144&usg=AOvVaw0TS8MfvrnQDhBTHjQNtMM2"],"62":[71918,"Alberto","https://www.google.com/url?q=https://www.youtube.com/watch?v%3DEAyNdnuUQZo&sa=D&source=editors&ust=1730081596801765&usg=AOvVaw22XqElzg3MAQq6y2Lr4H_G"],"63":[69223,"mosya","https://www.google.com/url?q=https://twitter.com/ms_8dan/status/1629901521453477889?t%3DFTDmACT8s-TWRUb7FJ7V1Q%26s%3D33&sa=D&source=editors&ust=1730081596802373&usg=AOvVaw3-7k3ZKmF01vQ7mpq-Dqmd"],"64":[82835,"Pianist15","https://www.google.com/url?q=https://www.youtube.com/watch?v%3DGS2Lm1ra55c&sa=D&source=editors&ust=1730081596803046&usg=AOvVaw0BUNcdFtY18Vpf9pnTplZ7"],"65":[93136,"Army","https://www.google.com/url?q=https://www.youtube.com/watch?v%3DvgsxVwHK6wY&sa=D&source=editors&ust=1730081596844692&usg=AOvVaw0JPN9JmD-BB0-4QmAqW0R5"],"66":[61988,"Army","https://www.google.com/url?q=https://www.youtube.com/watch?v%3DNX-9ZlTAfkI&sa=D&source=editors&ust=1730081596845472&usg=AOvVaw1R5W-VQONbPTdUqllqPc0x"],"67":[94932,"Technical","https://www.google.com/url?q=https://www.youtube.com/watch?v%3DBl2QKUakucc&sa=D&source=editors&ust=1730081596846213&usg=AOvVaw0Us13GKc730xSzCn1iy1Sz"],"68":[112632,"ちゃんりー","https://www.google.com/url?q=https://x.com/tdayo464969127/status/1790005169469407589?s%3D46&sa=D&source=editors&ust=1730081596847009&usg=AOvVaw202WVkKnNtosz_dxSOVCvH"],"69":[85634,"Alpaco","https://www.google.com/url?q=https://www.youtube.com/watch?v%3DbB6WHCtaEbw&sa=D&source=editors&ust=1730081596902212&usg=AOvVaw08czaAvctKJGOKv36Ds7yR"],"70":[89867,"Technical","https://www.google.com/url?q=https://youtu.be/Aqp0WsEftQg&sa=D&source=editors&ust=1730081596902980&usg=AOvVaw1a3z6NtbsNIZERakB83pPP"],"71":[84095,"Flour","https://www.google.com/url?q=https://youtu.be/WKQuWE9elyM?si%3DOK-GMVBcaTyB5npQ&sa=D&source=editors&ust=1730081596903730&usg=AOvVaw2aPWyc4RwZTRVQHZR-IKHz"],"72":[71832,"Elmer","https://www.google.com/url?q=https://www.youtube.com/watch?v%3DmONR8fosczg&sa=D&source=editors&ust=1730081596904452&usg=AOvVaw0WjX7MhsuvxGFYAQv_Wpfd"],"73":[70782,"flour","https://www.google.com/url?q=https://youtu.be/40nPX6bIQ10?feature%3Dshared&sa=D&source=editors&ust=1730081596961353&usg=AOvVaw3OekynpGMmBEvPdoTOb1r5"],"74":[67552,"yellow","https://www.google.com/url?q=https://photos.app.goo.gl/GiJTaRwdMZNFbqid8&sa=D&source=editors&ust=1730081596962106&usg=AOvVaw2IHPoryUnPiWNE2TyBBeu_"],"75":[96112,"MSG8819","https://www.google.com/url?q=https://youtu.be/5t-lu68qcvU?si%3DG548LkhUD6DFARz3&sa=D&source=editors&ust=1730081596962827&usg=AOvVaw2vck83G-hPlwx8Vivd_eWO"],"76":[89968,"Technical","https://www.google.com/url?q=https://www.youtube.com/watch?v%3DU2OEePZGuK0&sa=D&source=editors&ust=1730081596963613&usg=AOvVaw32Pi-Rhpo7ubsvpCMC_7Rt"],"77":[75049,"SKaR","https://www.google.com/url?q=https://www.youtube.com/watch?v%3DEdsO8b4fxXU&sa=D&source=editors&ust=1730081597010065&usg=AOvVaw2hpV4bMTolzygykYpDiVO-"],"78":[74579,"SKaR","https://www.google.com/url?q=https://www.youtube.com/watch?v%3DPBeKyhSYQJM&sa=D&source=editors&ust=1730081597010778&usg=AOvVaw25U5aUjHTKFJD2nx2Y0qlu"],"79":[91587,"Technical","https://www.google.com/url?q=https://youtu.be/dHQepUOZx5I&sa=D&source=editors&ust=1730081597011747&usg=AOvVaw31iXRt6csUctVFsJNVN2FH"],"80":[84026,"Technical","https://www.google.com/url?q=https://youtu.be/KaauixuD1qo&sa=D&source=editors&ust=1730081597012542&usg=AOvVaw2tyKreIOCtLRjY8PK3iDWF"],"81":[73511,"Technical","https://www.google.com/url?q=https://youtu.be/CFcvUky3p_s&sa=D&source=editors&ust=1730081597064338&usg=AOvVaw0AOu7xq_j5av2xCBgVnehs"],"82":[70663,"Technical","https://www.google.com/url?q=https://youtu.be/aAvL3qGUurA&sa=D&source=editors&ust=1730081597065186&usg=AOvVaw38SPf3qtVOU1pz8iYfnKfE"],"83":[75088,"zill","https://www.google.com/url?q=https://www.youtube.com/watch?v%3DRHkO3bUYjlI&sa=D&source=editors&ust=1730081597065923&usg=AOvVaw1GbIYGA2gBWAz0usqFa6qm"],"84":[88292,"Alberto","https://www.google.com/url?q=https://youtu.be/zeULHUTWtpw&sa=D&source=editors&ust=1730081597066609&usg=AOvVaw2aQptjcsBU0-Z4LSF61lmo"],"85":[78300,"Flour","https://www.google.com/url?q=https://youtu.be/Za3qhyLG9uQ?si%3D8i_-9piVYnYNnBjb&sa=D&source=editors&ust=1730081597113509&usg=AOvVaw1uax9ujqODUEnOS2REKcWM"],"86":[71976,"Kouta.","https://www.google.com/url?q=https://youtu.be/6i8DjHYIZGI&sa=D&source=editors&ust=1730081597114249&usg=AOvVaw3XByezBTZG-0olf3lojVHv"],"87":[88305,"Technical","https://www.google.com/url?q=https://youtu.be/EWqSPkIVWI0&sa=D&source=editors&ust=1730081597114959&usg=AOvVaw03HrShBWsBWfJIfda1ikrN"],"88":[87809,"zill","https://www.google.com/url?q=https://www.youtube.com/watch?v%3DqDLC5I8JAyQ&sa=D&source=editors&ust=1730081597115756&usg=AOvVaw0GQk7IFbUuho6m7TWbOQxG"],"89":[77681,"Naoto","https://www.google.com/url?q=https://youtu.be/srtK1hqoMiQ?si%3DltoL4sPuucSXziej&sa=D&source=editors&ust=1730081597150812&usg=AOvVaw3ffowEl0f652ZmnxHc0oGD"],"90":[108986,"Elmer","https://www.google.com/url?q=https://www.youtube.com/watch?v%3DdVsunL-FtUY%26ab_channel%3DElmer&sa=D&source=editors&ust=1730081597151692&usg=AOvVaw1TXb30s_ngTUYQHi5Y8srf"],"91":[79730,"Pianist15","https://www.google.com/url?q=https://youtu.be/9_eFGJXAsSQ?si%3Dej43TUingbdFJq0s%26t%3D229&sa=D&source=editors&ust=1730081597152623&usg=AOvVaw0z72jUrAITApcWKIqg9Ka-"],"92":[88713,"konni","https://www.google.com/url?q=https://youtu.be/nNkk0YpYi-0&sa=D&source=editors&ust=1730081597153436&usg=AOvVaw3A-yDSl4k3WVT1OPEEBUuV"],"93":[85808,"Flour","https://www.google.com/url?q=https://youtu.be/5z3azwF1grI?si%3DH0g4nFfIdmg6QF2W&sa=D&source=editors&ust=1730081597191799&usg=AOvVaw1QO8TZJP4r8IBMlXJljZs5"],"94":[89693,"Wood22","https://www.google.com/url?q=https://youtu.be/RiPPMRUN4f0?si%3DzqY6TD44QapX5Xte&sa=D&source=editors&ust=1730081597192602&usg=AOvVaw2hqyT5WQ9gCrggmNnvtEfX"],"95":[76620,"konni","https://www.google.com/url?q=https://youtu.be/uQRudglSdvo&sa=D&source=editors&ust=1730081597193416&usg=AOvVaw3IQxvQB9BSTrnSJNdFMGjz"],"96":[115349,"B Yoru","https://www.google.com/url?q=https://www.youtube.com/watch?v%3DBam3i5tCJ7U&sa=D&source=editors&ust=1730081597194301&usg=AOvVaw26uDPEca_bzQSUXl3RkWcu"]},"ta150":{"1":[94277,"しらぬい","https://www.youtube.com/watch?v=f178X-eHEto"],"2":[98995,"Vincent","https://www.youtube.com/watch?v=02TkOgMD-Qg"],"3":[108030,"Vincent","https://www.youtube.com/watch?v=EoehsIVq3-Q"],"4":[107080,"Panda","https://www.youtube.com/watch?v=WB59kvCa68w"],"5":[103723,"Vincent","https://www.youtube.com/watch?v=e-SOkLrSgpg"],"6":[121586,"なすの","https://www.youtube.com/watch?v=2CnwKPnLlTc"],"7":[113354,"Alberto","https://youtu.be/3ndwXMfV50s"],"8":[115279,"Yerson","https://www.youtube.com/watch?v=yssM9sKoevM"],"9":[116971,"Vincent","https://www.youtube.com/watch?v=hc3WYtlCbVg"],"10":[111951,"StervtL","https://www.youtube.com/watch?v=0KsT5AnwXAc"],"11":[115086,"Alberto","https://www.youtube.com/watch?v=jAEcZZ3Lj6M"],"12":[100545,"F。","https://www.youtube.com/watch?v=3ZnHO8Q0464"],"13":[119262,"F。","https://www.youtube.com/watch?v=r0k4n3oX19Y"],"14":[106413,"Army","https://www.youtube.com/watch?v=RDjIYAVE3NA"],"15":[117655,"Vincent","https://youtu.be/tibmjUAnRVg"],"16":[118454,"Alberto","https://youtu.be/HNT0st5ePqo"],"17":[83642,"Panda","https://www.youtube.com/watch?v=2R46yX3twqs"],"18":[58517,"Albert","https://www.youtube.com/watch?v=KVgc9D5R5EU"],"19":[59892,"StervtL","https://www.youtube.com/watch?v=uaEmg6ATdEo"],"20":[75569,"Alberto","https://youtu.be/lPMQF1NjN7Y?si=0ScZmSM6c5OG5O24"],"21":[71977,"Alphabet Soup","https://youtu.be/DA9BP3X391g"],"22":[76879,"Panda","https://youtu.be/JK10RFNKDeo"],"23":[55241,"JenZua","https://www.youtube.com/watch?v=wOngIj1x_Rw"],"24":[83413,"Technical","https://www.youtube.com/watch?v=E3bYUdaTGh4"],"25":[87316,"Panda","https://www.youtube.com/watch?v=RBukMzcLvLU"],"26":[81128,"Pii","https://www.youtube.com/watch?v=CSYslhqZgVA"],"27":[76130,"Alberto","https://www.youtube.com/watch?v=E4Qegv_QCCI"],"28":[83309,"Alberto","https://www.youtube.com/watch?v=wD0SK8CZnwc"],"29":[83992,"Alberto","https://www.youtube.com/watch?v=lGoatvaM7Jo"],"30":[72991,"Alberto",null],"31":[86082,"Pii","https://www.youtube.com/watch?v=xd5rI8wg0d4"],"32":[81673,"Hgt","https://www.youtube.com/watch?v=8XfhPNlIFsg"],"33":[56335,"kwartz","https://www.youtube.com/watch?v=T7RP6M-cGMU"],"34":[73025,"Army","https://www.youtube.com/watch?v=yYV9BnvqIqE"],"35":[73889,"しらぬい","https://www.youtube.com/watch?v=hsYvYs4PQmA"],"36":[100081,"Alberto","https://www.youtube.com/watch?v=l07fps_68nA"],"37":[110788,"StervtL","https://www.youtube.com/watch?v=5XNqlk0Fp-I"],"38":[121373,"Vincent","https://www.youtube.com/watch?v=9-n6nxPRrgk"],"39":[85569,"Vincent","https://www.youtube.com/watch?v=Fdw_09Kn-VE"],"40":[104738,"Alberto","https://www.youtube.com/watch?v=inc-eNkSo_U"],"41":[76926,"grace","https://www.youtube.com/watch?v=rg-R4BXxG8k"],"42":[79631,"JenZua",null],"43":[44731,"alpha","https://www.youtube.com/watch?v=7LSoZfVAKfk"],"44":[74917,"alpha","https://www.youtube.com/watch?v=JduphBt80w4"],"45":[76609,"Alberto","https://www.youtube.com/watch?v=5CjiHfzGhOY"],"46":[70407,"4laps2win","https://www.youtube.com/watch?v=vq3Lb62fRvg"],"47":[78871,"Alberto","https://youtu.be/f9V8qU5wJ9Q"],"48":[76949,"Army","https://www.youtube.com/watch?v=2l1KZIgyDAA"],"49":[72788,"Alberto",null],"50":[60361,"FA","https://www.youtube.com/watch?v=lNQsHaQDQeo"],"51":[76395,"Army","https://www.youtube.com/watch?v=GitYX9Ulem4"],"52":[56489,"Army","https://www.youtube.com/watch?v=2HGIfNhOeZI"],"53":[79651,"Vincent","https://www.youtube.com/watch?v=g0F5_VnykZw"],"54":[73865,"Army","https://www.youtube.com/watch?v=oYfJB0uDxXA"],"55":[58852,"Alberto","https://youtu.be/cTwX9-lIH6o"],"56":[75426,"Alberto","https://www.youtube.com/watch?v=QxgAJpeusGI"],"57":[61722,"Technical","https://youtu.be/DAi7K8LO8n0"],"58":[84193,"Panda","https://www.youtube.com/watch?v=5_mycIie7hA"],"59":[58262,"Army","https://www.youtube.com/watch?v=UGOl7374cHU"],"60":[64323,"JenZua","https://www.youtube.com/watch?v=wm4I5EoG7p4"],"61":[60995,"Panda",null],"62":[105773,"Technical","https://www.youtube.com/watch?v=qzkKfuwdH38"],"63":[84349,"Vincent","https://www.youtube.com/watch?v=69Ncs_NHgw0"],"64":[64209,"Alberto","https://www.youtube.com/watch?v=DfsfF8nbxLI"],"65":[61808,"4laps2win","https://www.youtube.com/watch?v=yXug6Wcc1W4"],"66":[79467,"Draygo","https://www.youtube.com/watch?v=R_2fYIrJ69g"],"67":[88528,"Army","https://www.youtube.com/watch?v=uUdDTH83dp4"],"68":[59359,"Pii","https://www.youtube.com/watch?v=sZuRmtDp3aQ"],"69":[87316,"grace","https://youtu.be/ghbJbUwcEwk"],"70":[108764,"Vincent","https://www.youtube.com/watch?v=7rrppUxcGVM"],"71":[81802,"Army","https://www.youtube.com/watch?v=AMbN23iCuok"],"72":[86018,"Army","https://www.youtube.com/watch?v=gbqlxONCMjM"],"73":[78541,"bup","https://www.youtube.com/watch?v=DM1LCf4iHX8"],"74":[69446,"Technical","https://www.youtube.com/watch?v=eo4gQN_U6K0"],"75":[66568,"Technical","https://www.youtube.com/watch?v=YF8bS0Gigic"],"76":[62066,"Mirai","https://www.youtube.com/watch?v=bWcGyRY4_pw"],"77":[91428,"Technical","https://www.youtube.com/watch?v=OnH5H0aeI7c"],"78":[85990,"Technical","https://www.youtube.com/watch?v=rsmsi1pijg4"],"79":[72953,"Alberto","https://www.youtube.com/watch?v=xXcLaw4z_Is"],"80":[70765,"Pii","https://www.youtube.com/watch?v=1hcEIph-d-0"],"81":[85178,"JenZua","https://www.youtube.com/watch?v=SffAUF6WAzE"],"82":[80774,"Alberto","https://www.youtube.com/watch?v=IHKLpZhVkq8"],"83":[70762,"Technical","https://www.youtube.com/watch?v=O63voitA39U"],"84":[68546,"Army","https://www.youtube.com/watch?v=5IQYxrVfgcw"],"85":[71672,"Matt","https://www.youtube.com/watch?v=14esHk9Mj8Y"],"86":[85431,"Technical","https://www.youtube.com/watch?v=2sQ1XiUBW7U"],"87":[74102,"Alberto","https://www.youtube.com/watch?v=TkrPTeY5GxI"],"88":[67131,"Panda","https://www.youtube.com/watch?v=UlcXd3DHfyk"],"89":[116882,"Alberto","https://www.youtube.com/watch?v=XTkxY9vTaqE"],"90":[119093,"Panda","https://www.youtube.com/watch?v=DM6ywJR6574"],"91":[103326,"ささゆき","https://www.youtube.com/watch?v=ozt-Pa2KhFQ"],"92":[128958,"くぜろ","https://www.youtube.com/watch?v=gCY74FrFL8E"],"93":[107664,"Vincent","https://www.youtube.com/watch?v=a4d6JyMhxcc"],"94":[117947,"Panda","https://www.youtube.com/watch?v=3-bI8lkPNMk"],"95":[116142,"Alberto","https://www.youtube.com/watch?v=fuOuQ2zMCZc"],"96":[82371,"Alberto","https://www.youtube.com/watch?v=I-x8UgdJEH4"]},"ta200":{"1":[67271,"Army","https://www.youtube.com/watch?v=yQ3iuP2FK_Y"],"2":[70557,"Alberto","https://www.youtube.com/watch?v=A5o_JmPuJd4"],"3":[81254,"Technical","https://www.youtube.com/watch?v=lfxb0P9GzGs"],"4":[75654,"Alberto","https://www.youtube.com/watch?v=9ul4y1JVfFc"],"5":[72662,"ろーる","https://www.youtube.com/watch?v=ebxaJ3YwTB4"],"6":[86141,"Army","https://www.youtube.com/watch?v=_ejgi-L7dNU"],"7":[81982,"grace","https://www.youtube.com/watch?v=BZspqX9FLlw"],"8":[85763,"Army","https://www.youtube.com/watch?v=gnLB33dlO6c"],"9":[87987,"Alberto","https://www.youtube.com/watch?v=H18b3ICqBq0"],"10":[81899,"Alberto","https://www.youtube.com/watch?v=NljYyNfHCnk"],"11":[81669,"Alberto","https://www.youtube.com/watch?v=Y0ST_uT47ZA"],"12":[75133,"Alberto","https://youtu.be/FHM6m2XV9lE"],"13":[88808,"Alberto","https://youtu.be/Aue4_okSihY"],"14":[79265,"Panda","https://www.youtube.com/watch?v=MvCvJWFIuao"],"15":[85874,"Vincent","https://www.youtube.com/watch?v=TeIoLPDqybw"],"16":[91513,"Technical","https://www.youtube.com/watch?v=jhRuarOet60"],"17":[58517,"Army","https://www.youtube.com/watch?v=iZ1gkLY5gFs"],"18":[82953,"もぺち","https://www.youtube.com/watch?v=nRMGYjzX2pE"],"19":[106080,"Vincent","https://www.youtube.com/watch?v=sPcC6Syo2xg"],"20":[105563,"Vincent","https://www.youtube.com/watch?v=nwEpePGCDoI"],"21":[112431,"Army","https://www.youtube.com/watch?v=M8ddFvmWRZA"],"22":[72833,"Alpaco","https://youtu.be/CK9E7sR6MyE"],"23":[114778,"Panda","https://www.youtube.com/watch?v=_OUJ0odWlfc"],"24":[120477,"k","https://www.youtube.com/watch?v=vAJn8NJFnEE"],"25":[109988,"StervtL","https://www.youtube.com/watch?v=ThkwR41lQn0"],"26":[106298,"Alberto","https://www.youtube.com/watch?v=2NyImxWD2Jg"],"27":[110477,"Alberto","https://www.youtube.com/watch?v=X2PVFC-pTUo"],"28":[117482,"Vincent","https://www.youtube.com/watch?v=TCljaLkAT_o"],"29":[100997,"ありす","https://www.youtube.com/watch?v=OYRVbRIF7z8"],"30":[117960,"Pii","https://www.youtube.com/watch?v=QshLk8KJUkE"],"31":[112441,"Panda","https://youtu.be/gXOWJEBcTv4"],"32":[79196,"Vincent","https://www.youtube.com/watch?v=0S8s-zAZ7cM"],"33":[101253,"Army","https://youtu.be/szygfU_3FZI"],"34":[98467,"Army","https://www.youtube.com/watch?v=ahTFf2US1Gk"],"35":[73889,"ろーる","https://www.youtube.com/watch?v=bDFYqheit2k"],"36":[76211,"Army","https://www.youtube.com/watch?v=DZwUTCWdmJ0"],"37":[80588,"Pii","https://www.youtube.com/watch?v=YlrDXJb1goo"],"38":[84881,"Alberto","https://www.youtube.com/watch?v=XQh1VytSd7Y"],"39":[61981,"alpha","https://www.youtube.com/watch?v=GbyytniAzxc"],"40":[76926,"Alberto","https://www.youtube.com/watch?v=WqyZso1MoGk"],"41":[106905,"エル","https://youtu.be/vm1y3MLKWKg"],"42":[61836,"JenZua","https://youtu.be/6eAsFElRIww"],"43":[101432,"Army","https://www.youtube.com/watch?v=yeiaXQGKjKg"],"44":[105286,"Alberto","https://www.youtube.com/watch?v=TFgBm9oBEps"],"45":[95976,"Army","https://www.youtube.com/watch?v=SItTncntHfs"],"46":[102158,"Alberto","https://www.youtube.com/watch?v=FlSM-lU90fE"],"47":[103489,"Army","https://www.youtube.com/watch?v=K5ztD9tN5do"],"48":[99680,"Army","https://www.youtube.com/watch?v=a2UN8qyxnnE"],"49":[83189,"SorNano","https://www.youtube.com/watch?v=QDDubUQnEmc"],"50":[109376,"Army","https://youtu.be/ZtTb2Fu2M0A"],"51":[79900,"Army","https://www.youtube.com/watch?v=D17_4QRLIW4"],"52":[111619,"Vincent",null],"53":[100464,"Alberto","https://www.youtube.com/watch?v=mrBvbPjaOJM"],"54":[85014,"Vincent","https://www.youtube.com/watch?v=TDycDWSEQUw"],"55":[104094,"Vincent","https://www.youtube.com/watch?v=-hV9bi9AyhA"],"56":[85897,"Alberto","https://www.youtube.com/watch?v=nJPxQn8xH7M"],"57":[111764,"ヒビキ","https://www.youtube.com/watch?v=yShSL3hXlGI"],"58":[82481,"Panda","https://www.youtube.com/watch?v=AQ1cCF2Na48"],"59":[90525,"Vincent","https://www.youtube.com/watch?v=YBl29dKpvzc"],"60":[87642,"Army","https://www.youtube.com/watch?v=4C9eoybAJ2U"],"61":[138596,"F。","https://www.youtube.com/watch?v=6MpTi-ccdZg"],"62":[119382,"Alberto","https://www.youtube.com/watch?v=OgTqCBR5hds"],"63":[85971,"Army","https://www.youtube.com/watch?v=QV14OtCKpQs"],"64":[86945,"fairy","https://www.youtube.com/watch?v=hGX9UBnajd4"],"65":[113631,"stove","https://www.youtube.com/watch?v=VlX3zrTbAe8"],"66":[126799,"¥146","https://www.youtube.com/watch?v=80F4-lQbimo"],"67":[80255,"Army",null],"68":[126997,"Panda",null],"69":[142604,"aybzq","https://www.youtube.com/watch?v=0SZ3ibJ-yNI"],"70":[115207,"Vincent","https://www.youtube.com/watch?v=ehcpVhYo2z0"],"71":[122853,"Panda","https://www.youtube.com/watch?v=iEGfIk16daE"],"72":[109453,"Vincent","https://www.youtube.com/watch?v=Yez3Y_evdc8"],"73":[96718,"Alberto","https://www.youtube.com/watch?v=CbNGPC9ZOA4"],"74":[94766,"Panda","https://www.youtube.com/watch?v=_-wSdyRnv6A"],"75":[85011,"Vincent",null],"76":[115472,"StervtL","https://www.youtube.com/watch?v=tI3cbIM751I"],"77":[117052,"YOS","https://www.youtube.com/watch?v=qrhY5WOMyLQ"],"78":[101889,"ささゆき","https://www.youtube.com/watch?v=IfXdK_GsZGM"],"79":[96957,"Pii","https://www.youtube.com/watch?v=oeR2rXeIoXs"],"80":[113193,"F。","https://www.youtube.com/watch?v=hZLsyzuHzLA"],"81":[115682,"Vincent","https://www.youtube.com/watch?v=eAH5yRLCf0A"],"82":[97508,"Panda","https://www.youtube.com/watch?v=nXOLHE3KXxc"],"83":[93951,"Army","https://www.youtube.com/watch?v=ujVoiS_NYEQ"],"84":[101918,"Jamie","https://www.youtube.com/watch?v=Sdbx8Go4Moc"],"85":[119749,"AK","https://youtu.be/21Y_6UDjIyY?feature=shared"],"86":[105460,"ささゆき","https://www.youtube.com/watch?v=NGafpCcKgRQ"],"87":[92261,"¥146","https://www.youtube.com/watch?v=p2UXpeH6dns"],"88":[67131,"Pii","https://www.youtube.com/watch?v=RDJ3utAS2jw"],"89":[85655,"JenZua","https://www.youtube.com/watch?v=ehx9Qe6jHZ4"],"90":[83897,"Vincent","https://www.youtube.com/watch?v=NzD7Lo6Ijik"],"91":[73929,"Alberto","https://www.youtube.com/watch?v=L7zEvupkSnM"],"92":[104532,"Zae","https://www.youtube.com/watch?v=NhtvBImFYSc"],"93":[76118,"Army","https://www.youtube.com/watch?v=Ldu2Byu7nGA"],"94":[83776,"Bruh",null],"95":[82371,"Army","https://www.youtube.com/watch?v=I-x8UgdJEH4"],"96":[115976,"Alberto","https://www.youtube.com/watch?v=U_qgqgVAArM"]}}}